Workbook
Name lst_ActiveStatus: LOOKUP!$T$4:$T$5
Name lst_AdmissionStatus: LOOKUP!$J$4:$J$8
Name lst_BedStatus: LOOKUP!$U$4:$U$7
Name lst_BloodGroup: LOOKUP!$B$4:$B$11
Name lst_ClaimStatus: LOOKUP!$L$4:$L$9
Name lst_Department: LOOKUP!$E$4:$E$12
Name lst_Designation: LOOKUP!$F$4:$F$8
Name lst_DiscountType: LOOKUP!$O$4:$O$8
Name lst_DoctorNames: LOOKUP!$V$4:$W$13
Name lst_DoctorStatus: LOOKUP!$R$4:$R$7
Name lst_Gender: LOOKUP!$A$4:$A$6
Name lst_GSTPercent: LOOKUP!$Q$4:$Q$7
Name lst_IDProof: LOOKUP!$C$4:$C$8
Name lst_InsCoverage: LOOKUP!$S$4:$S$6
Name lst_InsuranceProvider: LOOKUP!$P$4:$P$14
Name lst_PayerType: LOOKUP!$D$4:$D$6
Name lst_PaymentMode: LOOKUP!$K$4:$K$10
Name lst_PaymentStatus: LOOKUP!$M$4:$M$8
Name lst_ServiceCategory: LOOKUP!$G$4:$G$11
Name lst_StaffRole: LOOKUP!$N$4:$N$10
Name lst_VisitType: LOOKUP!$I$4:$I$6
Name lst_WardType: LOOKUP!$H$4:$H$8
Name Slicer_Department: #N/A
Name Slicer_Discount_Type: #N/A
Name Slicer_Payment_Status: #N/A
Name Slicer_Status: #N/A
Name Slicer_Visit_Type: #N/A

Sheet INSTRUCTIONS
B2: CityMed Multi-Specialty Hospital
B3: Patient & Billing Management System | Est. 2024 | Version 1.0
B5: NAVIGATE TO MODULE
B6: PT_Master — Patient Register | C6: Register new patients, search existing records, update contact and insurance details | E6: Receptionist
B7: DR_Master — Doctor Directory | C7: Manage doctor profiles, consultation fees, department assignments | E7: Admin
B8: SVC_RateCard — Services & Pricing | C8: Add or update services, procedures, lab tests and their rates | E8: Admin
B9: BED_Master — Bed Management | C9: Track bed availability, ward types, occupancy status | E9: Admin / Nurse
B10: ADM_Log — Admissions & OPD | C10: ADM_Log — Admissions & OPD | E10: Receptionist
B11: SVC_Log — Services Consumed | C11: Log all services, tests, procedures given to admitted patients | E11: Nurse / Lab
B12: BILLING — Invoice Generation | C12: Generate patient bills, apply insurance split, issue final invoices | E12: Billing Clerk
B13: DASHBOARD — KPI & Reports | C13: View live hospital performance metrics, revenue, occupancy, collections | E13: Manager
B15: IMPORTANT INFORMATION
B16: Last Updated: | C16: =TODAY() -> 46169
B17: Version | C17: 1.0 — CityMed HMS (Excel 2021)
B18: Support Contact:
B19: Data Backup:

Sheet DASHBOARD
B2: CityMed Multi-Specialty Hospital — Operations Dashboard
B3: =("Dashboard refreshed: "&TEXT(TODAY(),"DD MMM YYYY")&" | Data is live and auto-updating") -> Dashboard refreshed: 27 May 2026 | Data is live and auto-updating
B4: PATIENT VOLUME
B5: Metric | C5: Value | D5: Metric | E5: Value | F5: Metric | G5: Value
B6: Total Patients | C6: =COUNTA(PT_Master!A5:A5000) -> 200 | D6: OPD Visits | E6: =COUNTIF(ADM_Log!D5:D5000,"OPD") -> 84 | F6: IPD Admissions | G6: =COUNTIF(ADM_Log!D5:D5000,"IPD") -> 55
B7: Active IPD Patients | C7: =COUNTIFS(ADM_Log!D5:D1004,"IPD",ADM_Log!O5:O1004,"Active") -> 6 | D7: Discharged This Month | E7: {=SUMPRODUCT( (ADM_Log!O5:O1004="Discharged")* (MONTH(IFERROR(DATEVALUE(ADM_Log!F5:F1004),0))=MONTH(TODAY()))* (YEAR(IFERROR(DATEVALUE(ADM_Log!F5:F1004),0))=YEAR(TODAY())) )} -> 5 | F7: Emergency Cases | G7: =COUNTIF(ADM_Log!D5:D5000,"Emergency") -> 11
B8: Avg Length of Stay | C8: =IFERROR(AVERAGEIF(ADM_Log!G5:G5000,">"&0,ADM_Log!G5:G5000),0) -> 5.7878788 | D8: New Patients This Month | E8: {=SUMPRODUCT((MONTH(IFERROR(DATEVALUE(PT_Master!B5:B204),0))=MONTH(TODAY()))*(YEAR(IFERROR(DATEVALUE(PT_Master!B5:B204),0))=YEAR(TODAY()))*(PT_Master!B5:B204<>""))} -> 5 | F8: LAMA Cases | G8: =COUNTIF(ADM_Log!O5:O5000,"LAMA") -> 7
B10: REVENUE SUMMARY
B11: Metric | C11: Amount (₹) | D11: Metric | E11: Amount (₹) | F11: Metric | G11: Amount (₹)
B12: Gross Revenue (₹) | C12: =IFERROR(SUM(BILLING!J5:J5000),0) -> 13492580 | D12: Net Revenue (₹) | E12: =IFERROR(SUM(BILLING!M5:M5000),0) -> 13101277 | F12: Total Discounts (₹) | G12: =IFERROR(SUM(BILLING!L5:L5000),0) -> 391302.76
B13: Rev Per Bed Per Day (₹) | C13: =IFERROR(SUM(BILLING!J5:J1004)/SUMIF(ADM_Log!D5:D1004,"IPD",ADM_Log!G5:G1004),0) -> 37067.527 | D13: Avg Bill Value (₹) | E13: =IFERROR(AVERAGE(BILLING!M5:M5000),0) -> 87341.848 | F13: Highest Single Bill (₹) | G13: =IFERROR(MAX(BILLING!J5:J5000),0) -> 472828.5
B14: Services Revenue (₹) | C14: =IFERROR(SUM(BILLING!G5:G5000),0) -> 12222750 | D14: Room Revenue (₹) | E14: =IFERROR(SUM(BILLING!H5:H5000),0) -> 1075500 | F14: Doctor Fee Revenue (₹) | G14: =IFERROR(SUM(BILLING!I5:I5000),0) -> 194330
B16: COLLECTIONS & ACCOUNTS RECEIVABLE
B17: Metric | C17: Amount (₹) | D17: Metric | E17: Amount (₹) | F17: Metric | G17: Amount (₹)
B18: Total Collected (₹) | C18: =IFERROR(PAYMENTS!E4,0) -> 5434705.8 | D18: Total Outstanding (₹) | E18: =IFERROR(PAYMENTS!G4,0) -> 2356305.2 | F18: Collection Rate | G18: =IFERROR(PAYMENTS!I4,"0.0%") -> 69.8%
B19: AR 0-30 Days (₹) | C19: =IFERROR(SUMIF(PAYMENTS!L6:L2005,"0-30 Days",PAYMENTS!J6:J2005),0) -> 162472.68 | D19: AR 31-60 Days (₹) | E19: =IFERROR(SUMIF(PAYMENTS!L6:L2005,"31-60 Days",PAYMENTS!J6:J2005),0) -> 87853.88 | F19: AR 61-90 Days (₹) | G19: =IFERROR(SUMIF(PAYMENTS!L6:L2005,"61-90 Days",PAYMENTS!J6:J2005),0) -> 356654.16
B20: Critical AR 90+ (₹) | C20: =IFERROR(PAYMENTS!K4,0) -> 1749114.5 | D20: Unpaid Bills Count | E20: =COUNTIF(BILLING!P5:P5000,"Unpaid") -> 18 | F20: Partial Payment Bills | G20: =COUNTIF(BILLING!P5:P5000,"Partial") -> 37
B22: BED OCCUPANCY
B23: Metric | C23: Value | D23: Metric | E23: Value | F23: Metric | G23: Value
B24: Total Beds | C24: =BED_Master!C3 -> 115 | D24: Occupied Beds | E24: =BED_Master!G3 -> 12 | F24: Occupancy Rate | G24: =IFERROR(BED_Master!G3/BED_Master!C3,0) -> 0.10434783
B25: Available Beds | C25: =BED_Master!E3 -> 15 | D25: Under Maintenance | E25: =COUNTIF(BED_Master!G5:G119,"Maintenance") -> 0 | F25: Reserved Beds | G25: =COUNTIF(BED_Master!G5:G119,"Reserved") -> 2
B26: ICU Beds Occupied | C26: =COUNTIFS(BED_Master!B5:B119,"ICU",BED_Master!G5:G119,"Occupied") -> 3 | D26: ICU Beds Available | E26: =COUNTIFS(BED_Master!B5:B119,"ICU",BED_Master!G5:G119,"Available") -> 1 | F26: ICU Occupancy Rate | G26: =IFERROR(C26/(C26+E26),0) -> 0.75
B28: INSURANCE PERFORMANCE
B29: Metric | C29: Amount (₹) | D29: Metric | E29: Amount (₹) | F29: Metric | G29: Amount (₹)
B30: Total Claims Submitted | C30: =COUNTA(INSURANCE!A6:A1005) -> 1000 | D30: Total Claimed (₹) | E30: =IFERROR(INSURANCE!C4,0) -> 4217770 | F30: Total Approved (₹) | G30: =IFERROR(INSURANCE!E4,0) -> 1826643.1
B31: Claims Approval Rate | C31: =IFERROR(INSURANCE!I4,"0.0%") -> 43.3% | D31: Rejected Claims | E31: =IFERROR(INSURANCE!K4,0) -> 15 | F31: Total Variance (₹) | G31: =IFERROR(INSURANCE!G4,0) -> 2391030
B32: Pending Claims | C32: =COUNTIF(INSURANCE!L6:L1005,"Pending") -> 0 | D32: Paid Claims | E32: =COUNTIF(INSURANCE!L6:L1005,"Approved") -> 19 | F32: Avg Approval Rate (₹) | G32: =IFERROR(INSURANCE!E4/COUNTIF(INSURANCE!L6:L1005,"Approved"),0) -> 96139.108
B33: CityMed HMS v1.0 | Confidential — For Management Use Only | Do not distribute

Sheet PIVOT_CHARTS
B1: CityMed Multi-Specialty Hospital — Analytics Dashboard
AW3: Count of Admission_ID | AX3: Column Labels
AW4: Row Labels | AX4: Emergency | AY4: IPD | AZ4: OPD | BA4: Grand Total
AW5: Cardiology | AY5: 6 | AZ5: 18 | BA5: 24
AW6: Diagnostics | AY6: 8 | AZ6: 4 | BA6: 12
AW7: Emergency | AY7: 3 | AZ7: 13 | BA7: 16
AW8: General Medicine | AX8: 2 | AY8: 5 | AZ8: 11 | BA8: 18
AW9: Gynaecology | AX9: 2 | AY9: 2 | AZ9: 9 | BA9: 13
AW10: Orthopaedics | AX10: 3 | AY10: 10 | AZ10: 20 | BA10: 33
AW11: Paediatrics | AY11: 4 | AZ11: 9 | BA11: 13
AW12: Grand Total | AX12: 7 | AY12: 38 | AZ12: 84 | BA12: 129
AW15: Row Labels | AX15: Count of Net_Payable (₹) | AY15: Sum of Insurance_Claim (₹)
AW16: Apr 2026 | AX16: 1 | AY16: 0
AW17: Aug 2025 | AX17: 3 | AY17: 8592.11
AW18: Dec 2025 | AX18: 3 | AY18: 74779.42
AW19: Feb 2026 | AX19: 7 | AY19: 184445.92
AW20: Jan 2026 | AX20: 1 | AY20: 0
AW21: Mar 2026 | AX21: 2 | AY21: 0
AW22: Sep 2025 | AX22: 1 | AY22: 0
AW23: Grand Total | AX23: 18 | AY23: 267817.45
AW36: Row Labels | AX36: Count of Net_Payable (₹) | AY36: Sum of Discount_Ammount (₹)
AW37: Insurance Pending | AX37: 4 | AY37: 22228.49
AW38: Paid | AX38: 11 | AY38: 50171.24
AW39: Partial | AX39: 7 | AY39: 60943.71
AW40: Unpaid | AX40: 1 | AY40: 9653.07
AW41: Grand Total | AX41: 23 | AY41: 142996.51
AX47: Row Labels | AY47: Count of Admission_ID | AZ47: Count of Length_of_Stay
AX48: Dr. Meena Pillai | AY48: 9 | AZ48: 9
AX49: Grand Total | AY49: 9 | AZ49: 9

Sheet PT_Master
A2: CityMed Multi-Specialty Hospital — Patient Master Register
A4: Patient_ID | B4: Reg_Date | C4: Full_Name | D4: Date_of_Birth | E4: Age | F4: Gender | G4: Blood_Group | H4: Phone | I4: Emergency_Name | J4: Emergency_Phone | K4: Address | L4: City | M4: ID_Proof_Type | N4: ID_Proof_No | O4: Payer_Type | P4: Insurance_Provider | Q4: Policy_No | R4: Member_ID | S4: Registerd_By
A5: =IF(C5="","",TEXT(ROW(A1),"PT-00000")) -> PT-00001 | B5: 24/03/2026 | C5: Ananya Roy | D5: 24/03/1985 | E5: =IF(D5="","",DATEDIF(D5,TODAY(),"Y")) -> 41 | F5: Female | G5: B- | H5: 9783058538 | I5: Bhavesh Dutta | J5: 9480289677 | K5: 107, VIP Road | L5: 107, VIP Road | M5: Driving Licence | N5: 348581372836 | O5: Insurance | P5: Care Health Insurance | Q5: POL858660 | R5: MEM63751 | S5: Receptionist
A6: =IF(C6="","",TEXT(ROW(A2),"PT-00000")) -> PT-00002 | B6: 31/12/2025 | C6: Rahul Sharma | D6: 21/06/2004 | E6: =IF(D6="","",DATEDIF(D6,TODAY(),"Y")) -> 21 | F6: Male | G6: B+ | H6: 9919062257 | I6: Tarun Patra | J6: 9455221955 | K6: 89, Camac Street | L6: 89, Camac Street | M6: Passport | N6: 665936330304 | O6: Self-Pay | S6: Ward Nurse
A7: =IF(C7="","",TEXT(ROW(A3),"PT-00000")) -> PT-00003 | B7: 02/01/2026 | C7: Priya Mehta | D7: 26/10/2004 | E7: =IF(D7="","",DATEDIF(D7,TODAY(),"Y")) -> 21 | F7: Male | G7: O- | H7: 9800862269 | I7: Rani Dubey | J7: 9347607381 | K7: 61, BT Road | L7: 61, BT Road | M7: PAN Card | N7: 357924695572 | O7: Corporate | S7: Billing Clerk
A8: =IF(C8="","",TEXT(ROW(A4),"PT-00000")) -> PT-00004 | B8: 04/07/2025 | C8: Debasis Mondal | D8: 19/04/1976 | E8: =IF(D8="","",DATEDIF(D8,TODAY(),"Y")) -> 50 | F8: Male | G8: A+ | H8: 9261768743 | I8: Gaurav Verma | J8: 9353065117 | K8: 90, Lake Avenue | L8: 90, Lake Avenue | M8: PAN Card | N8: 437947866314 | O8: Self-Pay | S8: Ward Nurse
A9: =IF(C9="","",TEXT(ROW(A5),"PT-00000")) -> PT-00005 | B9: 05/05/2026 | C9: Sneha Das | D9: 19/03/1972 | E9: =IF(D9="","",DATEDIF(D9,TODAY(),"Y")) -> 54 | F9: Female | G9: B- | H9: 9309852596 | I9: Tanvi Patra | J9: 9289105347 | K9: 132, Elgin Road | L9: 132, Elgin Road | M9: Passport | N9: 509861130823 | O9: Insurance | P9: Bajaj Allianz Health | Q9: POL652928 | R9: MEM23187 | S9: Receptionist
A10: =IF(C10="","",TEXT(ROW(A6),"PT-00000")) -> PT-00006 | B10: 29/09/2025 | C10: Amit Gupta | D10: 06/09/2015 | E10: =IF(D10="","",DATEDIF(D10,TODAY(),"Y")) -> 10 | F10: Male | G10: B+ | H10: 9193188214 | I10: Nisha Nair | J10: 9211988429 | K10: 153, VIP Road | L10: 153, VIP Road | M10: Driving Licence | N10: 91828501402 | O10: Self-Pay | S10: Receptionist
A11: =IF(C11="","",TEXT(ROW(A7),"PT-00000")) -> PT-00007 | B11: 16/04/2026 | C11: Kavita Singh | D11: 28/11/1961 | E11: =IF(D11="","",DATEDIF(D11,TODAY(),"Y")) -> 64 | F11: Male | G11: B- | H11: 9594968614 | I11: Deepak Ganguly | J11: 9436792410 | K11: 70, Ultadanga Main Road | L11: 70, Ultadanga Main Road | M11: Voter ID | N11: 369769232463 | O11: Insurance | P11: MediAssist TPA | Q11: POL869885 | R11: MEM37547 | S11: Billing Clerk
A12: =IF(C12="","",TEXT(ROW(A8),"PT-00000")) -> PT-00008 | B12: 08/06/2025 | C12: Suresh Chatterjee | D12: 22/08/1977 | E12: =IF(D12="","",DATEDIF(D12,TODAY(),"Y")) -> 48 | F12: Female | G12: A+ | H12: 9929816846 | I12: Smita Pandey | J12: 9644264885 | K12: 108, Jessore Road | L12: 108, Jessore Road | M12: PAN Card | N12: 978780650858 | O12: Self-Pay | S12: Ward Nurse
A13: =IF(C13="","",TEXT(ROW(A9),"PT-00000")) -> PT-00009 | B13: 24/09/2025 | C13: Pooja Mukherjee | D13: 06/12/1997 | E13: =IF(D13="","",DATEDIF(D13,TODAY(),"Y")) -> 28 | F13: Male | G13: AB+ | H13: 9172490435 | I13: Sanjay Ghosh | J13: 9127151413 | K13: 87, College Street | L13: 87, College Street | M13: Voter ID | N13: 257679520115 | O13: Corporate | S13: Admin Manager
A14: =IF(C14="","",TEXT(ROW(A10),"PT-00000")) -> PT-00010 | B14: 19/07/2025 | C14: Arjun Bose | D14: 17/03/1995 | E14: =IF(D14="","",DATEDIF(D14,TODAY(),"Y")) -> 31 | F14: Female | G14: A+ | H14: 9970006310 | I14: Poonam Pal | J14: 9226308805 | K14: 82, VIP Road | L14: 82, VIP Road | M14: Driving Licence | N14: 239916194682 | O14: Self-Pay | S14: Billing Clerk
A15: =IF(C15="","",TEXT(ROW(A11),"PT-00000")) -> PT-00011 | B15: 03/08/2025 | C15: Meena Sen | D15: 17/01/2015 | E15: =IF(D15="","",DATEDIF(D15,TODAY(),"Y")) -> 11 | F15: Female | G15: AB- | H15: 9715090376 | I15: Tanvi Ghosh | J15: 9990832605 | K15: 166, Gariahat Road | L15: 166, Gariahat Road | M15: Driving Licence | N15: 449571664588 | O15: Insurance | P15: New India Assurance | Q15: POL661373 | R15: MEM85123 | S15: Billing Clerk
A16: =IF(C16="","",TEXT(ROW(A12),"PT-00000")) -> PT-00012 | B16: 02/01/2026 | C16: Vikram Ghosh | D16: 08/06/1970 | E16: =IF(D16="","",DATEDIF(D16,TODAY(),"Y")) -> 55 | F16: Female | G16: O+ | H16: 9825203461 | I16: Sarla Rathore | J16: 9308177964 | K16: 120, Jessore Road | L16: 120, Jessore Road | M16: Aadhaar | N16: 463468254821 | O16: Self-Pay | S16: Billing Clerk
A17: =IF(C17="","",TEXT(ROW(A13),"PT-00000")) -> PT-00013 | B17: 30/10/2025 | C17: Divya Banerjee | D17: 09/10/1984 | E17: =IF(D17="","",DATEDIF(D17,TODAY(),"Y")) -> 41 | F17: Male | G17: AB- | H17: 9966939462 | I17: Seema Sharma | J17: 9741675685 | K17: 166, Rabindra Sarani | L17: 166, Rabindra Sarani | M17: Aadhaar | N17: 216953194048 | O17: Insurance | P17: Aditya Birla Health | Q17: POL508333 | R17: MEM46946 | S17: Billing Clerk
A18: =IF(C18="","",TEXT(ROW(A14),"PT-00000")) -> PT-00014 | B18: 07/09/2025 | C18: Rajan Dey | D18: 06/07/2015 | E18: =IF(D18="","",DATEDIF(D18,TODAY(),"Y")) -> 10 | F18: Male | G18: AB- | H18: 9233355247 | I18: Divya Desai | J18: 9387700006 | K18: 34, Ultadanga Main Road | L18: 34, Ultadanga Main Road | M18: Driving Licence | N18: 139324261256 | O18: Insurance | P18: ICICI Lombard Health | Q18: POL966282 | R18: MEM44888 | S18: Ward Nurse
A19: =IF(C19="","",TEXT(ROW(A15),"PT-00000")) -> PT-00015 | B19: 08/03/2026 | C19: Sunita Pal | D19: 11/12/1995 | E19: =IF(D19="","",DATEDIF(D19,TODAY(),"Y")) -> 30 | F19: Female | G19: B+ | H19: 9711326792 | I19: Poonam Sen | J19: 9643258518 | K19: 66, Lake Avenue | L19: 66, Lake Avenue | M19: Driving Licence | N19: 268322340916 | O19: Insurance | P19: Star Health Insurance | Q19: POL731832 | R19: MEM46538 | S19: Admin Manager
A20: =IF(C20="","",TEXT(ROW(A16),"PT-00000")) -> PT-00016 | B20: 20/10/2025 | C20: Ajay Nath | D20: 05/08/1957 | E20: =IF(D20="","",DATEDIF(D20,TODAY(),"Y")) -> 68 | F20: Female | G20: AB- | H20: 9827162606 | I20: Mukesh Chowdhury | J20: 9693197599 | K20: 166, Park Street | L20: 166, Park Street | M20: Passport | N20: 267587521884 | O20: Insurance | P20: United India Insurance | Q20: POL583367 | R20: MEM55549 | S20: Billing Clerk
A21: =IF(C21="","",TEXT(ROW(A17),"PT-00000")) -> PT-00017 | B21: 15/11/2025 | C21: Nisha Saha | D21: 15/08/1966 | E21: =IF(D21="","",DATEDIF(D21,TODAY(),"Y")) -> 59 | F21: Male | G21: B+ | H21: 9889387399 | I21: Sunita Bhattacharya | J21: 9152965206 | K21: 73, Camac Street | L21: 73, Camac Street | M21: Aadhaar | N21: 177388358474 | O21: Corporate | S21: Receptionist
A22: =IF(C22="","",TEXT(ROW(A18),"PT-00000")) -> PT-00018 | B22: 04/03/2026 | C22: Sanjay Biswas | D22: 22/04/1998 | E22: =IF(D22="","",DATEDIF(D22,TODAY(),"Y")) -> 28 | F22: Male | G22: O+ | H22: 9796274488 | I22: Shreya Saha | J22: 9453376825 | K22: 11, Station Road | L22: 11, Station Road | M22: Driving Licence | N22: 845520509553 | O22: Self-Pay | S22: Billing Clerk
A23: =IF(C23="","",TEXT(ROW(A19),"PT-00000")) -> PT-00019 | B23: 19/01/2026 | C23: Rekha Chakraborty | D23: 26/05/2014 | E23: =IF(D23="","",DATEDIF(D23,TODAY(),"Y")) -> 12 | F23: Male | G23: B+ | H23: 9207030906 | I23: Tanvi Ganguly | J23: 9785596204 | K23: 68, Rabindra Sarani | L23: 68, Rabindra Sarani | M23: Voter ID | N23: 322507563159 | O23: Corporate | S23: Admin Manager
A24: =IF(C24="","",TEXT(ROW(A20),"PT-00000")) -> PT-00020 | B24: 01/04/2026 | C24: Manish Mitra | D24: 24/01/1975 | E24: =IF(D24="","",DATEDIF(D24,TODAY(),"Y")) -> 51 | F24: Female | G24: AB- | H24: 9317407204 | I24: Nisha Agarwal | J24: 9224635790 | K24: 131, Jessore Road | L24: 131, Jessore Road | M24: Voter ID | N24: 677307814158 | O24: Corporate | S24: Ward Nurse
A25: =IF(C25="","",TEXT(ROW(A21),"PT-00000")) -> PT-00021 | B25: 03/02/2026 | C25: Geeta Paul | D25: 26/06/1959 | E25: =IF(D25="","",DATEDIF(D25,TODAY(),"Y")) -> 66 | F25: Female | G25: O+ | H25: 9790521986 | I25: Vandana Mishra | J25: 9985495542 | K25: 97, VIP Road | L25: 97, VIP Road | M25: Passport | N25: 103862230040 | O25: Corporate | S25: Receptionist
A26: =IF(C26="","",TEXT(ROW(A22),"PT-00000")) -> PT-00022 | B26: 30/09/2025 | C26: Arun Karmakar | D26: 08/03/1976 | E26: =IF(D26="","",DATEDIF(D26,TODAY(),"Y")) -> 50 | F26: Female | G26: A- | H26: 9266624496 | I26: Amit Saha | J26: 9978359493 | K26: 92, MG Road | L26: 92, MG Road | M26: Passport | N26: 821540988679 | O26: Corporate | S26: Billing Clerk
A27: =IF(C27="","",TEXT(ROW(A23),"PT-00000")) -> PT-00023 | B27: 12/08/2025 | C27: Lata Mandal | D27: 22/01/2005 | E27: =IF(D27="","",DATEDIF(D27,TODAY(),"Y")) -> 21 | F27: Female | G27: B- | H27: 9493820247 | I27: Gaurav Mondal | J27: 9255979728 | K27: 54, Netaji Subhas Road | L27: 54, Netaji Subhas Road | M27: Driving Licence | N27: 171130127333 | O27: Insurance | P27: Bajaj Allianz Health | Q27: POL673253 | R27: MEM10398 | S27: Admin Manager
A28: =IF(C28="","",TEXT(ROW(A24),"PT-00000")) -> PT-00024 | B28: 25/03/2026 | C28: Deepak Sarkar | D28: 20/07/2008 | E28: =IF(D28="","",DATEDIF(D28,TODAY(),"Y")) -> 17 | F28: Female | G28: AB+ | H28: 9660715421 | I28: Poonam Jain | J28: 9980908699 | K28: 162, Ultadanga Main Road | L28: 162, Ultadanga Main Road | M28: PAN Card | N28: 353270246366 | O28: Self-Pay | S28: Billing Clerk
A29: =IF(C29="","",TEXT(ROW(A25),"PT-00000")) -> PT-00025 | B29: 20/03/2026 | C29: Shilpa Patra | D29: 15/07/1979 | E29: =IF(D29="","",DATEDIF(D29,TODAY(),"Y")) -> 46 | F29: Female | G29: B+ | H29: 9449972189 | I29: Ajay Menon | J29: 9815775202 | K29: 93, MG Road | L29: 93, MG Road | M29: Voter ID | N29: 193282719967 | O29: Insurance | P29: HDFC ERGO Health | Q29: POL862973 | R29: MEM45401 | S29: Admin Manager
A30: =IF(C30="","",TEXT(ROW(A26),"PT-00000")) -> PT-00026 | B30: 13/11/2025 | C30: Rajesh Haldar | D30: 16/08/2002 | E30: =IF(D30="","",DATEDIF(D30,TODAY(),"Y")) -> 23 | F30: Female | G30: B- | H30: 9285770693 | I30: Smita Nair | J30: 9948881207 | K30: 106, Park Street | L30: 106, Park Street | M30: Voter ID | N30: 850429433996 | O30: Corporate | S30: Admin Manager
A31: =IF(C31="","",TEXT(ROW(A27),"PT-00000")) -> PT-00027 | B31: 15/07/2025 | C31: Asha Majumdar | D31: 23/09/1977 | E31: =IF(D31="","",DATEDIF(D31,TODAY(),"Y")) -> 48 | F31: Female | G31: O- | H31: 9117631103 | I31: Manjula Banerjee | J31: 9904160644 | K31: 122, Lake Avenue | L31: 122, Lake Avenue | M31: Passport | N31: 768127864485 | O31: Self-Pay | S31: Receptionist
A32: =IF(C32="","",TEXT(ROW(A28),"PT-00000")) -> PT-00028 | B32: 04/03/2026 | C32: Vivek Bhattacharya | D32: 03/04/1964 | E32: =IF(D32="","",DATEDIF(D32,TODAY(),"Y")) -> 62 | F32: Female | G32: B- | H32: 9962422558 | I32: Kartik Tiwari | J32: 9275854686 | K32: 41, MG Road | L32: 41, MG Road | M32: Voter ID | N32: 285455727367 | O32: Insurance | P32: Aditya Birla Health | Q32: POL133628 | R32: MEM87621 | S32: Receptionist
A33: =IF(C33="","",TEXT(ROW(A29),"PT-00000")) -> PT-00029 | B33: 23/06/2025 | C33: Smita Chowdhury | D33: 25/12/1987 | E33: =IF(D33="","",DATEDIF(D33,TODAY(),"Y")) -> 38 | F33: Female | G33: O+ | H33: 9280392878 | I33: Sarla Dey | J33: 9148773878 | K33: 28, Diamond Harbour Road | L33: 28, Diamond Harbour Road | M33: PAN Card | N33: 121150183998 | O33: Self-Pay | S33: Admin Manager
A34: =IF(C34="","",TEXT(ROW(A30),"PT-00000")) -> PT-00030 | B34: 06/06/2025 | C34: Prakash Lahiri | D34: 07/08/1967 | E34: =IF(D34="","",DATEDIF(D34,TODAY(),"Y")) -> 58 | F34: Male | G34: A- | H34: 9963585493 | I34: Indira Bhatt | J34: 9995601154 | K34: 179, Camac Street | L34: 179, Camac Street | M34: Passport | N34: 568372141239 | O34: Insurance | P34: United India Insurance | Q34: POL506231 | R34: MEM46730 | S34: Ward Nurse
A35: =IF(C35="","",TEXT(ROW(A31),"PT-00000")) -> PT-00031 | B35: 05/10/2025 | C35: Usha Ganguly | D35: 28/09/2014 | E35: =IF(D35="","",DATEDIF(D35,TODAY(),"Y")) -> 11 | F35: Male | G35: O- | H35: 9909063790 | I35: Vivek Mukherjee | J35: 9513689640 | K35: 172, Ultadanga Main Road | L35: 172, Ultadanga Main Road | M35: PAN Card | N35: 304199375630 | O35: Self-Pay | S35: Receptionist
A36: =IF(C36="","",TEXT(ROW(A32),"PT-00000")) -> PT-00032 | B36: 08/11/2025 | C36: Nikhil Dutta | D36: 24/04/1972 | E36: =IF(D36="","",DATEDIF(D36,TODAY(),"Y")) -> 54 | F36: Male | G36: A+ | H36: 9716664469 | I36: Prakash Gupta | J36: 9673811373 | K36: 62, BT Road | L36: 62, BT Road | M36: Voter ID | N36: 828508076566 | O36: Self-Pay | S36: Receptionist
A37: =IF(C37="","",TEXT(ROW(A33),"PT-00000")) -> PT-00033 | B37: 09/05/2026 | C37: Anjali Sanyal | D37: 11/03/1960 | E37: =IF(D37="","",DATEDIF(D37,TODAY(),"Y")) -> 66 | F37: Male | G37: O- | H37: 9633972714 | I37: Prakash Sharma | J37: 9508529756 | K37: 163, Station Road | L37: 163, Station Road | M37: Voter ID | N37: 520625913342 | O37: Insurance | P37: MediAssist TPA | Q37: POL376832 | R37: MEM27150 | S37: Ward Nurse
A38: =IF(C38="","",TEXT(ROW(A34),"PT-00000")) -> PT-00034 | B38: 08/12/2025 | C38: Sunil Bhatt | D38: 16/01/2001 | E38: =IF(D38="","",DATEDIF(D38,TODAY(),"Y")) -> 25 | F38: Female | G38: O- | H38: 9757320202 | I38: Kavita Roy | J38: 9399466325 | K38: 11, BT Road | L38: 11, BT Road | M38: Aadhaar | N38: 383938729801 | O38: Self-Pay | S38: Receptionist
A39: =IF(C39="","",TEXT(ROW(A35),"PT-00000")) -> PT-00035 | B39: 27/06/2025 | C39: Poonam Joshi | D39: 16/02/1956 | E39: =IF(D39="","",DATEDIF(D39,TODAY(),"Y")) -> 70 | F39: Female | G39: O+ | H39: 9963736709 | I39: Pallavi Pillai | J39: 9757148892 | K39: 16, Camac Street | L39: 16, Camac Street | M39: Aadhaar | N39: 813961015110 | O39: Corporate | S39: Admin Manager
A40: =IF(C40="","",TEXT(ROW(A36),"PT-00000")) -> PT-00036 | B40: 05/05/2026 | C40: Hemant Patel | D40: 03/11/1971 | E40: =IF(D40="","",DATEDIF(D40,TODAY(),"Y")) -> 54 | F40: Female | G40: A+ | H40: 9615235811 | I40: Manoj Lahiri | J40: 9217766587 | K40: 98, Rabindra Sarani | L40: 98, Rabindra Sarani | M40: PAN Card | N40: 362792330484 | O40: Self-Pay | S40: Admin Manager
A41: =IF(C41="","",TEXT(ROW(A37),"PT-00000")) -> PT-00037 | B41: 14/01/2026 | C41: Madhuri Shah | D41: 28/01/2001 | E41: =IF(D41="","",DATEDIF(D41,TODAY(),"Y")) -> 25 | F41: Female | G41: A+ | H41: 9114475614 | I41: Madhuri Kapoor | J41: 9448077890 | K41: 34, Netaji Subhas Road | L41: 34, Netaji Subhas Road | M41: Voter ID | N41: 24839643733 | O41: Insurance | P41: Star Health Insurance | Q41: POL691456 | R41: MEM89235 | S41: Admin Manager
A42: =IF(C42="","",TEXT(ROW(A38),"PT-00000")) -> PT-00038 | B42: 03/06/2025 | C42: Girish Desai | D42: 02/11/2002 | E42: =IF(D42="","",DATEDIF(D42,TODAY(),"Y")) -> 23 | F42: Female | G42: A+ | H42: 9831452863 | I42: Ananya Agarwal | J42: 9565654407 | K42: 62, Station Road | L42: 62, Station Road | M42: Voter ID | N42: 976407029997 | O42: Self-Pay | S42: Ward Nurse
A43: =IF(C43="","",TEXT(ROW(A39),"PT-00000")) -> PT-00039 | B43: 10/01/2026 | C43: Swati Pillai | D43: 16/02/1992 | E43: =IF(D43="","",DATEDIF(D43,TODAY(),"Y")) -> 34 | F43: Female | G43: A- | H43: 9451918479 | I43: Tejas Patel | J43: 9456090724 | K43: 110, Elgin Road | L43: 110, Elgin Road | M43: Passport | N43: 691471567147 | O43: Insurance | P43: Niva Bupa | Q43: POL138103 | R43: MEM61597 | S43: Ward Nurse
A44: =IF(C44="","",TEXT(ROW(A40),"PT-00000")) -> PT-00040 | B44: 20/06/2025 | C44: Ravi Nair | D44: 03/01/1980 | E44: =IF(D44="","",DATEDIF(D44,TODAY(),"Y")) -> 46 | F44: Female | G44: AB- | H44: 9944008376 | I44: Vivek Roy | J44: 9169847466 | K44: 22, MG Road | L44: 22, MG Road | M44: Passport | N44: 583100111509 | O44: Self-Pay | S44: Receptionist
A45: =IF(C45="","",TEXT(ROW(A41),"PT-00000")) -> PT-00041 | B45: 20/10/2025 | C45: Shreya Menon | D45: 09/10/1967 | E45: =IF(D45="","",DATEDIF(D45,TODAY(),"Y")) -> 58 | F45: Female | G45: AB- | H45: 9204791614 | I45: Parth Kapoor | J45: 9681889645 | K45: 112, BT Road | L45: 112, BT Road | M45: Passport | N45: 376171071702 | O45: Self-Pay | S45: Billing Clerk
A46: =IF(C46="","",TEXT(ROW(A42),"PT-00000")) -> PT-00042 | B46: 29/08/2025 | C46: Tarun Iyer | D46: 06/11/1998 | E46: =IF(D46="","",DATEDIF(D46,TODAY(),"Y")) -> 27 | F46: Male | G46: AB+ | H46: 9102032469 | I46: Jay Singh | J46: 9575042945 | K46: 193, Park Street | L46: 193, Park Street | M46: Aadhaar | N46: 556453762029 | O46: Insurance | P46: HDFC ERGO Health | Q46: POL476308 | R46: MEM15486 | S46: Ward Nurse
A47: =IF(C47="","",TEXT(ROW(A43),"PT-00000")) -> PT-00043 | B47: 24/01/2026 | C47: Neha Rao | D47: 12/05/1988 | E47: =IF(D47="","",DATEDIF(D47,TODAY(),"Y")) -> 38 | F47: Female | G47: B- | H47: 9815812660 | I47: Geeta Gupta | J47: 9669066981 | K47: 100, Park Street | L47: 100, Park Street | M47: Driving Licence | N47: 611470699652 | O47: Insurance | P47: Aditya Birla Health | Q47: POL532394 | R47: MEM90826 | S47: Receptionist
A48: =IF(C48="","",TEXT(ROW(A44),"PT-00000")) -> PT-00044 | B48: 17/01/2026 | C48: Bhaskar Reddy | D48: 08/02/1974 | E48: =IF(D48="","",DATEDIF(D48,TODAY(),"Y")) -> 52 | F48: Female | G48: O- | H48: 9581320009 | I48: Lalita Bose | J48: 9969391361 | K48: 93, Elgin Road | L48: 93, Elgin Road | M48: Driving Licence | N48: 667516353355 | O48: Self-Pay | S48: Billing Clerk
A49: =IF(C49="","",TEXT(ROW(A45),"PT-00000")) -> PT-00045 | B49: 03/09/2025 | C49: Jyoti Kumar | D49: 19/12/1964 | E49: =IF(D49="","",DATEDIF(D49,TODAY(),"Y")) -> 61 | F49: Female | G49: O- | H49: 9259864820 | I49: Yash Tiwari | J49: 9860763076 | K49: 3, BT Road | L49: 3, BT Road | M49: Aadhaar | N49: 533655077876 | O49: Insurance | P49: ICICI Lombard Health | Q49: POL760636 | R49: MEM40211 | S49: Receptionist
A50: =IF(C50="","",TEXT(ROW(A46),"PT-00000")) -> PT-00046 | B50: 06/06/2025 | C50: Alok Verma | D50: 23/04/1964 | E50: =IF(D50="","",DATEDIF(D50,TODAY(),"Y")) -> 62 | F50: Female | G50: B+ | H50: 9433864756 | I50: Kavita Desai | J50: 9470446564 | K50: 179, College Street | L50: 179, College Street | M50: PAN Card | N50: 255327901911 | O50: Self-Pay | S50: Receptionist
A51: =IF(C51="","",TEXT(ROW(A47),"PT-00000")) -> PT-00047 | B51: 21/01/2026 | C51: Seema Mishra | D51: 11/11/1978 | E51: =IF(D51="","",DATEDIF(D51,TODAY(),"Y")) -> 47 | F51: Female | G51: B+ | H51: 9568035438 | I51: Lalita Pillai | J51: 9144377236 | K51: 36, VIP Road | L51: 36, VIP Road | M51: Driving Licence | N51: 919585032112 | O51: Insurance | P51: ICICI Lombard Health | Q51: POL226858 | R51: MEM57571 | S51: Admin Manager
A52: =IF(C52="","",TEXT(ROW(A48),"PT-00000")) -> PT-00048 | B52: 06/05/2026 | C52: Varun Tiwari | D52: 14/09/1962 | E52: =IF(D52="","",DATEDIF(D52,TODAY(),"Y")) -> 63 | F52: Male | G52: B- | H52: 9797858178 | I52: Sarla Karmakar | J52: 9843784396 | K52: 185, Camac Street | L52: 185, Camac Street | M52: Aadhaar | N52: 19104120879 | O52: Insurance | P52: Star Health Insurance | Q52: POL211569 | R52: MEM47173 | S52: Admin Manager
A53: =IF(C53="","",TEXT(ROW(A49),"PT-00000")) -> PT-00049 | B53: 02/12/2025 | C53: Pallavi Pandey | D53: 04/09/1967 | E53: =IF(D53="","",DATEDIF(D53,TODAY(),"Y")) -> 58 | F53: Male | G53: B+ | H53: 9433108043 | I53: Pooja Singh | J53: 9422884013 | K53: 71, Jessore Road | L53: 71, Jessore Road | M53: Voter ID | N53: 994180531481 | O53: Self-Pay | S53: Admin Manager
A54: =IF(C54="","",TEXT(ROW(A50),"PT-00000")) -> PT-00050 | B54: 29/10/2025 | C54: Rohit Dubey | D54: 16/09/1959 | E54: =IF(D54="","",DATEDIF(D54,TODAY(),"Y")) -> 66 | F54: Male | G54: AB+ | H54: 9142324795 | I54: Nandini Khanna | J54: 9383616172 | K54: 159, Rabindra Sarani | L54: 159, Rabindra Sarani | M54: Driving Licence | N54: 569082490872 | O54: Insurance | P54: Niva Bupa | Q54: POL771399 | R54: MEM79878 | S54: Admin Manager
A55: =IF(C55="","",TEXT(ROW(A51),"PT-00000")) -> PT-00051 | B55: 14/03/2026 | C55: Sarita Shukla | D55: 15/08/1994 | E55: =IF(D55="","",DATEDIF(D55,TODAY(),"Y")) -> 31 | F55: Female | G55: B+ | H55: 9649029684 | I55: Sunita Karmakar | J55: 9383300326 | K55: 11, Lake Avenue | L55: 11, Lake Avenue | M55: Aadhaar | N55: 365860016457 | O55: Corporate | S55: Billing Clerk
A56: =IF(C56="","",TEXT(ROW(A52),"PT-00000")) -> PT-00052 | B56: 01/11/2025 | C56: Dinesh Yadav | D56: 18/04/2004 | E56: =IF(D56="","",DATEDIF(D56,TODAY(),"Y")) -> 22 | F56: Male | G56: AB+ | H56: 9776301267 | I56: Rekha Nair | J56: 9211963322 | K56: 176, Lake Avenue | L56: 176, Lake Avenue | M56: Aadhaar | N56: 823624175415 | O56: Insurance | P56: MediAssist TPA | Q56: POL912125 | R56: MEM60246 | S56: Billing Clerk
A57: =IF(C57="","",TEXT(ROW(A53),"PT-00000")) -> PT-00053 | B57: 01/01/2026 | C57: Vandana Jain | D57: 16/04/2010 | E57: =IF(D57="","",DATEDIF(D57,TODAY(),"Y")) -> 16 | F57: Male | G57: B- | H57: 9651963906 | I57: Parth Patel | J57: 9496078615 | K57: 168, College Street | L57: 168, College Street | M57: Driving Licence | N57: 11997169842 | O57: Corporate | S57: Receptionist
A58: =IF(C58="","",TEXT(ROW(A54),"PT-00000")) -> PT-00054 | B58: 01/05/2026 | C58: Kiran Agarwal | D58: 13/02/2014 | E58: =IF(D58="","",DATEDIF(D58,TODAY(),"Y")) -> 12 | F58: Male | G58: AB+ | H58: 9985971684 | I58: Madhuri Nath | J58: 9456337059 | K58: 81, MG Road | L58: 81, MG Road | M58: Passport | N58: 835722605344 | O58: Insurance | P58: HDFC ERGO Health | Q58: POL709058 | R58: MEM28938 | S58: Receptionist
A59: =IF(C59="","",TEXT(ROW(A55),"PT-00000")) -> PT-00055 | B59: 28/09/2025 | C59: Mohan Khanna | D59: 09/08/1995 | E59: =IF(D59="","",DATEDIF(D59,TODAY(),"Y")) -> 30 | F59: Female | G59: B- | H59: 9799901392 | I59: Amit Singh | J59: 9284769278 | K59: 42, Park Street | L59: 42, Park Street | M59: PAN Card | N59: 619299408455 | O59: Insurance | P59: Star Health Insurance | Q59: POL151371 | R59: MEM81804 | S59: Receptionist
A60: =IF(C60="","",TEXT(ROW(A56),"PT-00000")) -> PT-00056 | B60: 15/07/2025 | C60: Lalita Malhotra | D60: 18/11/1991 | E60: =IF(D60="","",DATEDIF(D60,TODAY(),"Y")) -> 34 | F60: Female | G60: A- | H60: 9541017324 | I60: Chirag Pillai | J60: 9689037104 | K60: 137, Netaji Subhas Road | L60: 137, Netaji Subhas Road | M60: Voter ID | N60: 288777091323 | O60: Insurance | P60: HDFC ERGO Health | Q60: POL558585 | R60: MEM87486 | S60: Receptionist
A61: =IF(C61="","",TEXT(ROW(A57),"PT-00000")) -> PT-00057 | B61: 30/07/2025 | C61: Gaurav Kapoor | D61: 16/01/2002 | E61: =IF(D61="","",DATEDIF(D61,TODAY(),"Y")) -> 24 | F61: Male | G61: O- | H61: 9497795557 | I61: Kartik Roy | J61: 9761969597 | K61: 138, BT Road | L61: 138, BT Road | M61: PAN Card | N61: 928132007746 | O61: Insurance | P61: New India Assurance | Q61: POL128095 | R61: MEM99753 | S61: Ward Nurse
A62: =IF(C62="","",TEXT(ROW(A58),"PT-00000")) -> PT-00058 | B62: 10/12/2025 | C62: Preeti Bajaj | D62: 25/12/1960 | E62: =IF(D62="","",DATEDIF(D62,TODAY(),"Y")) -> 65 | F62: Female | G62: A- | H62: 9340273330 | I62: Ramesh Malhotra | J62: 9476967818 | K62: 192, Station Road | L62: 192, Station Road | M62: Driving Licence | N62: 194890380711 | O62: Corporate | S62: Receptionist
A63: =IF(C63="","",TEXT(ROW(A59),"PT-00000")) -> PT-00059 | B63: 14/06/2025 | C63: Ashok Chandra | D63: 28/04/1989 | E63: =IF(D63="","",DATEDIF(D63,TODAY(),"Y")) -> 37 | F63: Male | G63: B+ | H63: 9997336808 | I63: Poonam Chakraborty | J63: 9561928626 | K63: 38, College Street | L63: 38, College Street | M63: Passport | N63: 390116298066 | O63: Corporate | S63: Billing Clerk
A64: =IF(C64="","",TEXT(ROW(A60),"PT-00000")) -> PT-00060 | B64: 04/01/2026 | C64: Nandini Rathore | D64: 02/02/1965 | E64: =IF(D64="","",DATEDIF(D64,TODAY(),"Y")) -> 61 | F64: Female | G64: B- | H64: 9959517751 | I64: Bhavesh Chakraborty | J64: 9227556629 | K64: 136, Ultadanga Main Road | L64: 136, Ultadanga Main Road | M64: Driving Licence | N64: 50627416419 | O64: Insurance | P64: HDFC ERGO Health | Q64: POL235452 | R64: MEM71112 | S64: Billing Clerk
A65: =IF(C65="","",TEXT(ROW(A61),"PT-00000")) -> PT-00061 | B65: 24/01/2026 | C65: Manoj Roy | D65: 16/09/2000 | E65: =IF(D65="","",DATEDIF(D65,TODAY(),"Y")) -> 25 | F65: Female | G65: O- | H65: 9205880849 | I65: Devang Iyer | J65: 9592799053 | K65: 97, Diamond Harbour Road | L65: 97, Diamond Harbour Road | M65: PAN Card | N65: 936691202565 | O65: Insurance | P65: Niva Bupa | Q65: POL909104 | R65: MEM84876 | S65: Ward Nurse
A66: =IF(C66="","",TEXT(ROW(A62),"PT-00000")) -> PT-00062 | B66: 02/02/2026 | C66: Sudha Sharma | D66: 22/02/1968 | E66: =IF(D66="","",DATEDIF(D66,TODAY(),"Y")) -> 58 | F66: Female | G66: B- | H66: 9182754486 | I66: Nikhil Pandey | J66: 9583556075 | K66: 13, VIP Road | L66: 13, VIP Road | M66: Voter ID | N66: 47153382911 | O66: Self-Pay | S66: Admin Manager
A67: =IF(C67="","",TEXT(ROW(A63),"PT-00000")) -> PT-00063 | B67: 22/08/2025 | C67: Harish Mehta | D67: 09/11/1957 | E67: =IF(D67="","",DATEDIF(D67,TODAY(),"Y")) -> 68 | F67: Female | G67: B- | H67: 9849422702 | I67: Ananya Reddy | J67: 9444683574 | K67: 111, MG Road | L67: 111, MG Road | M67: Voter ID | N67: 954284896841 | O67: Self-Pay | S67: Admin Manager
A68: =IF(C68="","",TEXT(ROW(A64),"PT-00000")) -> PT-00064 | B68: 16/08/2025 | C68: Chhaya Mondal | D68: 04/07/1969 | E68: =IF(D68="","",DATEDIF(D68,TODAY(),"Y")) -> 56 | F68: Female | G68: B- | H68: 9874930400 | I68: Indira Chakraborty | J68: 9921708720 | K68: 27, Station Road | L68: 27, Station Road | M68: Driving Licence | N68: 898208324762 | O68: Insurance | P68: ICICI Lombard Health | Q68: POL640263 | R68: MEM71932 | S68: Admin Manager
A69: =IF(C69="","",TEXT(ROW(A65),"PT-00000")) -> PT-00065 | B69: 17/06/2025 | C69: Ramesh Das | D69: 25/12/2001 | E69: =IF(D69="","",DATEDIF(D69,TODAY(),"Y")) -> 24 | F69: Female | G69: A- | H69: 9439142403 | I69: Vishal Rao | J69: 9311676221 | K69: 200, Jessore Road | L69: 200, Jessore Road | M69: Passport | N69: 203907602059 | O69: Self-Pay | S69: Billing Clerk
A70: =IF(C70="","",TEXT(ROW(A66),"PT-00000")) -> PT-00066 | B70: 19/11/2025 | C70: Bharati Gupta | D70: 13/09/1974 | E70: =IF(D70="","",DATEDIF(D70,TODAY(),"Y")) -> 51 | F70: Female | G70: B- | H70: 9929458031 | I70: Gita Pal | J70: 9991995328 | K70: 125, Gariahat Road | L70: 125, Gariahat Road | M70: Aadhaar | N70: 612828296167 | O70: Self-Pay | S70: Admin Manager
A71: =IF(C71="","",TEXT(ROW(A67),"PT-00000")) -> PT-00067 | B71: 09/06/2025 | C71: Vishal Singh | D71: 14/03/1995 | E71: =IF(D71="","",DATEDIF(D71,TODAY(),"Y")) -> 31 | F71: Male | G71: O- | H71: 9477493603 | I71: Vandana Chandra | J71: 9156097428 | K71: 89, Ultadanga Main Road | L71: 89, Ultadanga Main Road | M71: Aadhaar | N71: 476877309284 | O71: Insurance | P71: Star Health Insurance | Q71: POL256521 | R71: MEM52680 | S71: Ward Nurse
A72: =IF(C72="","",TEXT(ROW(A68),"PT-00000")) -> PT-00068 | B72: 04/03/2026 | C72: Kamla Chatterjee | D72: 18/04/1981 | E72: =IF(D72="","",DATEDIF(D72,TODAY(),"Y")) -> 45 | F72: Female | G72: A+ | H72: 9998972049 | I72: Sunil Mondal | J72: 9856992772 | K72: 137, Camac Street | L72: 137, Camac Street | M72: Voter ID | N72: 827689501881 | O72: Self-Pay | S72: Receptionist
A73: =IF(C73="","",TEXT(ROW(A69),"PT-00000")) -> PT-00069 | B73: 31/03/2026 | C73: Abhishek Mukherjee | D73: 10/01/1991 | E73: =IF(D73="","",DATEDIF(D73,TODAY(),"Y")) -> 35 | F73: Male | G73: A+ | H73: 9704922176 | I73: Mohan Haldar | J73: 9206975129 | K73: 170, BT Road | L73: 170, BT Road | M73: PAN Card | N73: 317858676114 | O73: Insurance | P73: United India Insurance | Q73: POL352344 | R73: MEM19947 | S73: Receptionist
A74: =IF(C74="","",TEXT(ROW(A70),"PT-00000")) -> PT-00070 | B74: 20/01/2026 | C74: Shanta Bose | D74: 11/08/2010 | E74: =IF(D74="","",DATEDIF(D74,TODAY(),"Y")) -> 15 | F74: Male | G74: B+ | H74: 9224799608 | I74: Swati Haldar | J74: 9739354875 | K74: 19, Diamond Harbour Road | L74: 19, Diamond Harbour Road | M74: Driving Licence | N74: 422630718865 | O74: Corporate | S74: Ward Nurse
A75: =IF(C75="","",TEXT(ROW(A71),"PT-00000")) -> PT-00071 | B75: 22/10/2025 | C75: Nilesh Sen | D75: 21/12/2014 | E75: =IF(D75="","",DATEDIF(D75,TODAY(),"Y")) -> 11 | F75: Male | G75: A- | H75: 9866600885 | I75: Nandini Sharma | J75: 9680546972 | K75: 98, MG Road | L75: 98, MG Road | M75: Voter ID | N75: 579674809226 | O75: Self-Pay | S75: Billing Clerk
A76: =IF(C76="","",TEXT(ROW(A72),"PT-00000")) -> PT-00072 | B76: 27/03/2026 | C76: Rupal Ghosh | D76: 28/10/2004 | E76: =IF(D76="","",DATEDIF(D76,TODAY(),"Y")) -> 21 | F76: Male | G76: B- | H76: 9124007295 | I76: Sagar Bhatt | J76: 9186672229 | K76: 188, BT Road | L76: 188, BT Road | M76: Aadhaar | N76: 667993788152 | O76: Self-Pay | S76: Admin Manager
A77: =IF(C77="","",TEXT(ROW(A73),"PT-00000")) -> PT-00073 | B77: 23/10/2025 | C77: Saurabh Banerjee | D77: 18/02/2009 | E77: =IF(D77="","",DATEDIF(D77,TODAY(),"Y")) -> 17 | F77: Female | G77: B- | H77: 9440784139 | I77: Arjun Kapoor | J77: 9613719587 | K77: 19, MG Road | L77: 19, MG Road | M77: Passport | N77: 166637085617 | O77: Self-Pay | S77: Billing Clerk
A78: =IF(C78="","",TEXT(ROW(A74),"PT-00000")) -> PT-00074 | B78: 30/08/2025 | C78: Taruna Dey | D78: 27/11/1980 | E78: =IF(D78="","",DATEDIF(D78,TODAY(),"Y")) -> 45 | F78: Female | G78: O- | H78: 9513293496 | I78: Sunita Mandal | J78: 9116973368 | K78: 178, Diamond Harbour Road | L78: 178, Diamond Harbour Road | M78: Voter ID | N78: 282595900207 | O78: Corporate | S78: Ward Nurse
A79: =IF(C79="","",TEXT(ROW(A75),"PT-00000")) -> PT-00075 | B79: 24/01/2026 | C79: Mukesh Pal | D79: 26/01/1972 | E79: =IF(D79="","",DATEDIF(D79,TODAY(),"Y")) -> 54 | F79: Female | G79: AB+ | H79: 9733913808 | I79: Pallavi Chandra | J79: 9762291415 | K79: 145, Gariahat Road | L79: 145, Gariahat Road | M79: PAN Card | N79: 428387927134 | O79: Corporate | S79: Admin Manager
A80: =IF(C80="","",TEXT(ROW(A76),"PT-00000")) -> PT-00076 | B80: 15/08/2025 | C80: Savita Nath | D80: 22/04/1996 | E80: =IF(D80="","",DATEDIF(D80,TODAY(),"Y")) -> 30 | F80: Male | G80: A+ | H80: 9251838910 | I80: Rajan Chakraborty | J80: 9429583047 | K80: 95, BT Road | L80: 95, BT Road | M80: Passport | N80: 613248432796 | O80: Corporate | S80: Receptionist
A81: =IF(C81="","",TEXT(ROW(A77),"PT-00000")) -> PT-00077 | B81: 05/10/2025 | C81: Aditya Saha | D81: 03/10/1977 | E81: =IF(D81="","",DATEDIF(D81,TODAY(),"Y")) -> 48 | F81: Female | G81: AB- | H81: 9281010348 | I81: Chhaya Rathore | J81: 9886149701 | K81: 154, BT Road | L81: 154, BT Road | M81: Passport | N81: 795103316448 | O81: Insurance | P81: MediAssist TPA | Q81: POL145668 | R81: MEM47734 | S81: Admin Manager
A82: =IF(C82="","",TEXT(ROW(A78),"PT-00000")) -> PT-00078 | B82: 24/04/2026 | C82: Rani Biswas | D82: 12/04/1987 | E82: =IF(D82="","",DATEDIF(D82,TODAY(),"Y")) -> 39 | F82: Female | G82: AB- | H82: 9296978131 | I82: Arjun Pillai | J82: 9607995468 | K82: 42, Ultadanga Main Road | L82: 42, Ultadanga Main Road | M82: Driving Licence | N82: 970490136388 | O82: Corporate | S82: Admin Manager
A83: =IF(C83="","",TEXT(ROW(A79),"PT-00000")) -> PT-00079 | B83: 21/10/2025 | C83: Chirag Chakraborty | D83: 01/06/1998 | E83: =IF(D83="","",DATEDIF(D83,TODAY(),"Y")) -> 27 | F83: Male | G83: O- | H83: 9261891949 | I83: Rekha Karmakar | J83: 9980486264 | K83: 114, College Street | L83: 114, College Street | M83: PAN Card | N83: 765035025776 | O83: Insurance | P83: HDFC ERGO Health | Q83: POL258403 | R83: MEM15423 | S83: Ward Nurse
A84: =IF(C84="","",TEXT(ROW(A80),"PT-00000")) -> PT-00080 | B84: 15/07/2025 | C84: Manjula Mitra | D84: 17/08/1966 | E84: =IF(D84="","",DATEDIF(D84,TODAY(),"Y")) -> 59 | F84: Male | G84: O- | H84: 9868182167 | I84: Usha Kapoor | J84: 9361379643 | K84: 53, BT Road | L84: 53, BT Road | M84: Passport | N84: 217631772958 | O84: Insurance | P84: Care Health Insurance | Q84: POL615870 | R84: MEM74081 | S84: Receptionist
A85: =IF(C85="","",TEXT(ROW(A81),"PT-00000")) -> PT-00081 | B85: 23/04/2026 | C85: Yash Paul | D85: 13/05/1980 | E85: =IF(D85="","",DATEDIF(D85,TODAY(),"Y")) -> 46 | F85: Female | G85: B+ | H85: 9541031810 | I85: Tarun Paul | J85: 9520846596 | K85: 48, Ultadanga Main Road | L85: 48, Ultadanga Main Road | M85: Driving Licence | N85: 697872302831 | O85: Self-Pay | S85: Receptionist
A86: =IF(C86="","",TEXT(ROW(A82),"PT-00000")) -> PT-00082 | B86: 04/12/2025 | C86: Hema Karmakar | D86: 27/01/1978 | E86: =IF(D86="","",DATEDIF(D86,TODAY(),"Y")) -> 48 | F86: Female | G86: B+ | H86: 9893538953 | I86: Leela Singh | J86: 9752632762 | K86: 56, Jessore Road | L86: 56, Jessore Road | M86: Aadhaar | N86: 363361719728 | O86: Corporate | S86: Billing Clerk
A87: =IF(C87="","",TEXT(ROW(A83),"PT-00000")) -> PT-00083 | B87: 02/09/2025 | C87: Kartik Mandal | D87: 05/04/1971 | E87: =IF(D87="","",DATEDIF(D87,TODAY(),"Y")) -> 55 | F87: Male | G87: O+ | H87: 9214473505 | I87: Poonam Singh | J87: 9998016551 | K87: 127, Camac Street | L87: 127, Camac Street | M87: PAN Card | N87: 3930033202 | O87: Self-Pay | S87: Receptionist
A88: =IF(C88="","",TEXT(ROW(A84),"PT-00000")) -> PT-00084 | B88: 30/09/2025 | C88: Gita Sarkar | D88: 12/04/1998 | E88: =IF(D88="","",DATEDIF(D88,TODAY(),"Y")) -> 28 | F88: Male | G88: O+ | H88: 9857535659 | I88: Radha Kapoor | J88: 9507789733 | K88: 82, Rabindra Sarani | L88: 82, Rabindra Sarani | M88: Voter ID | N88: 661705819782 | O88: Insurance | P88: Care Health Insurance | Q88: POL695513 | R88: MEM22432 | S88: Receptionist
A89: =IF(C89="","",TEXT(ROW(A85),"PT-00000")) -> PT-00085 | B89: 04/03/2026 | C89: Parth Patra | D89: 07/04/2011 | E89: =IF(D89="","",DATEDIF(D89,TODAY(),"Y")) -> 15 | F89: Male | G89: O- | H89: 9405666163 | I89: Sunita Lahiri | J89: 9903783354 | K89: 94, Elgin Road | L89: 94, Elgin Road | M89: PAN Card | N89: 989358085125 | O89: Insurance | P89: Star Health Insurance | Q89: POL285322 | R89: MEM56082 | S89: Receptionist
A90: =IF(C90="","",TEXT(ROW(A86),"PT-00000")) -> PT-00086 | B90: 01/08/2025 | C90: Radha Haldar | D90: 27/06/2013 | E90: =IF(D90="","",DATEDIF(D90,TODAY(),"Y")) -> 12 | F90: Female | G90: AB+ | H90: 9171841645 | I90: Poonam Agarwal | J90: 9464288543 | K90: 38, Ultadanga Main Road | L90: 38, Ultadanga Main Road | M90: Aadhaar | N90: 353126286844 | O90: Insurance | P90: Star Health Insurance | Q90: POL662881 | R90: MEM51725 | S90: Receptionist
A91: =IF(C91="","",TEXT(ROW(A87),"PT-00000")) -> PT-00087 | B91: 28/02/2026 | C91: Mihir Majumdar | D91: 06/02/1999 | E91: =IF(D91="","",DATEDIF(D91,TODAY(),"Y")) -> 27 | F91: Male | G91: AB- | H91: 9686050716 | I91: Nilesh Menon | J91: 9599338558 | K91: 12, Camac Street | L91: 12, Camac Street | M91: Passport | N91: 699126904772 | O91: Insurance | P91: Care Health Insurance | Q91: POL417180 | R91: MEM80265 | S91: Ward Nurse
A92: =IF(C92="","",TEXT(ROW(A88),"PT-00000")) -> PT-00088 | B92: 02/03/2026 | C92: Sarla Bhattacharya | D92: 23/11/1966 | E92: =IF(D92="","",DATEDIF(D92,TODAY(),"Y")) -> 59 | F92: Male | G92: B- | H92: 9359371607 | I92: Vikram Das | J92: 9861993354 | K92: 93, Diamond Harbour Road | L92: 93, Diamond Harbour Road | M92: PAN Card | N92: 858033018475 | O92: Self-Pay | S92: Billing Clerk
A93: =IF(C93="","",TEXT(ROW(A89),"PT-00000")) -> PT-00089 | B93: 01/01/2026 | C93: Devang Chowdhury | D93: 02/02/1992 | E93: =IF(D93="","",DATEDIF(D93,TODAY(),"Y")) -> 34 | F93: Female | G93: AB+ | H93: 9237303145 | I93: Vandana Yadav | J93: 9665456447 | K93: 184, Gariahat Road | L93: 184, Gariahat Road | M93: Passport | N93: 105081142864 | O93: Insurance | P93: Care Health Insurance | Q93: POL181069 | R93: MEM23374 | S93: Ward Nurse
A94: =IF(C94="","",TEXT(ROW(A90),"PT-00000")) -> PT-00090 | B94: 24/02/2026 | C94: Pushpa Lahiri | D94: 26/06/2009 | E94: =IF(D94="","",DATEDIF(D94,TODAY(),"Y")) -> 16 | F94: Female | G94: B+ | H94: 9678528038 | I94: Bhavesh Verma | J94: 9564337287 | K94: 83, College Street | L94: 83, College Street | M94: Driving Licence | N94: 388438344732 | O94: Self-Pay | S94: Billing Clerk
A95: =IF(C95="","",TEXT(ROW(A91),"PT-00000")) -> PT-00091 | B95: 26/09/2025 | C95: Tejas Ganguly | D95: 21/12/1961 | E95: =IF(D95="","",DATEDIF(D95,TODAY(),"Y")) -> 64 | F95: Male | G95: A- | H95: 9256474014 | I95: Sanjay Kapoor | J95: 9498958998 | K95: 58, College Street | L95: 58, College Street | M95: Aadhaar | N95: 966774628545 | O95: Insurance | P95: Star Health Insurance | Q95: POL767246 | R95: MEM27626 | S95: Receptionist
A96: =IF(C96="","",TEXT(ROW(A92),"PT-00000")) -> PT-00092 | B96: 19/09/2025 | C96: Sharda Dutta | D96: 06/05/1979 | E96: =IF(D96="","",DATEDIF(D96,TODAY(),"Y")) -> 47 | F96: Male | G96: A- | H96: 9784705868 | I96: Abhishek Sanyal | J96: 9752983789 | K96: 88, Lake Avenue | L96: 88, Lake Avenue | M96: Aadhaar | N96: 988451852287 | O96: Self-Pay | S96: Billing Clerk
A97: =IF(C97="","",TEXT(ROW(A93),"PT-00000")) -> PT-00093 | B97: 24/06/2025 | C97: Jay Sanyal | D97: 23/11/1963 | E97: =IF(D97="","",DATEDIF(D97,TODAY(),"Y")) -> 62 | F97: Female | G97: O+ | H97: 9433728344 | I97: Alok Agarwal | J97: 9164964870 | K97: 16, College Street | L97: 16, College Street | M97: Driving Licence | N97: 377002555383 | O97: Insurance | P97: Aditya Birla Health | Q97: POL721730 | R97: MEM40560 | S97: Billing Clerk
A98: =IF(C98="","",TEXT(ROW(A94),"PT-00000")) -> PT-00094 | B98: 13/01/2026 | C98: Meera Bhatt | D98: 15/07/2010 | E98: =IF(D98="","",DATEDIF(D98,TODAY(),"Y")) -> 15 | F98: Male | G98: AB- | H98: 9660628021 | I98: Madhuri Nath | J98: 9944546457 | K98: 20, Station Road | L98: 20, Station Road | M98: Aadhaar | N98: 937282205113 | O98: Insurance | P98: ICICI Lombard Health | Q98: POL159758 | R98: MEM19013 | S98: Receptionist
A99: =IF(C99="","",TEXT(ROW(A95),"PT-00000")) -> PT-00095 | B99: 21/04/2026 | C99: Bhavesh Joshi | D99: 14/06/1985 | E99: =IF(D99="","",DATEDIF(D99,TODAY(),"Y")) -> 40 | F99: Male | G99: A- | H99: 9906330633 | I99: Bhavesh Banerjee | J99: 9459961840 | K99: 71, VIP Road | L99: 71, VIP Road | M99: Aadhaar | N99: 991589180880 | O99: Insurance | P99: Aditya Birla Health | Q99: POL845308 | R99: MEM15321 | S99: Admin Manager
A100: =IF(C100="","",TEXT(ROW(A96),"PT-00000")) -> PT-00096 | B100: 13/03/2026 | C100: Indira Patel | D100: 18/03/1985 | E100: =IF(D100="","",DATEDIF(D100,TODAY(),"Y")) -> 41 | F100: Male | G100: A- | H100: 9442267330 | I100: Mihir Mitra | J100: 9739807055 | K100: 168, MG Road | L100: 168, MG Road | M100: Voter ID | N100: 639908216056 | O100: Corporate | S100: Admin Manager
A101: =IF(C101="","",TEXT(ROW(A97),"PT-00000")) -> PT-00097 | B101: 29/07/2025 | C101: Sagar Shah | D101: 06/08/1964 | E101: =IF(D101="","",DATEDIF(D101,TODAY(),"Y")) -> 61 | F101: Male | G101: A- | H101: 9273825868 | I101: Nilesh Haldar | J101: 9245115549 | K101: 68, Netaji Subhas Road | L101: 68, Netaji Subhas Road | M101: Aadhaar | N101: 515632552443 | O101: Self-Pay | S101: Billing Clerk
A102: =IF(C102="","",TEXT(ROW(A98),"PT-00000")) -> PT-00098 | B102: 26/04/2026 | C102: Leela Desai | D102: 08/03/2008 | E102: =IF(D102="","",DATEDIF(D102,TODAY(),"Y")) -> 18 | F102: Male | G102: A- | H102: 9695440035 | I102: Hemant Ganguly | J102: 9275500689 | K102: 34, BT Road | L102: 34, BT Road | M102: Aadhaar | N102: 355860414818 | O102: Corporate | S102: Admin Manager
...

Sheet DR_Master
A2: CityMed Multi-Specialty Hospital — Doctor Directory
A4: Doctor_ID | B4: Full_Name | C4: Designation | D4: Department | E4: Specialization | F4: Qualification | G4: OPD_Fee (₹) | H4: IPD_Daily_Fee (₹) | I4: Emergency_Fee (₹) | J4: Available_Days | K4: OPD_Timing | L4: Status
A5: =IF(B5="","","DR-"&TEXT(ROW(A1),"000")) -> DR-001 | B5: Dr. Arjun Bose | C5: Senior Consultant | D5: Cardiology | E5: Interventional Cardiology | F5: MBBS, MD, DM | G5: 800 | H5: 500 | I5: 1200 | J5: Mon-Sat | K5: 9AM-1PM | L5: Active
A6: =IF(B6="","","DR-"&TEXT(ROW(A2),"000")) -> DR-002 | B6: Dr. Meena Pillai | C6: Head of Department | D6: Gynaecology | E6: Maternal & Fetal Medicine | F6: MBBS, MS | G6: 700 | H6: 450 | I6: 1000 | J6: Mon-Fri | K6: 10AM-2PM | L6: Active
A7: =IF(B7="","","DR-"&TEXT(ROW(A3),"000")) -> DR-003 | B7: Dr. Sanjay Ghosh | C7: Consultant | D7: General Medicine | E7: Internal Medicine | F7: MBBS, MD | G7: 500 | H7: 350 | I7: 800 | J7: Mon-Sat | K7: 8AM-12PM | L7: Active
A8: =IF(B8="","","DR-"&TEXT(ROW(A4),"000")) -> DR-004 | B8: Dr. Ritika Sharma | C8: Senior Consultant | D8: Paediatrics | E8: Neonatology | F8: MBBS, MD | G8: 600 | H8: 400 | I8: 900 | J8: Mon-Fri | K8: 9AM-1PM | L8: Active
A9: =IF(B9="","","DR-"&TEXT(ROW(A5),"000")) -> DR-005 | B9: Dr. Tanmoy Das | C9: Consultant | D9: Orthopaedics | E9: Joint Replacement | F9: MBBS, MS | G9: 650 | H9: 420 | I9: 950 | J9: Tue-Sat | K9: 11AM-3PM | L9: Active
A10: =IF(B10="","","DR-"&TEXT(ROW(A6),"000")) -> DR-006 | B10: Dr. Farhan Qureshi | C10: Resident Doctor | D10: Emergency | E10: Emergency Medicine | F10: MBBS | G10: 300 | H10: 200 | I10: 500 | J10: On-Call | K10: 24x7 | L10: Active
A11: =IF(B11="","","DR-"&TEXT(ROW(A7),"000")) -> DR-007 | B11: Dr. Lipika Sen | C11: Consultant | D11: Diagnostics | E11: Radiology & Imaging | F11: MBBS, MD | G11: 400 | H11: 0 | I11: 600 | J11: Mon-Fri | K11: 9AM-5PM | L11: Active
A12: =IF(B12="","","DR-"&TEXT(ROW(A8),"000")) -> DR-008 | B12: Dr. Prabal Roy | C12: Senior Consultant | D12: General Medicine | E12: Diabetology | F12: MBBS, MD | G12: 550 | H12: 380 | I12: 850 | J12: Mon-Sat | K12: 8AM-11AM | L12: On Leave
A13: =IF(B13="","","DR-"&TEXT(ROW(A9),"000")) -> DR-009 | B13: Dr. Kamala Nair | C13: Visiting Consultant | D13: Cardiology | E13: Cardiac Surgery | F13: MBBS, MS, MCh | G13: 1200 | H13: 800 | I13: 2000 | J13: Wed & Fri | K13: 2PM-5PM | L13: Active
A14: =IF(B14="","","DR-"&TEXT(ROW(A10),"000")) -> DR-010 | B14: Dr. Subhash Patra | C14: Head of Department | D14: Orthopaedics | E14: Spine Surgery | F14: MBBS, MS | G14: 750 | H14: 500 | I14: 1100 | J14: Mon-Fri | K14: 10AM-1PM | L14: Active
A15: =IF(B15="","","DR-"&TEXT(ROW(A11),"000"))
A16: =IF(B16="","","DR-"&TEXT(ROW(A12),"000"))
A17: =IF(B17="","","DR-"&TEXT(ROW(A13),"000"))
A18: =IF(B18="","","DR-"&TEXT(ROW(A14),"000"))
A19: =IF(B19="","","DR-"&TEXT(ROW(A15),"000"))
A20: =IF(B20="","","DR-"&TEXT(ROW(A16),"000"))
A21: =IF(B21="","","DR-"&TEXT(ROW(A17),"000"))
A22: =IF(B22="","","DR-"&TEXT(ROW(A18),"000"))
A23: =IF(B23="","","DR-"&TEXT(ROW(A19),"000"))
A24: =IF(B24="","","DR-"&TEXT(ROW(A20),"000"))
A25: =IF(B25="","","DR-"&TEXT(ROW(A21),"000"))
A26: =IF(B26="","","DR-"&TEXT(ROW(A22),"000"))
... A104: =IF(B104="","","DR-"&TEXT(ROW(A100),"000"))

Sheet SVC_RateCard
A2: CityMed Multi-Specialty Hospital — Services & Rate Card
A4: Service_Code | B4: Service_Nmae | C4: Category | D4: Department | E4: Unit | F4: Base_Rate (₹) | G4: GST_% | H4: GST_Amount (₹) | I4: Total_Rate (₹) | J4: Insurance_Coverd | K4: Status
A5: =IF(B5="","","SVC-"&TEXT(ROW(A1),"0000")) -> SVC-0001 | B5: General Consultation | C5: Consultation | D5: General Medicine | E5: Per Visit | F5: 500 | G5: 0 | H5: =IF(F5="","",F5*G5/100) -> 0 | I5: =IF(F5="","",F5+H5) -> 500 | J5: Yes | K5: Active
A6: =IF(B6="","","SVC-"&TEXT(ROW(A2),"0000")) -> SVC-0002 | B6: Cardiology Consultation | C6: Consultation | D6: Cardiology | E6: Per Visit | F6: 800 | G6: 0 | H6: =IF(F6="","",F6*G6/100) -> 0 | I6: =IF(F6="","",F6+H6) -> 800 | J6: Yes | K6: Active
A7: =IF(B7="","","SVC-"&TEXT(ROW(A3),"0000")) -> SVC-0003 | B7: Paediatrics Consultation | C7: Consultation | D7: Paediatrics | E7: Per Visit | F7: 600 | G7: 0 | H7: =IF(F7="","",F7*G7/100) -> 0 | I7: =IF(F7="","",F7+H7) -> 600 | J7: Yes | K7: Active
A8: =IF(B8="","","SVC-"&TEXT(ROW(A4),"0000")) -> SVC-0004 | B8: Orthopaedics Consultation | C8: Consultation | D8: Orthopaedics | E8: Per Visit | F8: 650 | G8: 0 | H8: =IF(F8="","",F8*G8/100) -> 0 | I8: =IF(F8="","",F8+H8) -> 650 | J8: Yes | K8: Active
A9: =IF(B9="","","SVC-"&TEXT(ROW(A5),"0000")) -> SVC-0005 | B9: Gynaecology Consultation | C9: Consultation | D9: Gynaecology | E9: Per Visit | F9: 700 | G9: 0 | H9: =IF(F9="","",F9*G9/100) -> 0 | I9: =IF(F9="","",F9+H9) -> 700 | J9: Yes | K9: Active
A10: =IF(B10="","","SVC-"&TEXT(ROW(A6),"0000")) -> SVC-0006 | B10: Emergency Consultation | C10: Emergency | D10: Emergency | E10: Per Visit | F10: 1200 | G10: 0 | H10: =IF(F10="","",F10*G10/100) -> 0 | I10: =IF(F10="","",F10+H10) -> 1200 | J10: Yes | K10: Active
A11: =IF(B11="","","SVC-"&TEXT(ROW(A7),"0000")) -> SVC-0007 | B11: Complete Blood Count (CBC) | C11: Laboratory | D11: Diagnostics | E11: Per Test | F11: 350 | G11: 5 | H11: =IF(F11="","",F11*G11/100) -> 17.5 | I11: =IF(F11="","",F11+H11) -> 367.5 | J11: Yes | K11: Active
A12: =IF(B12="","","SVC-"&TEXT(ROW(A8),"0000")) -> SVC-0008 | B12: Blood Glucose - Fasting | C12: Laboratory | D12: Diagnostics | E12: Per Test | F12: 120 | G12: 5 | H12: =IF(F12="","",F12*G12/100) -> 6 | I12: =IF(F12="","",F12+H12) -> 126 | J12: Yes | K12: Active
A13: =IF(B13="","","SVC-"&TEXT(ROW(A9),"0000")) -> SVC-0009 | B13: HbA1c Test | C13: Laboratory | D13: Diagnostics | E13: Per Test | F13: 380 | G13: 5 | H13: =IF(F13="","",F13*G13/100) -> 19 | I13: =IF(F13="","",F13+H13) -> 399 | J13: Yes | K13: Active
A14: =IF(B14="","","SVC-"&TEXT(ROW(A10),"0000")) -> SVC-0010 | B14: Lipid Profile | C14: Laboratory | D14: Diagnostics | E14: Per Test | F14: 450 | G14: 5 | H14: =IF(F14="","",F14*G14/100) -> 22.5 | I14: =IF(F14="","",F14+H14) -> 472.5 | J14: Yes | K14: Active
A15: =IF(B15="","","SVC-"&TEXT(ROW(A11),"0000")) -> SVC-0011 | B15: Liver Function Test | C15: Laboratory | D15: Diagnostics | E15: Per Test | F15: 520 | G15: 5 | H15: =IF(F15="","",F15*G15/100) -> 26 | I15: =IF(F15="","",F15+H15) -> 546 | J15: Yes | K15: Active
A16: =IF(B16="","","SVC-"&TEXT(ROW(A12),"0000")) -> SVC-0012 | B16: Kidney Function Test | C16: Laboratory | D16: Diagnostics | E16: Per Test | F16: 480 | G16: 5 | H16: =IF(F16="","",F16*G16/100) -> 24 | I16: =IF(F16="","",F16+H16) -> 504 | J16: Yes | K16: Active
... A54: =IF(B54="","","SVC-"&TEXT(ROW(A50),"0000")) -> SVC-0050 | B54: Endoscopy (Upper GI) | C54: Procedure | D54: General Medicine | E54: Per Procedure | F54: 3500 | G54: 5 | H54: =IF(F54="","",F54*G54/100) -> 175 | I54: =IF(F54="","",F54+H54) -> 3675 | J54: Partial | K54: Active
A55: =IF(B55="","","SVC-"&TEXT(ROW(A51),"0000")) | H55: =IF(F55="","",F55*G55/100) | I55: =IF(F55="","",F55+H55)
A56: =IF(B56="","","SVC-"&TEXT(ROW(A52),"0000")) | H56: =IF(F56="","",F56*G56/100) | I56: =IF(F56="","",F56+H56)
A57: =IF(B57="","","SVC-"&TEXT(ROW(A53),"0000")) | H57: =IF(F57="","",F57*G57/100) | I57: =IF(F57="","",F57+H57)
A58: =IF(B58="","","SVC-"&TEXT(ROW(A54),"0000")) | H58: =IF(F58="","",F58*G58/100) | I58: =IF(F58="","",F58+H58)
A59: =IF(B59="","","SVC-"&TEXT(ROW(A55),"0000")) | H59: =IF(F59="","",F59*G59/100) | I59: =IF(F59="","",F59+H59)
A60: =IF(B60="","","SVC-"&TEXT(ROW(A56),"0000")) | H60: =IF(F60="","",F60*G60/100) | I60: =IF(F60="","",F60+H60)
A61: =IF(B61="","","SVC-"&TEXT(ROW(A57),"0000")) | H61: =IF(F61="","",F61*G61/100) | I61: =IF(F61="","",F61+H61)
A62: =IF(B62="","","SVC-"&TEXT(ROW(A58),"0000")) | H62: =IF(F62="","",F62*G62/100) | I62: =IF(F62="","",F62+H62)
A63: =IF(B63="","","SVC-"&TEXT(ROW(A59),"0000")) | H63: =IF(F63="","",F63*G63/100) | I63: =IF(F63="","",F63+H63)
A64: =IF(B64="","","SVC-"&TEXT(ROW(A60),"0000")) | H64: =IF(F64="","",F64*G64/100) | I64: =IF(F64="","",F64+H64)
A65: =IF(B65="","","SVC-"&TEXT(ROW(A61),"0000")) | H65: =IF(F65="","",F65*G65/100) | I65: =IF(F65="","",F65+H65)
A66: =IF(B66="","","SVC-"&TEXT(ROW(A62),"0000")) | H66: =IF(F66="","",F66*G66/100) | I66: =IF(F66="","",F66+H66)
... A304: =IF(B304="","","SVC-"&TEXT(ROW(A300),"0000")) | H304: =IF(F304="","",F304*G304/100) | I304: =IF(F304="","",F304+H304)

Sheet BED_Master
A2: CityMed Multi-Specialty Hospital — Bed Inventory & Occupancy | B2: Column1 | C2: Column2 | D2: Column3 | E2: Column4 | F2: Column5 | G2: Column6 | H2: Column7 | I2: Column8 | J2: Column9
B3: Total Beds: | C3: =COUNTA(A5:A119) -> 115 | D3: Available: | E3: =COUNTIF(G5:G119,"Available") -> 15 | F3: Occupied: | G3: =COUNTIF(G5:G119,"Occupied") -> 12 | H3: Occupancy_Rate: | I3: =IF(C3=0,"",TEXT(G3/C3,"0%")) -> 10%
A4: Bed_ID | B4: Ward_Type | C4: Room_No | D4: Floor | E4: Department | F4: Daily_Rate (₹) | G4: Status | H4: Current_Patient_ID | I4: Patient_Name | J4: Admission_ID
A5: =IF(B5="","","BED-"&TEXT(ROW(A1),"000")) -> BED-001 | B5: General Ward | C5: G-101 | D5: 1 | E5: General Medicine | F5: 800 | G5: Available
A6: =IF(B6="","","BED-"&TEXT(ROW(A2),"000")) -> BED-002 | B6: General Ward | C6: G-102 | D6: 1 | E6: General Medicine | F6: 800 | G6: Occupied
A7: =IF(B7="","","BED-"&TEXT(ROW(A3),"000")) -> BED-003 | B7: General Ward | C7: G-103 | D7: 1 | E7: General Medicine | F7: 800 | G7: Available
A8: =IF(B8="","","BED-"&TEXT(ROW(A4),"000")) -> BED-004 | B8: General Ward | C8: G-104 | D8: 1 | E8: General Medicine | F8: 800 | G8: Occupied
A9: =IF(B9="","","BED-"&TEXT(ROW(A5),"000")) -> BED-005 | B9: General Ward | C9: G-105 | D9: 1 | E9: General Medicine | F9: 800 | G9: Available
A10: =IF(B10="","","BED-"&TEXT(ROW(A6),"000")) -> BED-006 | B10: General Ward | C10: G-106 | D10: 1 | E10: Paediatrics | F10: 800 | G10: Occupied
A11: =IF(B11="","","BED-"&TEXT(ROW(A7),"000")) -> BED-007 | B11: General Ward | C11: G-107 | D11: 1 | E11: Paediatrics | F11: 800 | G11: Available
A12: =IF(B12="","","BED-"&TEXT(ROW(A8),"000")) -> BED-008 | B12: General Ward | C12: G-108 | D12: 1 | E12: Paediatrics | F12: 800 | G12: Available
A13: =IF(B13="","","BED-"&TEXT(ROW(A9),"000")) -> BED-009 | B13: Semi-Private | C13: S-201 | D13: 2 | E13: General Medicine | F13: 1800 | G13: Occupied
A14: =IF(B14="","","BED-"&TEXT(ROW(A10),"000")) -> BED-010 | B14: Semi-Private | C14: S-202 | D14: 2 | E14: Cardiology | F14: 1800 | G14: Available
A15: =IF(B15="","","BED-"&TEXT(ROW(A11),"000")) -> BED-011 | B15: Semi-Private | C15: S-203 | D15: 2 | E15: Cardiology | F15: 1800 | G15: Occupied
A16: =IF(B16="","","BED-"&TEXT(ROW(A12),"000")) -> BED-012 | B16: Semi-Private | C16: S-204 | D16: 2 | E16: Orthopaedics | F16: 1800 | G16: Available
... A34: =IF(B34="","","BED-"&TEXT(ROW(A30),"000")) -> BED-030 | B34: Emergency | C34: EM-03 | D34: 1 | E34: Emergency | F34: 2000 | G34: Available
A35: =IF(B35="","","BED-"&TEXT(ROW(A31),"000"))
A36: =IF(B36="","","BED-"&TEXT(ROW(A32),"000"))
A37: =IF(B37="","","BED-"&TEXT(ROW(A33),"000"))
A38: =IF(B38="","","BED-"&TEXT(ROW(A34),"000"))
A39: =IF(B39="","","BED-"&TEXT(ROW(A35),"000"))
A40: =IF(B40="","","BED-"&TEXT(ROW(A36),"000"))
A41: =IF(B41="","","BED-"&TEXT(ROW(A37),"000"))
A42: =IF(B42="","","BED-"&TEXT(ROW(A38),"000"))
A43: =IF(B43="","","BED-"&TEXT(ROW(A39),"000"))
A44: =IF(B44="","","BED-"&TEXT(ROW(A40),"000"))
A45: =IF(B45="","","BED-"&TEXT(ROW(A41),"000"))
A46: =IF(B46="","","BED-"&TEXT(ROW(A42),"000"))
... A120: =IF(B120="","","BED-"&TEXT(ROW(A116),"000"))

Sheet ADM_Log
A2: CityMed Multi-Specialty Hospital — Admissions & OPD Log
A4: Admission_ID | B4: Patient_ID | C4: Patient_Name | D4: Visit_Type | E4: Admission_Date | F4: Discharge_Date | G4: Length_of_Stay | H4: Department | I4: Doctor_ID | J4: Doctor_Name | K4: Bed_ID | L4: Ward_Type | M4: Primary_Diagnosis | N4: ICD10_Code | O4: Status | P4: Referred_By | Q4: Enterd_By
A5: =IF(B5="","","ADM-"&TEXT(ROW(A1),"00000")) -> ADM-00001 | B5: PT-00001 | C5: =IF(B5="","",IFERROR(_xlfn.XLOOKUP(B5,PT_Master!A:A,PT_Master!C:C),"Patient ID not found")) -> Ananya Roy | D5: OPD | E5: 02/03/2026 | F5: 02/03/2026 | G5: =IF(OR(E5="",F5=""),"",MAX(0,DATEDIF(E5,F5,"D"))) -> 0 | H5: General Medicine | I5: DR-008 | J5: =IF(I5="","",IFERROR(_xlfn.XLOOKUP(I5,DR_Master!A:A,DR_Master!B:B),"Doctor ID not found")) -> Dr. Prabal Roy | L5: =IF(K5="","",IFERROR(_xlfn.XLOOKUP(K5,BED_Master!A:A,BED_Master!B:B),"Bed ID not found")) | M5: Atrial Fibrillation | N5: I48.9 | O5: Discharged | P5: Self | Q5: Billing Clerk
A6: =IF(B6="","","ADM-"&TEXT(ROW(A2),"00000")) -> ADM-00002 | B6: PT-00002 | C6: =IF(B6="","",IFERROR(_xlfn.XLOOKUP(B6,PT_Master!A:A,PT_Master!C:C),"Patient ID not found")) -> Rahul Sharma | D6: OPD | E6: 19/08/2025 | F6: 19/08/2025 | G6: =IF(OR(E6="",F6=""),"",MAX(0,DATEDIF(E6,F6,"D"))) -> 0 | H6: Orthopaedics | I6: DR-005 | J6: =IF(I6="","",IFERROR(_xlfn.XLOOKUP(I6,DR_Master!A:A,DR_Master!B:B),"Doctor ID not found")) -> Dr. Tanmoy Das | L6: =IF(K6="","",IFERROR(_xlfn.XLOOKUP(K6,BED_Master!A:A,BED_Master!B:B),"Bed ID not found")) | M6: Lumbar Disc Herniation | N6: M51.1 | O6: Discharged | P6: Online Booking | Q6: Receptionist
A7: =IF(B7="","","ADM-"&TEXT(ROW(A3),"00000")) -> ADM-00003 | B7: PT-00003 | C7: =IF(B7="","",IFERROR(_xlfn.XLOOKUP(B7,PT_Master!A:A,PT_Master!C:C),"Patient ID not found")) -> Priya Mehta | D7: OPD | E7: 11/03/2026 | F7: 11/03/2026 | G7: =IF(OR(E7="",F7=""),"",MAX(0,DATEDIF(E7,F7,"D"))) -> 0 | H7: General Medicine | I7: DR-003 | J7: =IF(I7="","",IFERROR(_xlfn.XLOOKUP(I7,DR_Master!A:A,DR_Master!B:B),"Doctor ID not found")) -> Dr. Sanjay Ghosh | L7: =IF(K7="","",IFERROR(_xlfn.XLOOKUP(K7,BED_Master!A:A,BED_Master!B:B),"Bed ID not found")) | M7: Paediatric Bronchitis | N7: J20.9 | O7: Discharged | P7: Specialist Referral | Q7: Admin Manager
A8: =IF(B8="","","ADM-"&TEXT(ROW(A4),"00000")) -> ADM-00004 | B8: PT-00004 | C8: =IF(B8="","",IFERROR(_xlfn.XLOOKUP(B8,PT_Master!A:A,PT_Master!C:C),"Patient ID not found")) -> Debasis Mondal | D8: Emergency | E8: 27/03/2026 | F8: 29/03/2026 | G8: =IF(OR(E8="",F8=""),"",MAX(0,DATEDIF(E8,F8,"D"))) -> 2 | H8: Orthopaedics | I8: DR-010 | J8: =IF(I8="","",IFERROR(_xlfn.XLOOKUP(I8,DR_Master!A:A,DR_Master!B:B),"Doctor ID not found")) -> Dr. Subhash Patra | L8: =IF(K8="","",IFERROR(_xlfn.XLOOKUP(K8,BED_Master!A:A,BED_Master!B:B),"Bed ID not found")) | M8: Neonatal Jaundice | N8: P59.9 | O8: Discharged | P8: Self | Q8: Receptionist
A9: =IF(B9="","","ADM-"&TEXT(ROW(A5),"00000")) -> ADM-00005 | B9: PT-00005 | C9: =IF(B9="","",IFERROR(_xlfn.XLOOKUP(B9,PT_Master!A:A,PT_Master!C:C),"Patient ID not found")) -> Sneha Das | D9: IPD | E9: 04/10/2025 | F9: 15/10/2025 | G9: =IF(OR(E9="",F9=""),"",MAX(0,DATEDIF(E9,F9,"D"))) -> 11 | H9: General Medicine | I9: DR-008 | J9: =IF(I9="","",IFERROR(_xlfn.XLOOKUP(I9,DR_Master!A:A,DR_Master!B:B),"Doctor ID not found")) -> Dr. Prabal Roy | K9: BED-007 | L9: =IF(K9="","",IFERROR(_xlfn.XLOOKUP(K9,BED_Master!A:A,BED_Master!B:B),"Bed ID not found")) -> General Ward | M9: Hypertension | N9: I10 | O9: Discharged | P9: Self | Q9: Ward Nurse
A10: =IF(B10="","","ADM-"&TEXT(ROW(A6),"00000")) -> ADM-00006 | B10: PT-00006 | C10: =IF(B10="","",IFERROR(_xlfn.XLOOKUP(B10,PT_Master!A:A,PT_Master!C:C),"Patient ID not found")) -> Amit Gupta | D10: OPD | E10: 22/01/2026 | F10: 22/01/2026 | G10: =IF(OR(E10="",F10=""),"",MAX(0,DATEDIF(E10,F10,"D"))) -> 0 | H10: Cardiology | I10: DR-009 | J10: =IF(I10="","",IFERROR(_xlfn.XLOOKUP(I10,DR_Master!A:A,DR_Master!B:B),"Doctor ID not found")) -> Dr. Kamala Nair | L10: =IF(K10="","",IFERROR(_xlfn.XLOOKUP(K10,BED_Master!A:A,BED_Master!B:B),"Bed ID not found")) | M10: Lumbar Disc Herniation | N10: M51.1 | O10: Discharged | P10: Emergency | Q10: Billing Clerk
A11: =IF(B11="","","ADM-"&TEXT(ROW(A7),"00000")) -> ADM-00007 | B11: PT-00007 | C11: =IF(B11="","",IFERROR(_xlfn.XLOOKUP(B11,PT_Master!A:A,PT_Master!C:C),"Patient ID not found")) -> Kavita Singh | D11: IPD | E11: 17/01/2026 | F11: 25/01/2026 | G11: =IF(OR(E11="",F11=""),"",MAX(0,DATEDIF(E11,F11,"D"))) -> 8 | H11: Cardiology | I11: DR-001 | J11: =IF(I11="","",IFERROR(_xlfn.XLOOKUP(I11,DR_Master!A:A,DR_Master!B:B),"Doctor ID not found")) -> Dr. Arjun Bose | K11: BED-001 | L11: =IF(K11="","",IFERROR(_xlfn.XLOOKUP(K11,BED_Master!A:A,BED_Master!B:B),"Bed ID not found")) -> General Ward | M11: Urinary Tract Infection | N11: N39.0 | O11: Discharged | P11: Self | Q11: Billing Clerk
A12: =IF(B12="","","ADM-"&TEXT(ROW(A8),"00000")) -> ADM-00008 | B12: PT-00008 | C12: =IF(B12="","",IFERROR(_xlfn.XLOOKUP(B12,PT_Master!A:A,PT_Master!C:C),"Patient ID not found")) -> Suresh Chatterjee | D12: OPD | E12: 10/09/2025 | F12: 10/09/2025 | G12: =IF(OR(E12="",F12=""),"",MAX(0,DATEDIF(E12,F12,"D"))) -> 0 | H12: Emergency | I12: DR-006 | J12: =IF(I12="","",IFERROR(_xlfn.XLOOKUP(I12,DR_Master!A:A,DR_Master!B:B),"Doctor ID not found")) -> Dr. Farhan Qureshi | L12: =IF(K12="","",IFERROR(_xlfn.XLOOKUP(K12,BED_Master!A:A,BED_Master!B:B),"Bed ID not found")) | M12: Febrile Seizure | N12: R56.0 | O12: Discharged | P12: GP Referral | Q12: Ward Nurse
A13: =IF(B13="","","ADM-"&TEXT(ROW(A9),"00000")) -> ADM-00009 | B13: PT-00009 | C13: =IF(B13="","",IFERROR(_xlfn.XLOOKUP(B13,PT_Master!A:A,PT_Master!C:C),"Patient ID not found")) -> Pooja Mukherjee | D13: OPD | E13: 25/11/2025 | F13: 25/11/2025 | G13: =IF(OR(E13="",F13=""),"",MAX(0,DATEDIF(E13,F13,"D"))) -> 0 | H13: Cardiology | I13: DR-009 | J13: =IF(I13="","",IFERROR(_xlfn.XLOOKUP(I13,DR_Master!A:A,DR_Master!B:B),"Doctor ID not found")) -> Dr. Kamala Nair | L13: =IF(K13="","",IFERROR(_xlfn.XLOOKUP(K13,BED_Master!A:A,BED_Master!B:B),"Bed ID not found")) | M13: Shoulder Dislocation | N13: S43.0 | O13: Discharged | P13: Emergency | Q13: Admin Manager
A14: =IF(B14="","","ADM-"&TEXT(ROW(A10),"00000")) -> ADM-00010 | B14: PT-00010 | C14: =IF(B14="","",IFERROR(_xlfn.XLOOKUP(B14,PT_Master!A:A,PT_Master!C:C),"Patient ID not found")) -> Arjun Bose | D14: OPD | E14: 14/02/2026 | F14: 14/02/2026 | G14: =IF(OR(E14="",F14=""),"",MAX(0,DATEDIF(E14,F14,"D"))) -> 0 | H14: Cardiology | I14: DR-001 | J14: =IF(I14="","",IFERROR(_xlfn.XLOOKUP(I14,DR_Master!A:A,DR_Master!B:B),"Doctor ID not found")) -> Dr. Arjun Bose | L14: =IF(K14="","",IFERROR(_xlfn.XLOOKUP(K14,BED_Master!A:A,BED_Master!B:B),"Bed ID not found")) | M14: Gestational Diabetes | N14: O24.4 | O14: Discharged | P14: Self | Q14: Billing Clerk
A15: =IF(B15="","","ADM-"&TEXT(ROW(A11),"00000")) -> ADM-00011 | B15: PT-00011 | C15: =IF(B15="","",IFERROR(_xlfn.XLOOKUP(B15,PT_Master!A:A,PT_Master!C:C),"Patient ID not found")) -> Meena Sen | D15: Emergency | E15: 11/10/2025 | F15: 12/10/2025 | G15: =IF(OR(E15="",F15=""),"",MAX(0,DATEDIF(E15,F15,"D"))) -> 1 | H15: Orthopaedics | I15: DR-010 | J15: =IF(I15="","",IFERROR(_xlfn.XLOOKUP(I15,DR_Master!A:A,DR_Master!B:B),"Doctor ID not found")) -> Dr. Subhash Patra | L15: =IF(K15="","",IFERROR(_xlfn.XLOOKUP(K15,BED_Master!A:A,BED_Master!B:B),"Bed ID not found")) | M15: Type 2 Diabetes Mellitus | N15: E11.9 | O15: Discharged | P15: Online Booking | Q15: Admin Manager
A16: =IF(B16="","","ADM-"&TEXT(ROW(A12),"00000")) -> ADM-00012 | B16: PT-00012 | C16: =IF(B16="","",IFERROR(_xlfn.XLOOKUP(B16,PT_Master!A:A,PT_Master!C:C),"Patient ID not found")) -> Vikram Ghosh | D16: IPD | E16: 14/08/2025 | F16: 17/08/2025 | G16: =IF(OR(E16="",F16=""),"",MAX(0,DATEDIF(E16,F16,"D"))) -> 3 | H16: Cardiology | I16: DR-001 | J16: =IF(I16="","",IFERROR(_xlfn.XLOOKUP(I16,DR_Master!A:A,DR_Master!B:B),"Doctor ID not found")) -> Dr. Arjun Bose | K16: BED-011 | L16: =IF(K16="","",IFERROR(_xlfn.XLOOKUP(K16,BED_Master!A:A,BED_Master!B:B),"Bed ID not found")) -> Semi-Private | M16: Asthma | N16: J45.9 | O16: Discharged | P16: Specialist Referral | Q16: Receptionist
A17: =IF(B17="","","ADM-"&TEXT(ROW(A13),"00000")) -> ADM-00013 | B17: PT-00013 | C17: =IF(B17="","",IFERROR(_xlfn.XLOOKUP(B17,PT_Master!A:A,PT_Master!C:C),"Patient ID not found")) -> Divya Banerjee | D17: IPD | E17: 13/02/2026 | F17: 16/02/2026 | G17: =IF(OR(E17="",F17=""),"",MAX(0,DATEDIF(E17,F17,"D"))) -> 3 | H17: General Medicine | I17: DR-008 | J17: =IF(I17="","",IFERROR(_xlfn.XLOOKUP(I17,DR_Master!A:A,DR_Master!B:B),"Doctor ID not found")) -> Dr. Prabal Roy | K17: BED-025 | L17: =IF(K17="","",IFERROR(_xlfn.XLOOKUP(K17,BED_Master!A:A,BED_Master!B:B),"Bed ID not found")) -> ICU | M17: Cholecystitis | N17: K81.0 | O17: Discharged | P17: Emergency | Q17: Billing Clerk
A18: =IF(B18="","","ADM-"&TEXT(ROW(A14),"00000")) -> ADM-00014 | B18: PT-00014 | C18: =IF(B18="","",IFERROR(_xlfn.XLOOKUP(B18,PT_Master!A:A,PT_Master!C:C),"Patient ID not found")) -> Rajan Dey | D18: OPD | E18: 01/11/2025 | F18: 01/11/2025 | G18: =IF(OR(E18="",F18=""),"",MAX(0,DATEDIF(E18,F18,"D"))) -> 0 | H18: Cardiology | I18: DR-009 | J18: =IF(I18="","",IFERROR(_xlfn.XLOOKUP(I18,DR_Master!A:A,DR_Master!B:B),"Doctor ID not found")) -> Dr. Kamala Nair | L18: =IF(K18="","",IFERROR(_xlfn.XLOOKUP(K18,BED_Master!A:A,BED_Master!B:B),"Bed ID not found")) | M18: Acute Gastroenteritis | N18: A09 | O18: Discharged | P18: Emergency | Q18: Ward Nurse
A19: =IF(B19="","","ADM-"&TEXT(ROW(A15),"00000")) -> ADM-00015 | B19: PT-00015 | C19: =IF(B19="","",IFERROR(_xlfn.XLOOKUP(B19,PT_Master!A:A,PT_Master!C:C),"Patient ID not found")) -> Sunita Pal | D19: OPD | E19: 07/04/2026 | F19: 07/04/2026 | G19: =IF(OR(E19="",F19=""),"",MAX(0,DATEDIF(E19,F19,"D"))) -> 0 | H19: General Medicine | I19: DR-003 | J19: =IF(I19="","",IFERROR(_xlfn.XLOOKUP(I19,DR_Master!A:A,DR_Master!B:B),"Doctor ID not found")) -> Dr. Sanjay Ghosh | L19: =IF(K19="","",IFERROR(_xlfn.XLOOKUP(K19,BED_Master!A:A,BED_Master!B:B),"Bed ID not found")) | M19: Unstable Angina | N19: I20.0 | O19: Discharged | P19: GP Referral | Q19: Ward Nurse
A20: =IF(B20="","","ADM-"&TEXT(ROW(A16),"00000")) -> ADM-00016 | B20: PT-00016 | C20: =IF(B20="","",IFERROR(_xlfn.XLOOKUP(B20,PT_Master!A:A,PT_Master!C:C),"Patient ID not found")) -> Ajay Nath | D20: OPD | E20: 21/04/2026 | F20: 21/04/2026 | G20: =IF(OR(E20="",F20=""),"",MAX(0,DATEDIF(E20,F20,"D"))) -> 0 | H20: Emergency | I20: DR-006 | J20: =IF(I20="","",IFERROR(_xlfn.XLOOKUP(I20,DR_Master!A:A,DR_Master!B:B),"Doctor ID not found")) -> Dr. Farhan Qureshi | L20: =IF(K20="","",IFERROR(_xlfn.XLOOKUP(K20,BED_Master!A:A,BED_Master!B:B),"Bed ID not found")) | M20: Hypertension | N20: I10 | O20: Discharged | P20: GP Referral | Q20: Ward Nurse
A21: =IF(B21="","","ADM-"&TEXT(ROW(A17),"00000")) -> ADM-00017 | B21: PT-00017 | C21: =IF(B21="","",IFERROR(_xlfn.XLOOKUP(B21,PT_Master!A:A,PT_Master!C:C),"Patient ID not found")) -> Nisha Saha | D21: OPD | E21: 06/08/2025 | F21: 06/08/2025 | G21: =IF(OR(E21="",F21=""),"",MAX(0,DATEDIF(E21,F21,"D"))) -> 0 | H21: Gynaecology | I21: DR-002 | J21: =IF(I21="","",IFERROR(_xlfn.XLOOKUP(I21,DR_Master!A:A,DR_Master!B:B),"Doctor ID not found")) -> Dr. Meena Pillai | L21: =IF(K21="","",IFERROR(_xlfn.XLOOKUP(K21,BED_Master!A:A,BED_Master!B:B),"Bed ID not found")) | M21: Neonatal Jaundice | N21: P59.9 | O21: Discharged | P21: Online Booking | Q21: Receptionist
A22: =IF(B22="","","ADM-"&TEXT(ROW(A18),"00000")) -> ADM-00018 | B22: PT-00018 | C22: =IF(B22="","",IFERROR(_xlfn.XLOOKUP(B22,PT_Master!A:A,PT_Master!C:C),"Patient ID not found")) -> Sanjay Biswas | D22: OPD | E22: 12/10/2025 | F22: 12/10/2025 | G22: =IF(OR(E22="",F22=""),"",MAX(0,DATEDIF(E22,F22,"D"))) -> 0 | H22: Orthopaedics | I22: DR-010 | J22: =IF(I22="","",IFERROR(_xlfn.XLOOKUP(I22,DR_Master!A:A,DR_Master!B:B),"Doctor ID not found")) -> Dr. Subhash Patra | L22: =IF(K22="","",IFERROR(_xlfn.XLOOKUP(K22,BED_Master!A:A,BED_Master!B:B),"Bed ID not found")) | M22: GERD | N22: K21.0 | O22: Discharged | P22: GP Referral | Q22: Ward Nurse
A23: =IF(B23="","","ADM-"&TEXT(ROW(A19),"00000")) -> ADM-00019 | B23: PT-00019 | C23: =IF(B23="","",IFERROR(_xlfn.XLOOKUP(B23,PT_Master!A:A,PT_Master!C:C),"Patient ID not found")) -> Rekha Chakraborty | D23: IPD | E23: 14/11/2025 | F23: 23/11/2025 | G23: =IF(OR(E23="",F23=""),"",MAX(0,DATEDIF(E23,F23,"D"))) -> 9 | H23: Orthopaedics | I23: DR-005 | J23: =IF(I23="","",IFERROR(_xlfn.XLOOKUP(I23,DR_Master!A:A,DR_Master!B:B),"Doctor ID not found")) -> Dr. Tanmoy Das | K23: BED-001 | L23: =IF(K23="","",IFERROR(_xlfn.XLOOKUP(K23,BED_Master!A:A,BED_Master!B:B),"Bed ID not found")) -> General Ward | M23: Cholecystitis | N23: K81.0 | O23: Active | P23: Specialist Referral | Q23: Receptionist
A24: =IF(B24="","","ADM-"&TEXT(ROW(A20),"00000")) -> ADM-00020 | B24: PT-00020 | C24: =IF(B24="","",IFERROR(_xlfn.XLOOKUP(B24,PT_Master!A:A,PT_Master!C:C),"Patient ID not found")) -> Manish Mitra | D24: OPD | E24: 16/04/2026 | F24: 16/04/2026 | G24: =IF(OR(E24="",F24=""),"",MAX(0,DATEDIF(E24,F24,"D"))) -> 0 | H24: Orthopaedics | I24: DR-005 | J24: =IF(I24="","",IFERROR(_xlfn.XLOOKUP(I24,DR_Master!A:A,DR_Master!B:B),"Doctor ID not found")) -> Dr. Tanmoy Das | L24: =IF(K24="","",IFERROR(_xlfn.XLOOKUP(K24,BED_Master!A:A,BED_Master!B:B),"Bed ID not found")) | M24: Type 2 Diabetes Mellitus | N24: E11.9 | O24: Discharged | P24: Emergency | Q24: Receptionist
A25: =IF(B25="","","ADM-"&TEXT(ROW(A21),"00000")) -> ADM-00021 | B25: PT-00021 | C25: =IF(B25="","",IFERROR(_xlfn.XLOOKUP(B25,PT_Master!A:A,PT_Master!C:C),"Patient ID not found")) -> Geeta Paul | D25: IPD | E25: 12/03/2026 | F25: 19/03/2026 | G25: =IF(OR(E25="",F25=""),"",MAX(0,DATEDIF(E25,F25,"D"))) -> 7 | H25: Gynaecology | I25: DR-002 | J25: =IF(I25="","",IFERROR(_xlfn.XLOOKUP(I25,DR_Master!A:A,DR_Master!B:B),"Doctor ID not found")) -> Dr. Meena Pillai | K25: BED-009 | L25: =IF(K25="","",IFERROR(_xlfn.XLOOKUP(K25,BED_Master!A:A,BED_Master!B:B),"Bed ID not found")) -> Semi-Private | M25: Hypertension | N25: I10 | O25: Discharged | P25: Specialist Referral | Q25: Billing Clerk
A26: =IF(B26="","","ADM-"&TEXT(ROW(A22),"00000")) -> ADM-00022 | B26: PT-00022 | C26: =IF(B26="","",IFERROR(_xlfn.XLOOKUP(B26,PT_Master!A:A,PT_Master!C:C),"Patient ID not found")) -> Arun Karmakar | D26: IPD | E26: 07/10/2025 | F26: 15/10/2025 | G26: =IF(OR(E26="",F26=""),"",MAX(0,DATEDIF(E26,F26,"D"))) -> 8 | H26: Diagnostics | I26: DR-007 | J26: =IF(I26="","",IFERROR(_xlfn.XLOOKUP(I26,DR_Master!A:A,DR_Master!B:B),"Doctor ID not found")) -> Dr. Lipika Sen | K26: BED-011 | L26: =IF(K26="","",IFERROR(_xlfn.XLOOKUP(K26,BED_Master!A:A,BED_Master!B:B),"Bed ID not found")) -> Semi-Private | M26: COPD Exacerbation | N26: J44.1 | O26: Transferred | P26: Emergency | Q26: Receptionist
A27: =IF(B27="","","ADM-"&TEXT(ROW(A23),"00000")) -> ADM-00023 | B27: PT-00023 | C27: =IF(B27="","",IFERROR(_xlfn.XLOOKUP(B27,PT_Master!A:A,PT_Master!C:C),"Patient ID not found")) -> Lata Mandal | D27: OPD | E27: 05/04/2026 | F27: 05/04/2026 | G27: =IF(OR(E27="",F27=""),"",MAX(0,DATEDIF(E27,F27,"D"))) -> 0 | H27: Paediatrics | I27: DR-004 | J27: =IF(I27="","",IFERROR(_xlfn.XLOOKUP(I27,DR_Master!A:A,DR_Master!B:B),"Doctor ID not found")) -> Dr. Ritika Sharma | L27: =IF(K27="","",IFERROR(_xlfn.XLOOKUP(K27,BED_Master!A:A,BED_Master!B:B),"Bed ID not found")) | M27: Pancreatitis | N27: K85.9 | O27: Discharged | P27: Online Booking | Q27: Admin Manager
A28: =IF(B28="","","ADM-"&TEXT(ROW(A24),"00000")) -> ADM-00024 | B28: PT-00024 | C28: =IF(B28="","",IFERROR(_xlfn.XLOOKUP(B28,PT_Master!A:A,PT_Master!C:C),"Patient ID not found")) -> Deepak Sarkar | D28: IPD | E28: 13/11/2025 | F28: 21/11/2025 | G28: =IF(OR(E28="",F28=""),"",MAX(0,DATEDIF(E28,F28,"D"))) -> 8 | H28: Orthopaedics | I28: DR-005 | J28: =IF(I28="","",IFERROR(_xlfn.XLOOKUP(I28,DR_Master!A:A,DR_Master!B:B),"Doctor ID not found")) -> Dr. Tanmoy Das | K28: BED-013 | L28: =IF(K28="","",IFERROR(_xlfn.XLOOKUP(K28,BED_Master!A:A,BED_Master!B:B),"Bed ID not found")) -> Semi-Private | M28: Fracture Femur | N28: S72.0 | O28: Discharged | P28: Emergency | Q28: Ward Nurse
A29: =IF(B29="","","ADM-"&TEXT(ROW(A25),"00000")) -> ADM-00025 | B29: PT-00025 | C29: =IF(B29="","",IFERROR(_xlfn.XLOOKUP(B29,PT_Master!A:A,PT_Master!C:C),"Patient ID not found")) -> Shilpa Patra | D29: OPD | E29: 16/08/2025 | F29: 16/08/2025 | G29: =IF(OR(E29="",F29=""),"",MAX(0,DATEDIF(E29,F29,"D"))) -> 0 | H29: Orthopaedics | I29: DR-005 | J29: =IF(I29="","",IFERROR(_xlfn.XLOOKUP(I29,DR_Master!A:A,DR_Master!B:B),"Doctor ID not found")) -> Dr. Tanmoy Das | L29: =IF(K29="","",IFERROR(_xlfn.XLOOKUP(K29,BED_Master!A:A,BED_Master!B:B),"Bed ID not found")) | M29: Coronary Artery Disease | N29: I25.1 | O29: Discharged | P29: Online Booking | Q29: Admin Manager
A30: =IF(B30="","","ADM-"&TEXT(ROW(A26),"00000")) -> ADM-00026 | B30: PT-00026 | C30: =IF(B30="","",IFERROR(_xlfn.XLOOKUP(B30,PT_Master!A:A,PT_Master!C:C),"Patient ID not found")) -> Rajesh Haldar | D30: IPD | E30: 21/03/2026 | F30: 31/03/2026 | G30: =IF(OR(E30="",F30=""),"",MAX(0,DATEDIF(E30,F30,"D"))) -> 10 | H30: Cardiology | I30: DR-001 | J30: =IF(I30="","",IFERROR(_xlfn.XLOOKUP(I30,DR_Master!A:A,DR_Master!B:B),"Doctor ID not found")) -> Dr. Arjun Bose | K30: BED-024 | L30: =IF(K30="","",IFERROR(_xlfn.XLOOKUP(K30,BED_Master!A:A,BED_Master!B:B),"Bed ID not found")) -> ICU | M30: Acute Myocardial Infarction | N30: I21.9 | O30: Discharged | P30: Another Hospital | Q30: Ward Nurse
A31: =IF(B31="","","ADM-"&TEXT(ROW(A27),"00000")) -> ADM-00027 | B31: PT-00027 | C31: =IF(B31="","",IFERROR(_xlfn.XLOOKUP(B31,PT_Master!A:A,PT_Master!C:C),"Patient ID not found")) -> Asha Majumdar | D31: OPD | E31: 15/08/2025 | F31: 15/08/2025 | G31: =IF(OR(E31="",F31=""),"",MAX(0,DATEDIF(E31,F31,"D"))) -> 0 | H31: Gynaecology | I31: DR-002 | J31: =IF(I31="","",IFERROR(_xlfn.XLOOKUP(I31,DR_Master!A:A,DR_Master!B:B),"Doctor ID not found")) -> Dr. Meena Pillai | L31: =IF(K31="","",IFERROR(_xlfn.XLOOKUP(K31,BED_Master!A:A,BED_Master!B:B),"Bed ID not found")) | M31: Cellulitis | N31: L03.9 | O31: Discharged | P31: Specialist Referral | Q31: Billing Clerk
A32: =IF(B32="","","ADM-"&TEXT(ROW(A28),"00000")) -> ADM-00028 | B32: PT-00028 | C32: =IF(B32="","",IFERROR(_xlfn.XLOOKUP(B32,PT_Master!A:A,PT_Master!C:C),"Patient ID not found")) -> Vivek Bhattacharya | D32: OPD | E32: 26/02/2026 | F32: 26/02/2026 | G32: =IF(OR(E32="",F32=""),"",MAX(0,DATEDIF(E32,F32,"D"))) -> 0 | H32: Paediatrics | I32: DR-004 | J32: =IF(I32="","",IFERROR(_xlfn.XLOOKUP(I32,DR_Master!A:A,DR_Master!B:B),"Doctor ID not found")) -> Dr. Ritika Sharma | L32: =IF(K32="","",IFERROR(_xlfn.XLOOKUP(K32,BED_Master!A:A,BED_Master!B:B),"Bed ID not found")) | M32: Ischaemic Stroke | N32: I63.9 | O32: Discharged | P32: Emergency | Q32: Ward Nurse
A33: =IF(B33="","","ADM-"&TEXT(ROW(A29),"00000")) -> ADM-00029 | B33: PT-00029 | C33: =IF(B33="","",IFERROR(_xlfn.XLOOKUP(B33,PT_Master!A:A,PT_Master!C:C),"Patient ID not found")) -> Smita Chowdhury | D33: OPD | E33: 29/07/2025 | F33: 29/07/2025 | G33: =IF(OR(E33="",F33=""),"",MAX(0,DATEDIF(E33,F33,"D"))) -> 0 | H33: Cardiology | I33: DR-009 | J33: =IF(I33="","",IFERROR(_xlfn.XLOOKUP(I33,DR_Master!A:A,DR_Master!B:B),"Doctor ID not found")) -> Dr. Kamala Nair | L33: =IF(K33="","",IFERROR(_xlfn.XLOOKUP(K33,BED_Master!A:A,BED_Master!B:B),"Bed ID not found")) | M33: Viral Fever | N33: A99 | O33: Discharged | P33: Online Booking | Q33: Ward Nurse
A34: =IF(B34="","","ADM-"&TEXT(ROW(A30),"00000")) -> ADM-00030 | B34: PT-00030 | C34: =IF(B34="","",IFERROR(_xlfn.XLOOKUP(B34,PT_Master!A:A,PT_Master!C:C),"Patient ID not found")) -> Prakash Lahiri | D34: OPD | E34: 04/08/2025 | F34: 04/08/2025 | G34: =IF(OR(E34="",F34=""),"",MAX(0,DATEDIF(E34,F34,"D"))) -> 0 | H34: Orthopaedics | I34: DR-005 | J34: =IF(I34="","",IFERROR(_xlfn.XLOOKUP(I34,DR_Master!A:A,DR_Master!B:B),"Doctor ID not found")) -> Dr. Tanmoy Das | L34: =IF(K34="","",IFERROR(_xlfn.XLOOKUP(K34,BED_Master!A:A,BED_Master!B:B),"Bed ID not found")) | M34: Lumbar Disc Herniation | N34: M51.1 | O34: Discharged | P34: Corporate Tie-up | Q34: Receptionist
A35: =IF(B35="","","ADM-"&TEXT(ROW(A31),"00000")) -> ADM-00031 | B35: PT-00031 | C35: =IF(B35="","",IFERROR(_xlfn.XLOOKUP(B35,PT_Master!A:A,PT_Master!C:C),"Patient ID not found")) -> Usha Ganguly | D35: OPD | E35: 02/09/2025 | F35: 02/09/2025 | G35: =IF(OR(E35="",F35=""),"",MAX(0,DATEDIF(E35,F35,"D"))) -> 0 | H35: Paediatrics | I35: DR-004 | J35: =IF(I35="","",IFERROR(_xlfn.XLOOKUP(I35,DR_Master!A:A,DR_Master!B:B),"Doctor ID not found")) -> Dr. Ritika Sharma | L35: =IF(K35="","",IFERROR(_xlfn.XLOOKUP(K35,BED_Master!A:A,BED_Master!B:B),"Bed ID not found")) | M35: Septicaemia | N35: A41.9 | O35: Discharged | P35: Self | Q35: Ward Nurse
A36: =IF(B36="","","ADM-"&TEXT(ROW(A32),"00000")) -> ADM-00032 | B36: PT-00032 | C36: =IF(B36="","",IFERROR(_xlfn.XLOOKUP(B36,PT_Master!A:A,PT_Master!C:C),"Patient ID not found")) -> Nikhil Dutta | D36: OPD | E36: 13/11/2025 | F36: 13/11/2025 | G36: =IF(OR(E36="",F36=""),"",MAX(0,DATEDIF(E36,F36,"D"))) -> 0 | H36: Cardiology | I36: DR-001 | J36: =IF(I36="","",IFERROR(_xlfn.XLOOKUP(I36,DR_Master!A:A,DR_Master!B:B),"Doctor ID not found")) -> Dr. Arjun Bose | L36: =IF(K36="","",IFERROR(_xlfn.XLOOKUP(K36,BED_Master!A:A,BED_Master!B:B),"Bed ID not found")) | M36: Acute Myocardial Infarction | N36: I21.9 | O36: Discharged | P36: Another Hospital | Q36: Receptionist
A37: =IF(B37="","","ADM-"&TEXT(ROW(A33),"00000")) -> ADM-00033 | B37: PT-00033 | C37: =IF(B37="","",IFERROR(_xlfn.XLOOKUP(B37,PT_Master!A:A,PT_Master!C:C),"Patient ID not found")) -> Anjali Sanyal | D37: OPD | E37: 10/12/2025 | F37: 10/12/2025 | G37: =IF(OR(E37="",F37=""),"",MAX(0,DATEDIF(E37,F37,"D"))) -> 0 | H37: Paediatrics | I37: DR-004 | J37: =IF(I37="","",IFERROR(_xlfn.XLOOKUP(I37,DR_Master!A:A,DR_Master!B:B),"Doctor ID not found")) -> Dr. Ritika Sharma | L37: =IF(K37="","",IFERROR(_xlfn.XLOOKUP(K37,BED_Master!A:A,BED_Master!B:B),"Bed ID not found")) | M37: Dengue Fever | N37: A97.0 | O37: Discharged | P37: Online Booking | Q37: Admin Manager
A38: =IF(B38="","","ADM-"&TEXT(ROW(A34),"00000")) -> ADM-00034 | B38: PT-00034 | C38: =IF(B38="","",IFERROR(_xlfn.XLOOKUP(B38,PT_Master!A:A,PT_Master!C:C),"Patient ID not found")) -> Sunil Bhatt | D38: OPD | E38: 08/12/2025 | F38: 08/12/2025 | G38: =IF(OR(E38="",F38=""),"",MAX(0,DATEDIF(E38,F38,"D"))) -> 0 | H38: Emergency | I38: DR-006 | J38: =IF(I38="","",IFERROR(_xlfn.XLOOKUP(I38,DR_Master!A:A,DR_Master!B:B),"Doctor ID not found")) -> Dr. Farhan Qureshi | L38: =IF(K38="","",IFERROR(_xlfn.XLOOKUP(K38,BED_Master!A:A,BED_Master!B:B),"Bed ID not found")) | M38: Paediatric Bronchitis | N38: J20.9 | O38: Discharged | P38: Another Hospital | Q38: Admin Manager
A39: =IF(B39="","","ADM-"&TEXT(ROW(A35),"00000")) -> ADM-00035 | B39: PT-00035 | C39: =IF(B39="","",IFERROR(_xlfn.XLOOKUP(B39,PT_Master!A:A,PT_Master!C:C),"Patient ID not found")) -> Poonam Joshi | D39: IPD | E39: 05/05/2026 | F39: 16/05/2026 | G39: =IF(OR(E39="",F39=""),"",MAX(0,DATEDIF(E39,F39,"D"))) -> 11 | H39: Cardiology | I39: DR-001 | J39: =IF(I39="","",IFERROR(_xlfn.XLOOKUP(I39,DR_Master!A:A,DR_Master!B:B),"Doctor ID not found")) -> Dr. Arjun Bose | K39: BED-015 | L39: =IF(K39="","",IFERROR(_xlfn.XLOOKUP(K39,BED_Master!A:A,BED_Master!B:B),"Bed ID not found")) -> Semi-Private | M39: Deep Vein Thrombosis | N39: I82.4 | O39: Active | P39: GP Referral | Q39: Billing Clerk
A40: =IF(B40="","","ADM-"&TEXT(ROW(A36),"00000")) -> ADM-00036 | B40: PT-00036 | C40: =IF(B40="","",IFERROR(_xlfn.XLOOKUP(B40,PT_Master!A:A,PT_Master!C:C),"Patient ID not found")) -> Hemant Patel | D40: IPD | E40: 27/11/2025 | F40: 30/11/2025 | G40: =IF(OR(E40="",F40=""),"",MAX(0,DATEDIF(E40,F40,"D"))) -> 3 | H40: Diagnostics | I40: DR-007 | J40: =IF(I40="","",IFERROR(_xlfn.XLOOKUP(I40,DR_Master!A:A,DR_Master!B:B),"Doctor ID not found")) -> Dr. Lipika Sen | K40: BED-023 | L40: =IF(K40="","",IFERROR(_xlfn.XLOOKUP(K40,BED_Master!A:A,BED_Master!B:B),"Bed ID not found")) -> ICU | M40: Unstable Angina | N40: I20.0 | O40: Discharged | P40: GP Referral | Q40: Ward Nurse
A41: =IF(B41="","","ADM-"&TEXT(ROW(A37),"00000")) -> ADM-00037 | B41: PT-00037 | C41: =IF(B41="","",IFERROR(_xlfn.XLOOKUP(B41,PT_Master!A:A,PT_Master!C:C),"Patient ID not found")) -> Madhuri Shah | D41: IPD | E41: 24/01/2026 | F41: 02/02/2026 | G41: =IF(OR(E41="",F41=""),"",MAX(0,DATEDIF(E41,F41,"D"))) -> 9 | H41: Orthopaedics | I41: DR-010 | J41: =IF(I41="","",IFERROR(_xlfn.XLOOKUP(I41,DR_Master!A:A,DR_Master!B:B),"Doctor ID not found")) -> Dr. Subhash Patra | K41: BED-016 | L41: =IF(K41="","",IFERROR(_xlfn.XLOOKUP(K41,BED_Master!A:A,BED_Master!B:B),"Bed ID not found")) -> Private | M41: Paediatric Bronchitis | N41: J20.9 | O41: Discharged | P41: Emergency | Q41: Receptionist
A42: =IF(B42="","","ADM-"&TEXT(ROW(A38),"00000")) -> ADM-00038 | B42: PT-00038 | C42: =IF(B42="","",IFERROR(_xlfn.XLOOKUP(B42,PT_Master!A:A,PT_Master!C:C),"Patient ID not found")) -> Girish Desai | D42: OPD | E42: 26/08/2025 | F42: 26/08/2025 | G42: =IF(OR(E42="",F42=""),"",MAX(0,DATEDIF(E42,F42,"D"))) -> 0 | H42: Orthopaedics | I42: DR-005 | J42: =IF(I42="","",IFERROR(_xlfn.XLOOKUP(I42,DR_Master!A:A,DR_Master!B:B),"Doctor ID not found")) -> Dr. Tanmoy Das | L42: =IF(K42="","",IFERROR(_xlfn.XLOOKUP(K42,BED_Master!A:A,BED_Master!B:B),"Bed ID not found")) | M42: Type 2 Diabetes Mellitus | N42: E11.9 | O42: Discharged | P42: Another Hospital | Q42: Admin Manager
A43: =IF(B43="","","ADM-"&TEXT(ROW(A39),"00000")) -> ADM-00039 | B43: PT-00039 | C43: =IF(B43="","",IFERROR(_xlfn.XLOOKUP(B43,PT_Master!A:A,PT_Master!C:C),"Patient ID not found")) -> Swati Pillai | D43: IPD | E43: 11/03/2026 | F43: 17/03/2026 | G43: =IF(OR(E43="",F43=""),"",MAX(0,DATEDIF(E43,F43,"D"))) -> 6 | H43: Cardiology | I43: DR-001 | J43: =IF(I43="","",IFERROR(_xlfn.XLOOKUP(I43,DR_Master!A:A,DR_Master!B:B),"Doctor ID not found")) -> Dr. Arjun Bose | K43: BED-023 | L43: =IF(K43="","",IFERROR(_xlfn.XLOOKUP(K43,BED_Master!A:A,BED_Master!B:B),"Bed ID not found")) -> ICU | M43: Type 2 Diabetes Mellitus | N43: E11.9 | O43: Discharged | P43: Online Booking | Q43: Ward Nurse
A44: =IF(B44="","","ADM-"&TEXT(ROW(A40),"00000")) -> ADM-00040 | B44: PT-00040 | C44: =IF(B44="","",IFERROR(_xlfn.XLOOKUP(B44,PT_Master!A:A,PT_Master!C:C),"Patient ID not found")) -> Ravi Nair | D44: OPD | E44: 29/04/2026 | F44: 29/04/2026 | G44: =IF(OR(E44="",F44=""),"",MAX(0,DATEDIF(E44,F44,"D"))) -> 0 | H44: Emergency | I44: DR-006 | J44: =IF(I44="","",IFERROR(_xlfn.XLOOKUP(I44,DR_Master!A:A,DR_Master!B:B),"Doctor ID not found")) -> Dr. Farhan Qureshi | L44: =IF(K44="","",IFERROR(_xlfn.XLOOKUP(K44,BED_Master!A:A,BED_Master!B:B),"Bed ID not found")) | M44: Viral Fever | N44: A99 | O44: Discharged | P44: Another Hospital | Q44: Ward Nurse
A45: =IF(B45="","","ADM-"&TEXT(ROW(A41),"00000")) -> ADM-00041 | B45: PT-00041 | C45: =IF(B45="","",IFERROR(_xlfn.XLOOKUP(B45,PT_Master!A:A,PT_Master!C:C),"Patient ID not found")) -> Shreya Menon | D45: IPD | E45: 21/10/2025 | F45: 28/10/2025 | G45: =IF(OR(E45="",F45=""),"",MAX(0,DATEDIF(E45,F45,"D"))) -> 7 | H45: Orthopaedics | I45: DR-005 | J45: =IF(I45="","",IFERROR(_xlfn.XLOOKUP(I45,DR_Master!A:A,DR_Master!B:B),"Doctor ID not found")) -> Dr. Tanmoy Das | K45: BED-026 | L45: =IF(K45="","",IFERROR(_xlfn.XLOOKUP(K45,BED_Master!A:A,BED_Master!B:B),"Bed ID not found")) -> ICU | M45: Unstable Angina | N45: I20.0 | O45: Discharged | P45: Specialist Referral | Q45: Admin Manager
A46: =IF(B46="","","ADM-"&TEXT(ROW(A42),"00000")) -> ADM-00042 | B46: PT-00042 | C46: =IF(B46="","",IFERROR(_xlfn.XLOOKUP(B46,PT_Master!A:A,PT_Master!C:C),"Patient ID not found")) -> Tarun Iyer | D46: IPD | E46: 06/02/2026 | F46: 15/02/2026 | G46: =IF(OR(E46="",F46=""),"",MAX(0,DATEDIF(E46,F46,"D"))) -> 9 | H46: Orthopaedics | I46: DR-005 | J46: =IF(I46="","",IFERROR(_xlfn.XLOOKUP(I46,DR_Master!A:A,DR_Master!B:B),"Doctor ID not found")) -> Dr. Tanmoy Das | K46: BED-014 | L46: =IF(K46="","",IFERROR(_xlfn.XLOOKUP(K46,BED_Master!A:A,BED_Master!B:B),"Bed ID not found")) -> Semi-Private | M46: Ischaemic Stroke | N46: I63.9 | O46: Discharged | P46: Emergency | Q46: Admin Manager
A47: =IF(B47="","","ADM-"&TEXT(ROW(A43),"00000")) -> ADM-00043 | B47: PT-00043 | C47: =IF(B47="","",IFERROR(_xlfn.XLOOKUP(B47,PT_Master!A:A,PT_Master!C:C),"Patient ID not found")) -> Neha Rao | D47: OPD | E47: 06/01/2026 | F47: 06/01/2026 | G47: =IF(OR(E47="",F47=""),"",MAX(0,DATEDIF(E47,F47,"D"))) -> 0 | H47: Emergency | I47: DR-006 | J47: =IF(I47="","",IFERROR(_xlfn.XLOOKUP(I47,DR_Master!A:A,DR_Master!B:B),"Doctor ID not found")) -> Dr. Farhan Qureshi | L47: =IF(K47="","",IFERROR(_xlfn.XLOOKUP(K47,BED_Master!A:A,BED_Master!B:B),"Bed ID not found")) | M47: Deep Vein Thrombosis | N47: I82.4 | O47: Discharged | P47: Specialist Referral | Q47: Receptionist
A48: =IF(B48="","","ADM-"&TEXT(ROW(A44),"00000")) -> ADM-00044 | B48: PT-00044 | C48: =IF(B48="","",IFERROR(_xlfn.XLOOKUP(B48,PT_Master!A:A,PT_Master!C:C),"Patient ID not found")) -> Bhaskar Reddy | D48: OPD | E48: 28/10/2025 | F48: 28/10/2025 | G48: =IF(OR(E48="",F48=""),"",MAX(0,DATEDIF(E48,F48,"D"))) -> 0 | H48: Paediatrics | I48: DR-004 | J48: =IF(I48="","",IFERROR(_xlfn.XLOOKUP(I48,DR_Master!A:A,DR_Master!B:B),"Doctor ID not found")) -> Dr. Ritika Sharma | L48: =IF(K48="","",IFERROR(_xlfn.XLOOKUP(K48,BED_Master!A:A,BED_Master!B:B),"Bed ID not found")) | M48: Atrial Fibrillation | N48: I48.9 | O48: Discharged | P48: Corporate Tie-up | Q48: Admin Manager
A49: =IF(B49="","","ADM-"&TEXT(ROW(A45),"00000")) -> ADM-00045 | B49: PT-00045 | C49: =IF(B49="","",IFERROR(_xlfn.XLOOKUP(B49,PT_Master!A:A,PT_Master!C:C),"Patient ID not found")) -> Jyoti Kumar | D49: OPD | E49: 23/04/2026 | F49: 23/04/2026 | G49: =IF(OR(E49="",F49=""),"",MAX(0,DATEDIF(E49,F49,"D"))) -> 0 | H49: Emergency | I49: DR-006 | J49: =IF(I49="","",IFERROR(_xlfn.XLOOKUP(I49,DR_Master!A:A,DR_Master!B:B),"Doctor ID not found")) -> Dr. Farhan Qureshi | L49: =IF(K49="","",IFERROR(_xlfn.XLOOKUP(K49,BED_Master!A:A,BED_Master!B:B),"Bed ID not found")) | M49: Hypothyroidism | N49: E03.9 | O49: Discharged | P49: Another Hospital | Q49: Receptionist
A50: =IF(B50="","","ADM-"&TEXT(ROW(A46),"00000")) -> ADM-00046 | B50: PT-00046 | C50: =IF(B50="","",IFERROR(_xlfn.XLOOKUP(B50,PT_Master!A:A,PT_Master!C:C),"Patient ID not found")) -> Alok Verma | D50: IPD | E50: 04/07/2025 | F50: 07/07/2025 | G50: =IF(OR(E50="",F50=""),"",MAX(0,DATEDIF(E50,F50,"D"))) -> 3 | H50: Diagnostics | I50: DR-007 | J50: =IF(I50="","",IFERROR(_xlfn.XLOOKUP(I50,DR_Master!A:A,DR_Master!B:B),"Doctor ID not found")) -> Dr. Lipika Sen | K50: BED-012 | L50: =IF(K50="","",IFERROR(_xlfn.XLOOKUP(K50,BED_Master!A:A,BED_Master!B:B),"Bed ID not found")) -> Semi-Private | M50: Pancreatitis | N50: K85.9 | O50: Active | P50: Online Booking | Q50: Ward Nurse
A51: =IF(B51="","","ADM-"&TEXT(ROW(A47),"00000")) -> ADM-00047 | B51: PT-00047 | C51: =IF(B51="","",IFERROR(_xlfn.XLOOKUP(B51,PT_Master!A:A,PT_Master!C:C),"Patient ID not found")) -> Seema Mishra | D51: OPD | E51: 11/07/2025 | F51: 11/07/2025 | G51: =IF(OR(E51="",F51=""),"",MAX(0,DATEDIF(E51,F51,"D"))) -> 0 | H51: Cardiology | I51: DR-001 | J51: =IF(I51="","",IFERROR(_xlfn.XLOOKUP(I51,DR_Master!A:A,DR_Master!B:B),"Doctor ID not found")) -> Dr. Arjun Bose | L51: =IF(K51="","",IFERROR(_xlfn.XLOOKUP(K51,BED_Master!A:A,BED_Master!B:B),"Bed ID not found")) | M51: Epilepsy | N51: G40.9 | O51: Discharged | P51: Another Hospital | Q51: Ward Nurse
A52: =IF(B52="","","ADM-"&TEXT(ROW(A48),"00000")) -> ADM-00048 | B52: PT-00048 | C52: =IF(B52="","",IFERROR(_xlfn.XLOOKUP(B52,PT_Master!A:A,PT_Master!C:C),"Patient ID not found")) -> Varun Tiwari | D52: OPD | E52: 17/07/2025 | F52: 17/07/2025 | G52: =IF(OR(E52="",F52=""),"",MAX(0,DATEDIF(E52,F52,"D"))) -> 0 | H52: General Medicine | I52: DR-003 | J52: =IF(I52="","",IFERROR(_xlfn.XLOOKUP(I52,DR_Master!A:A,DR_Master!B:B),"Doctor ID not found")) -> Dr. Sanjay Ghosh | L52: =IF(K52="","",IFERROR(_xlfn.XLOOKUP(K52,BED_Master!A:A,BED_Master!B:B),"Bed ID not found")) | M52: Type 2 Diabetes Mellitus | N52: E11.9 | O52: Discharged | P52: GP Referral | Q52: Admin Manager
A53: =IF(B53="","","ADM-"&TEXT(ROW(A49),"00000")) -> ADM-00049 | B53: PT-00049 | C53: =IF(B53="","",IFERROR(_xlfn.XLOOKUP(B53,PT_Master!A:A,PT_Master!C:C),"Patient ID not found")) -> Pallavi Pandey | D53: IPD | E53: 29/04/2026 | F53: 01/05/2026 | G53: =IF(OR(E53="",F53=""),"",MAX(0,DATEDIF(E53,F53,"D"))) -> 2 | H53: Cardiology | I53: DR-001 | J53: =IF(I53="","",IFERROR(_xlfn.XLOOKUP(I53,DR_Master!A:A,DR_Master!B:B),"Doctor ID not found")) -> Dr. Arjun Bose | K53: BED-025 | L53: =IF(K53="","",IFERROR(_xlfn.XLOOKUP(K53,BED_Master!A:A,BED_Master!B:B),"Bed ID not found")) -> ICU | M53: Migraine | N53: G43.9 | O53: Transferred | P53: GP Referral | Q53: Billing Clerk
A54: =IF(B54="","","ADM-"&TEXT(ROW(A50),"00000")) -> ADM-00050 | B54: PT-00050 | C54: =IF(B54="","",IFERROR(_xlfn.XLOOKUP(B54,PT_Master!A:A,PT_Master!C:C),"Patient ID not found")) -> Rohit Dubey | D54: IPD | E54: 31/08/2025 | F54: 07/09/2025 | G54: =IF(OR(E54="",F54=""),"",MAX(0,DATEDIF(E54,F54,"D"))) -> 7 | H54: Cardiology | I54: DR-009 | J54: =IF(I54="","",IFERROR(_xlfn.XLOOKUP(I54,DR_Master!A:A,DR_Master!B:B),"Doctor ID not found")) -> Dr. Kamala Nair | K54: BED-021 | L54: =IF(K54="","",IFERROR(_xlfn.XLOOKUP(K54,BED_Master!A:A,BED_Master!B:B),"Bed ID not found")) -> Private | M54: Ischaemic Stroke | N54: I63.9 | O54: Transferred | P54: Specialist Referral | Q54: Admin Manager
A55: =IF(B55="","","ADM-"&TEXT(ROW(A51),"00000")) -> ADM-00051 | B55: PT-00051 | C55: =IF(B55="","",IFERROR(_xlfn.XLOOKUP(B55,PT_Master!A:A,PT_Master!C:C),"Patient ID not found")) -> Sarita Shukla | D55: OPD | E55: 02/01/2026 | F55: 02/01/2026 | G55: =IF(OR(E55="",F55=""),"",MAX(0,DATEDIF(E55,F55,"D"))) -> 0 | H55: Orthopaedics | I55: DR-005 | J55: =IF(I55="","",IFERROR(_xlfn.XLOOKUP(I55,DR_Master!A:A,DR_Master!B:B),"Doctor ID not found")) -> Dr. Tanmoy Das | L55: =IF(K55="","",IFERROR(_xlfn.XLOOKUP(K55,BED_Master!A:A,BED_Master!B:B),"Bed ID not found")) | M55: Unstable Angina | N55: I20.0 | O55: Discharged | P55: GP Referral | Q55: Billing Clerk
A56: =IF(B56="","","ADM-"&TEXT(ROW(A52),"00000")) -> ADM-00052 | B56: PT-00052 | C56: =IF(B56="","",IFERROR(_xlfn.XLOOKUP(B56,PT_Master!A:A,PT_Master!C:C),"Patient ID not found")) -> Dinesh Yadav | D56: IPD | E56: 14/07/2025 | F56: 20/07/2025 | G56: =IF(OR(E56="",F56=""),"",MAX(0,DATEDIF(E56,F56,"D"))) -> 6 | H56: General Medicine | I56: DR-008 | J56: =IF(I56="","",IFERROR(_xlfn.XLOOKUP(I56,DR_Master!A:A,DR_Master!B:B),"Doctor ID not found")) -> Dr. Prabal Roy | K56: BED-010 | L56: =IF(K56="","",IFERROR(_xlfn.XLOOKUP(K56,BED_Master!A:A,BED_Master!B:B),"Bed ID not found")) -> Semi-Private | M56: Atrial Fibrillation | N56: I48.9 | O56: Discharged | P56: Self | Q56: Receptionist
A57: =IF(B57="","","ADM-"&TEXT(ROW(A53),"00000")) -> ADM-00053 | B57: PT-00053 | C57: =IF(B57="","",IFERROR(_xlfn.XLOOKUP(B57,PT_Master!A:A,PT_Master!C:C),"Patient ID not found")) -> Vandana Jain | D57: OPD | E57: 30/12/2025 | F57: 30/12/2025 | G57: =IF(OR(E57="",F57=""),"",MAX(0,DATEDIF(E57,F57,"D"))) -> 0 | H57: Cardiology | I57: DR-001 | J57: =IF(I57="","",IFERROR(_xlfn.XLOOKUP(I57,DR_Master!A:A,DR_Master!B:B),"Doctor ID not found")) -> Dr. Arjun Bose | L57: =IF(K57="","",IFERROR(_xlfn.XLOOKUP(K57,BED_Master!A:A,BED_Master!B:B),"Bed ID not found")) | M57: COPD Exacerbation | N57: J44.1 | O57: Discharged | P57: Emergency | Q57: Receptionist
A58: =IF(B58="","","ADM-"&TEXT(ROW(A54),"00000")) -> ADM-00054 | B58: PT-00054 | C58: =IF(B58="","",IFERROR(_xlfn.XLOOKUP(B58,PT_Master!A:A,PT_Master!C:C),"Patient ID not found")) -> Kiran Agarwal | D58: IPD | E58: 22/01/2026 | F58: 29/01/2026 | G58: =IF(OR(E58="",F58=""),"",MAX(0,DATEDIF(E58,F58,"D"))) -> 7 | H58: Cardiology | I58: DR-009 | J58: =IF(I58="","",IFERROR(_xlfn.XLOOKUP(I58,DR_Master!A:A,DR_Master!B:B),"Doctor ID not found")) -> Dr. Kamala Nair | K58: BED-020 | L58: =IF(K58="","",IFERROR(_xlfn.XLOOKUP(K58,BED_Master!A:A,BED_Master!B:B),"Bed ID not found")) -> Private | M58: Rotator Cuff Tear | N58: M75.1 | O58: Active | P58: Online Booking | Q58: Ward Nurse
A59: =IF(B59="","","ADM-"&TEXT(ROW(A55),"00000")) -> ADM-00055 | B59: PT-00055 | C59: =IF(B59="","",IFERROR(_xlfn.XLOOKUP(B59,PT_Master!A:A,PT_Master!C:C),"Patient ID not found")) -> Mohan Khanna | D59: OPD | E59: 23/10/2025 | F59: 23/10/2025 | G59: =IF(OR(E59="",F59=""),"",MAX(0,DATEDIF(E59,F59,"D"))) -> 0 | H59: General Medicine | I59: DR-008 | J59: =IF(I59="","",IFERROR(_xlfn.XLOOKUP(I59,DR_Master!A:A,DR_Master!B:B),"Doctor ID not found")) -> Dr. Prabal Roy | L59: =IF(K59="","",IFERROR(_xlfn.XLOOKUP(K59,BED_Master!A:A,BED_Master!B:B),"Bed ID not found")) | M59: Acute Gastroenteritis | N59: A09 | O59: Discharged | P59: GP Referral | Q59: Admin Manager
A60: =IF(B60="","","ADM-"&TEXT(ROW(A56),"00000")) -> ADM-00056 | B60: PT-00056 | C60: =IF(B60="","",IFERROR(_xlfn.XLOOKUP(B60,PT_Master!A:A,PT_Master!C:C),"Patient ID not found")) -> Lalita Malhotra | D60: OPD | E60: 17/09/2025 | F60: 17/09/2025 | G60: =IF(OR(E60="",F60=""),"",MAX(0,DATEDIF(E60,F60,"D"))) -> 0 | H60: General Medicine | I60: DR-003 | J60: =IF(I60="","",IFERROR(_xlfn.XLOOKUP(I60,DR_Master!A:A,DR_Master!B:B),"Doctor ID not found")) -> Dr. Sanjay Ghosh | L60: =IF(K60="","",IFERROR(_xlfn.XLOOKUP(K60,BED_Master!A:A,BED_Master!B:B),"Bed ID not found")) | M60: Acute Myocardial Infarction | N60: I21.9 | O60: Discharged | P60: Self | Q60: Billing Clerk
A61: =IF(B61="","","ADM-"&TEXT(ROW(A57),"00000")) -> ADM-00057 | B61: PT-00057 | C61: =IF(B61="","",IFERROR(_xlfn.XLOOKUP(B61,PT_Master!A:A,PT_Master!C:C),"Patient ID not found")) -> Gaurav Kapoor | D61: Emergency | E61: 19/10/2025 | F61: 20/10/2025 | G61: =IF(OR(E61="",F61=""),"",MAX(0,DATEDIF(E61,F61,"D"))) -> 1 | H61: Orthopaedics | I61: DR-010 | J61: =IF(I61="","",IFERROR(_xlfn.XLOOKUP(I61,DR_Master!A:A,DR_Master!B:B),"Doctor ID not found")) -> Dr. Subhash Patra | L61: =IF(K61="","",IFERROR(_xlfn.XLOOKUP(K61,BED_Master!A:A,BED_Master!B:B),"Bed ID not found")) | M61: Hypertension | N61: I10 | O61: Active | P61: Corporate Tie-up | Q61: Admin Manager
A62: =IF(B62="","","ADM-"&TEXT(ROW(A58),"00000")) -> ADM-00058 | B62: PT-00058 | C62: =IF(B62="","",IFERROR(_xlfn.XLOOKUP(B62,PT_Master!A:A,PT_Master!C:C),"Patient ID not found")) -> Preeti Bajaj | D62: IPD | E62: 19/08/2025 | F62: 21/08/2025 | G62: =IF(OR(E62="",F62=""),"",MAX(0,DATEDIF(E62,F62,"D"))) -> 2 | H62: General Medicine | I62: DR-003 | J62: =IF(I62="","",IFERROR(_xlfn.XLOOKUP(I62,DR_Master!A:A,DR_Master!B:B),"Doctor ID not found")) -> Dr. Sanjay Ghosh | K62: BED-023 | L62: =IF(K62="","",IFERROR(_xlfn.XLOOKUP(K62,BED_Master!A:A,BED_Master!B:B),"Bed ID not found")) -> ICU | M62: Pancreatitis | N62: K85.9 | O62: Transferred | P62: Specialist Referral | Q62: Ward Nurse
A63: =IF(B63="","","ADM-"&TEXT(ROW(A59),"00000")) -> ADM-00059 | B63: PT-00059 | C63: =IF(B63="","",IFERROR(_xlfn.XLOOKUP(B63,PT_Master!A:A,PT_Master!C:C),"Patient ID not found")) -> Ashok Chandra | D63: OPD | E63: 28/02/2026 | F63: 28/02/2026 | G63: =IF(OR(E63="",F63=""),"",MAX(0,DATEDIF(E63,F63,"D"))) -> 0 | H63: Paediatrics | I63: DR-004 | J63: =IF(I63="","",IFERROR(_xlfn.XLOOKUP(I63,DR_Master!A:A,DR_Master!B:B),"Doctor ID not found")) -> Dr. Ritika Sharma | L63: =IF(K63="","",IFERROR(_xlfn.XLOOKUP(K63,BED_Master!A:A,BED_Master!B:B),"Bed ID not found")) | M63: Epilepsy | N63: G40.9 | O63: Discharged | P63: Specialist Referral | Q63: Billing Clerk
A64: =IF(B64="","","ADM-"&TEXT(ROW(A60),"00000")) -> ADM-00060 | B64: PT-00060 | C64: =IF(B64="","",IFERROR(_xlfn.XLOOKUP(B64,PT_Master!A:A,PT_Master!C:C),"Patient ID not found")) -> Nandini Rathore | D64: IPD | E64: 17/10/2025 | F64: 22/10/2025 | G64: =IF(OR(E64="",F64=""),"",MAX(0,DATEDIF(E64,F64,"D"))) -> 5 | H64: Orthopaedics | I64: DR-005 | J64: =IF(I64="","",IFERROR(_xlfn.XLOOKUP(I64,DR_Master!A:A,DR_Master!B:B),"Doctor ID not found")) -> Dr. Tanmoy Das | K64: BED-009 | L64: =IF(K64="","",IFERROR(_xlfn.XLOOKUP(K64,BED_Master!A:A,BED_Master!B:B),"Bed ID not found")) -> Semi-Private | M64: Viral Fever | N64: A99 | O64: Active | P64: Corporate Tie-up | Q64: Billing Clerk
A65: =IF(B65="","","ADM-"&TEXT(ROW(A61),"00000")) -> ADM-00061 | B65: PT-00061 | C65: =IF(B65="","",IFERROR(_xlfn.XLOOKUP(B65,PT_Master!A:A,PT_Master!C:C),"Patient ID not found")) -> Manoj Roy | D65: OPD | E65: 30/11/2025 | F65: 30/11/2025 | G65: =IF(OR(E65="",F65=""),"",MAX(0,DATEDIF(E65,F65,"D"))) -> 0 | H65: Emergency | I65: DR-006 | J65: =IF(I65="","",IFERROR(_xlfn.XLOOKUP(I65,DR_Master!A:A,DR_Master!B:B),"Doctor ID not found")) -> Dr. Farhan Qureshi | L65: =IF(K65="","",IFERROR(_xlfn.XLOOKUP(K65,BED_Master!A:A,BED_Master!B:B),"Bed ID not found")) | M65: Fracture Femur | N65: S72.0 | O65: Discharged | P65: Self | Q65: Admin Manager
A66: =IF(B66="","","ADM-"&TEXT(ROW(A62),"00000")) -> ADM-00062 | B66: PT-00062 | C66: =IF(B66="","",IFERROR(_xlfn.XLOOKUP(B66,PT_Master!A:A,PT_Master!C:C),"Patient ID not found")) -> Sudha Sharma | D66: IPD | E66: 27/08/2025 | F66: 04/09/2025 | G66: =IF(OR(E66="",F66=""),"",MAX(0,DATEDIF(E66,F66,"D"))) -> 8 | H66: Diagnostics | I66: DR-007 | J66: =IF(I66="","",IFERROR(_xlfn.XLOOKUP(I66,DR_Master!A:A,DR_Master!B:B),"Doctor ID not found")) -> Dr. Lipika Sen | K66: BED-009 | L66: =IF(K66="","",IFERROR(_xlfn.XLOOKUP(K66,BED_Master!A:A,BED_Master!B:B),"Bed ID not found")) -> Semi-Private | M66: Septicaemia | N66: A41.9 | O66: Discharged | P66: GP Referral | Q66: Ward Nurse
A67: =IF(B67="","","ADM-"&TEXT(ROW(A63),"00000")) -> ADM-00063 | B67: PT-00063 | C67: =IF(B67="","",IFERROR(_xlfn.XLOOKUP(B67,PT_Master!A:A,PT_Master!C:C),"Patient ID not found")) -> Harish Mehta | D67: OPD | E67: 12/04/2026 | F67: 12/04/2026 | G67: =IF(OR(E67="",F67=""),"",MAX(0,DATEDIF(E67,F67,"D"))) -> 0 | H67: Cardiology | I67: DR-009 | J67: =IF(I67="","",IFERROR(_xlfn.XLOOKUP(I67,DR_Master!A:A,DR_Master!B:B),"Doctor ID not found")) -> Dr. Kamala Nair | L67: =IF(K67="","",IFERROR(_xlfn.XLOOKUP(K67,BED_Master!A:A,BED_Master!B:B),"Bed ID not found")) | M67: Unstable Angina | N67: I20.0 | O67: Discharged | P67: Another Hospital | Q67: Ward Nurse
A68: =IF(B68="","","ADM-"&TEXT(ROW(A64),"00000")) -> ADM-00064 | B68: PT-00064 | C68: =IF(B68="","",IFERROR(_xlfn.XLOOKUP(B68,PT_Master!A:A,PT_Master!C:C),"Patient ID not found")) -> Chhaya Mondal | D68: IPD | E68: 08/05/2026 | F68: 10/05/2026 | G68: =IF(OR(E68="",F68=""),"",MAX(0,DATEDIF(E68,F68,"D"))) -> 2 | H68: Diagnostics | I68: DR-007 | J68: =IF(I68="","",IFERROR(_xlfn.XLOOKUP(I68,DR_Master!A:A,DR_Master!B:B),"Doctor ID not found")) -> Dr. Lipika Sen | K68: BED-013 | L68: =IF(K68="","",IFERROR(_xlfn.XLOOKUP(K68,BED_Master!A:A,BED_Master!B:B),"Bed ID not found")) -> Semi-Private | M68: Septicaemia | N68: A41.9 | O68: Discharged | P68: Another Hospital | Q68: Receptionist
A69: =IF(B69="","","ADM-"&TEXT(ROW(A65),"00000")) -> ADM-00065 | B69: PT-00065 | C69: =IF(B69="","",IFERROR(_xlfn.XLOOKUP(B69,PT_Master!A:A,PT_Master!C:C),"Patient ID not found")) -> Ramesh Das | D69: IPD | E69: 05/02/2026 | F69: 13/02/2026 | G69: =IF(OR(E69="",F69=""),"",MAX(0,DATEDIF(E69,F69,"D"))) -> 8 | H69: Paediatrics | I69: DR-004 | J69: =IF(I69="","",IFERROR(_xlfn.XLOOKUP(I69,DR_Master!A:A,DR_Master!B:B),"Doctor ID not found")) -> Dr. Ritika Sharma | K69: BED-022 | L69: =IF(K69="","",IFERROR(_xlfn.XLOOKUP(K69,BED_Master!A:A,BED_Master!B:B),"Bed ID not found")) -> Private | M69: Gestational Diabetes | N69: O24.4 | O69: Discharged | P69: Self | Q69: Billing Clerk
A70: =IF(B70="","","ADM-"&TEXT(ROW(A66),"00000")) -> ADM-00066 | B70: PT-00066 | C70: =IF(B70="","",IFERROR(_xlfn.XLOOKUP(B70,PT_Master!A:A,PT_Master!C:C),"Patient ID not found")) -> Bharati Gupta | D70: IPD | E70: 20/12/2025 | F70: 24/12/2025 | G70: =IF(OR(E70="",F70=""),"",MAX(0,DATEDIF(E70,F70,"D"))) -> 4 | H70: Orthopaedics | I70: DR-005 | J70: =IF(I70="","",IFERROR(_xlfn.XLOOKUP(I70,DR_Master!A:A,DR_Master!B:B),"Doctor ID not found")) -> Dr. Tanmoy Das | K70: BED-008 | L70: =IF(K70="","",IFERROR(_xlfn.XLOOKUP(K70,BED_Master!A:A,BED_Master!B:B),"Bed ID not found")) -> General Ward | M70: Hypertension | N70: I10 | O70: Transferred | P70: Corporate Tie-up | Q70: Billing Clerk
A71: =IF(B71="","","ADM-"&TEXT(ROW(A67),"00000")) -> ADM-00067 | B71: PT-00067 | C71: =IF(B71="","",IFERROR(_xlfn.XLOOKUP(B71,PT_Master!A:A,PT_Master!C:C),"Patient ID not found")) -> Vishal Singh | D71: IPD | E71: 05/09/2025 | F71: 15/09/2025 | G71: =IF(OR(E71="",F71=""),"",MAX(0,DATEDIF(E71,F71,"D"))) -> 10 | H71: General Medicine | I71: DR-008 | J71: =IF(I71="","",IFERROR(_xlfn.XLOOKUP(I71,DR_Master!A:A,DR_Master!B:B),"Doctor ID not found")) -> Dr. Prabal Roy | K71: BED-004 | L71: =IF(K71="","",IFERROR(_xlfn.XLOOKUP(K71,BED_Master!A:A,BED_Master!B:B),"Bed ID not found")) -> General Ward | M71: Febrile Seizure | N71: R56.0 | O71: Discharged | P71: Specialist Referral | Q71: Receptionist
A72: =IF(B72="","","ADM-"&TEXT(ROW(A68),"00000")) -> ADM-00068 | B72: PT-00068 | C72: =IF(B72="","",IFERROR(_xlfn.XLOOKUP(B72,PT_Master!A:A,PT_Master!C:C),"Patient ID not found")) -> Kamla Chatterjee | D72: IPD | E72: 09/11/2025 | F72: 11/11/2025 | G72: =IF(OR(E72="",F72=""),"",MAX(0,DATEDIF(E72,F72,"D"))) -> 2 | H72: Orthopaedics | I72: DR-010 | J72: =IF(I72="","",IFERROR(_xlfn.XLOOKUP(I72,DR_Master!A:A,DR_Master!B:B),"Doctor ID not found")) -> Dr. Subhash Patra | K72: BED-004 | L72: =IF(K72="","",IFERROR(_xlfn.XLOOKUP(K72,BED_Master!A:A,BED_Master!B:B),"Bed ID not found")) -> General Ward | M72: Acute Appendicitis | N72: K37 | O72: LAMA | P72: Specialist Referral | Q72: Receptionist
A73: =IF(B73="","","ADM-"&TEXT(ROW(A69),"00000")) -> ADM-00069 | B73: PT-00069 | C73: =IF(B73="","",IFERROR(_xlfn.XLOOKUP(B73,PT_Master!A:A,PT_Master!C:C),"Patient ID not found")) -> Abhishek Mukherjee | D73: OPD | E73: 24/10/2025 | F73: 24/10/2025 | G73: =IF(OR(E73="",F73=""),"",MAX(0,DATEDIF(E73,F73,"D"))) -> 0 | H73: Orthopaedics | I73: DR-010 | J73: =IF(I73="","",IFERROR(_xlfn.XLOOKUP(I73,DR_Master!A:A,DR_Master!B:B),"Doctor ID not found")) -> Dr. Subhash Patra | L73: =IF(K73="","",IFERROR(_xlfn.XLOOKUP(K73,BED_Master!A:A,BED_Master!B:B),"Bed ID not found")) | M73: Osteoarthritis Knee | N73: M17.1 | O73: Discharged | P73: Self | Q73: Billing Clerk
A74: =IF(B74="","","ADM-"&TEXT(ROW(A70),"00000")) -> ADM-00070 | B74: PT-00070 | C74: =IF(B74="","",IFERROR(_xlfn.XLOOKUP(B74,PT_Master!A:A,PT_Master!C:C),"Patient ID not found")) -> Shanta Bose | D74: IPD | E74: 28/04/2026 | F74: 05/05/2026 | G74: =IF(OR(E74="",F74=""),"",MAX(0,DATEDIF(E74,F74,"D"))) -> 7 | H74: Emergency | I74: DR-006 | J74: =IF(I74="","",IFERROR(_xlfn.XLOOKUP(I74,DR_Master!A:A,DR_Master!B:B),"Doctor ID not found")) -> Dr. Farhan Qureshi | K74: BED-008 | L74: =IF(K74="","",IFERROR(_xlfn.XLOOKUP(K74,BED_Master!A:A,BED_Master!B:B),"Bed ID not found")) -> General Ward | M74: Neonatal Jaundice | N74: P59.9 | O74: Discharged | P74: Emergency | Q74: Admin Manager
A75: =IF(B75="","","ADM-"&TEXT(ROW(A71),"00000")) -> ADM-00071 | B75: PT-00071 | C75: =IF(B75="","",IFERROR(_xlfn.XLOOKUP(B75,PT_Master!A:A,PT_Master!C:C),"Patient ID not found")) -> Nilesh Sen | D75: OPD | E75: 11/10/2025 | F75: 11/10/2025 | G75: =IF(OR(E75="",F75=""),"",MAX(0,DATEDIF(E75,F75,"D"))) -> 0 | H75: Orthopaedics | I75: DR-010 | J75: =IF(I75="","",IFERROR(_xlfn.XLOOKUP(I75,DR_Master!A:A,DR_Master!B:B),"Doctor ID not found")) -> Dr. Subhash Patra | L75: =IF(K75="","",IFERROR(_xlfn.XLOOKUP(K75,BED_Master!A:A,BED_Master!B:B),"Bed ID not found")) | M75: Typhoid Fever | N75: A01.0 | O75: Discharged | P75: Another Hospital | Q75: Receptionist
A76: =IF(B76="","","ADM-"&TEXT(ROW(A72),"00000")) -> ADM-00072 | B76: PT-00072 | C76: =IF(B76="","",IFERROR(_xlfn.XLOOKUP(B76,PT_Master!A:A,PT_Master!C:C),"Patient ID not found")) -> Rupal Ghosh | D76: OPD | E76: 05/03/2026 | F76: 05/03/2026 | G76: =IF(OR(E76="",F76=""),"",MAX(0,DATEDIF(E76,F76,"D"))) -> 0 | H76: Orthopaedics | I76: DR-010 | J76: =IF(I76="","",IFERROR(_xlfn.XLOOKUP(I76,DR_Master!A:A,DR_Master!B:B),"Doctor ID not found")) -> Dr. Subhash Patra | L76: =IF(K76="","",IFERROR(_xlfn.XLOOKUP(K76,BED_Master!A:A,BED_Master!B:B),"Bed ID not found")) | M76: Pancreatitis | N76: K85.9 | O76: Discharged | P76: Corporate Tie-up | Q76: Receptionist
A77: =IF(B77="","","ADM-"&TEXT(ROW(A73),"00000")) -> ADM-00073 | B77: PT-00073 | C77: =IF(B77="","",IFERROR(_xlfn.XLOOKUP(B77,PT_Master!A:A,PT_Master!C:C),"Patient ID not found")) -> Saurabh Banerjee | D77: OPD | E77: 17/02/2026 | F77: 17/02/2026 | G77: =IF(OR(E77="",F77=""),"",MAX(0,DATEDIF(E77,F77,"D"))) -> 0 | H77: Orthopaedics | I77: DR-005 | J77: =IF(I77="","",IFERROR(_xlfn.XLOOKUP(I77,DR_Master!A:A,DR_Master!B:B),"Doctor ID not found")) -> Dr. Tanmoy Das | L77: =IF(K77="","",IFERROR(_xlfn.XLOOKUP(K77,BED_Master!A:A,BED_Master!B:B),"Bed ID not found")) | M77: Typhoid Fever | N77: A01.0 | O77: Discharged | P77: GP Referral | Q77: Billing Clerk
A78: =IF(B78="","","ADM-"&TEXT(ROW(A74),"00000")) -> ADM-00074 | B78: PT-00074 | C78: =IF(B78="","",IFERROR(_xlfn.XLOOKUP(B78,PT_Master!A:A,PT_Master!C:C),"Patient ID not found")) -> Taruna Dey | D78: OPD | E78: 19/02/2026 | F78: 19/02/2026 | G78: =IF(OR(E78="",F78=""),"",MAX(0,DATEDIF(E78,F78,"D"))) -> 0 | H78: Gynaecology | I78: DR-002 | J78: =IF(I78="","",IFERROR(_xlfn.XLOOKUP(I78,DR_Master!A:A,DR_Master!B:B),"Doctor ID not found")) -> Dr. Meena Pillai | L78: =IF(K78="","",IFERROR(_xlfn.XLOOKUP(K78,BED_Master!A:A,BED_Master!B:B),"Bed ID not found")) | M78: Acute Gastroenteritis | N78: A09 | O78: Discharged | P78: Online Booking | Q78: Ward Nurse
A79: =IF(B79="","","ADM-"&TEXT(ROW(A75),"00000")) -> ADM-00075 | B79: PT-00075 | C79: =IF(B79="","",IFERROR(_xlfn.XLOOKUP(B79,PT_Master!A:A,PT_Master!C:C),"Patient ID not found")) -> Mukesh Pal | D79: Emergency | E79: 27/12/2025 | F79: 29/12/2025 | G79: =IF(OR(E79="",F79=""),"",MAX(0,DATEDIF(E79,F79,"D"))) -> 2 | H79: General Medicine | I79: DR-003 | J79: =IF(I79="","",IFERROR(_xlfn.XLOOKUP(I79,DR_Master!A:A,DR_Master!B:B),"Doctor ID not found")) -> Dr. Sanjay Ghosh | L79: =IF(K79="","",IFERROR(_xlfn.XLOOKUP(K79,BED_Master!A:A,BED_Master!B:B),"Bed ID not found")) | M79: Osteoarthritis Knee | N79: M17.1 | O79: Discharged | P79: Another Hospital | Q79: Ward Nurse
A80: =IF(B80="","","ADM-"&TEXT(ROW(A76),"00000")) -> ADM-00076 | B80: PT-00076 | C80: =IF(B80="","",IFERROR(_xlfn.XLOOKUP(B80,PT_Master!A:A,PT_Master!C:C),"Patient ID not found")) -> Savita Nath | D80: OPD | E80: 14/04/2026 | F80: 14/04/2026 | G80: =IF(OR(E80="",F80=""),"",MAX(0,DATEDIF(E80,F80,"D"))) -> 0 | H80: Gynaecology | I80: DR-002 | J80: =IF(I80="","",IFERROR(_xlfn.XLOOKUP(I80,DR_Master!A:A,DR_Master!B:B),"Doctor ID not found")) -> Dr. Meena Pillai | L80: =IF(K80="","",IFERROR(_xlfn.XLOOKUP(K80,BED_Master!A:A,BED_Master!B:B),"Bed ID not found")) | M80: Lumbar Disc Herniation | N80: M51.1 | O80: Discharged | P80: Emergency | Q80: Ward Nurse
A81: =IF(B81="","","ADM-"&TEXT(ROW(A77),"00000")) -> ADM-00077 | B81: PT-00077 | C81: =IF(B81="","",IFERROR(_xlfn.XLOOKUP(B81,PT_Master!A:A,PT_Master!C:C),"Patient ID not found")) -> Aditya Saha | D81: Emergency | E81: 30/08/2025 | F81: 01/09/2025 | G81: =IF(OR(E81="",F81=""),"",MAX(0,DATEDIF(E81,F81,"D"))) -> 2 | H81: Paediatrics | I81: DR-004 | J81: =IF(I81="","",IFERROR(_xlfn.XLOOKUP(I81,DR_Master!A:A,DR_Master!B:B),"Doctor ID not found")) -> Dr. Ritika Sharma | L81: =IF(K81="","",IFERROR(_xlfn.XLOOKUP(K81,BED_Master!A:A,BED_Master!B:B),"Bed ID not found")) | M81: Asthma | N81: J45.9 | O81: Active | P81: Emergency | Q81: Ward Nurse
A82: =IF(B82="","","ADM-"&TEXT(ROW(A78),"00000")) -> ADM-00078 | B82: PT-00078 | C82: =IF(B82="","",IFERROR(_xlfn.XLOOKUP(B82,PT_Master!A:A,PT_Master!C:C),"Patient ID not found")) -> Rani Biswas | D82: OPD | E82: 11/07/2025 | F82: 11/07/2025 | G82: =IF(OR(E82="",F82=""),"",MAX(0,DATEDIF(E82,F82,"D"))) -> 0 | H82: Orthopaedics | I82: DR-010 | J82: =IF(I82="","",IFERROR(_xlfn.XLOOKUP(I82,DR_Master!A:A,DR_Master!B:B),"Doctor ID not found")) -> Dr. Subhash Patra | L82: =IF(K82="","",IFERROR(_xlfn.XLOOKUP(K82,BED_Master!A:A,BED_Master!B:B),"Bed ID not found")) | M82: Chronic Kidney Disease | N82: N18.9 | O82: Discharged | P82: Specialist Referral | Q82: Ward Nurse
A83: =IF(B83="","","ADM-"&TEXT(ROW(A79),"00000")) -> ADM-00079 | B83: PT-00079 | C83: =IF(B83="","",IFERROR(_xlfn.XLOOKUP(B83,PT_Master!A:A,PT_Master!C:C),"Patient ID not found")) -> Chirag Chakraborty | D83: OPD | E83: 29/08/2025 | F83: 29/08/2025 | G83: =IF(OR(E83="",F83=""),"",MAX(0,DATEDIF(E83,F83,"D"))) -> 0 | H83: Emergency | I83: DR-006 | J83: =IF(I83="","",IFERROR(_xlfn.XLOOKUP(I83,DR_Master!A:A,DR_Master!B:B),"Doctor ID not found")) -> Dr. Farhan Qureshi | L83: =IF(K83="","",IFERROR(_xlfn.XLOOKUP(K83,BED_Master!A:A,BED_Master!B:B),"Bed ID not found")) | M83: Ischaemic Stroke | N83: I63.9 | O83: Discharged | P83: Self | Q83: Ward Nurse
A84: =IF(B84="","","ADM-"&TEXT(ROW(A80),"00000")) -> ADM-00080 | B84: PT-00080 | C84: =IF(B84="","",IFERROR(_xlfn.XLOOKUP(B84,PT_Master!A:A,PT_Master!C:C),"Patient ID not found")) -> Manjula Mitra | D84: IPD | E84: 04/09/2025 | F84: 09/09/2025 | G84: =IF(OR(E84="",F84=""),"",MAX(0,DATEDIF(E84,F84,"D"))) -> 5 | H84: Paediatrics | I84: DR-004 | J84: =IF(I84="","",IFERROR(_xlfn.XLOOKUP(I84,DR_Master!A:A,DR_Master!B:B),"Doctor ID not found")) -> Dr. Ritika Sharma | K84: BED-003 | L84: =IF(K84="","",IFERROR(_xlfn.XLOOKUP(K84,BED_Master!A:A,BED_Master!B:B),"Bed ID not found")) -> General Ward | M84: Acute Myocardial Infarction | N84: I21.9 | O84: Discharged | P84: Another Hospital | Q84: Admin Manager
A85: =IF(B85="","","ADM-"&TEXT(ROW(A81),"00000")) -> ADM-00081 | B85: PT-00081 | C85: =IF(B85="","",IFERROR(_xlfn.XLOOKUP(B85,PT_Master!A:A,PT_Master!C:C),"Patient ID not found")) -> Yash Paul | D85: IPD | E85: 10/08/2025 | F85: 22/08/2025 | G85: =IF(OR(E85="",F85=""),"",MAX(0,DATEDIF(E85,F85,"D"))) -> 12 | H85: Paediatrics | I85: DR-004 | J85: =IF(I85="","",IFERROR(_xlfn.XLOOKUP(I85,DR_Master!A:A,DR_Master!B:B),"Doctor ID not found")) -> Dr. Ritika Sharma | K85: BED-002 | L85: =IF(K85="","",IFERROR(_xlfn.XLOOKUP(K85,BED_Master!A:A,BED_Master!B:B),"Bed ID not found")) -> General Ward | M85: Septicaemia | N85: A41.9 | O85: Discharged | P85: Corporate Tie-up | Q85: Ward Nurse
A86: =IF(B86="","","ADM-"&TEXT(ROW(A82),"00000")) -> ADM-00082 | B86: PT-00082 | C86: =IF(B86="","",IFERROR(_xlfn.XLOOKUP(B86,PT_Master!A:A,PT_Master!C:C),"Patient ID not found")) -> Hema Karmakar | D86: OPD | E86: 21/08/2025 | F86: 21/08/2025 | G86: =IF(OR(E86="",F86=""),"",MAX(0,DATEDIF(E86,F86,"D"))) -> 0 | H86: Cardiology | I86: DR-009 | J86: =IF(I86="","",IFERROR(_xlfn.XLOOKUP(I86,DR_Master!A:A,DR_Master!B:B),"Doctor ID not found")) -> Dr. Kamala Nair | L86: =IF(K86="","",IFERROR(_xlfn.XLOOKUP(K86,BED_Master!A:A,BED_Master!B:B),"Bed ID not found")) | M86: GERD | N86: K21.0 | O86: Discharged | P86: Online Booking | Q86: Ward Nurse
A87: =IF(B87="","","ADM-"&TEXT(ROW(A83),"00000")) -> ADM-00083 | B87: PT-00083 | C87: =IF(B87="","",IFERROR(_xlfn.XLOOKUP(B87,PT_Master!A:A,PT_Master!C:C),"Patient ID not found")) -> Kartik Mandal | D87: IPD | E87: 16/12/2025 | F87: 25/12/2025 | G87: =IF(OR(E87="",F87=""),"",MAX(0,DATEDIF(E87,F87,"D"))) -> 9 | H87: Emergency | I87: DR-006 | J87: =IF(I87="","",IFERROR(_xlfn.XLOOKUP(I87,DR_Master!A:A,DR_Master!B:B),"Doctor ID not found")) -> Dr. Farhan Qureshi | K87: BED-005 | L87: =IF(K87="","",IFERROR(_xlfn.XLOOKUP(K87,BED_Master!A:A,BED_Master!B:B),"Bed ID not found")) -> General Ward | M87: Type 2 Diabetes Mellitus | N87: E11.9 | O87: Discharged | P87: Specialist Referral | Q87: Billing Clerk
A88: =IF(B88="","","ADM-"&TEXT(ROW(A84),"00000")) -> ADM-00084 | B88: PT-00084 | C88: =IF(B88="","",IFERROR(_xlfn.XLOOKUP(B88,PT_Master!A:A,PT_Master!C:C),"Patient ID not found")) -> Gita Sarkar | D88: IPD | E88: 17/02/2026 | F88: 28/02/2026 | G88: =IF(OR(E88="",F88=""),"",MAX(0,DATEDIF(E88,F88,"D"))) -> 11 | H88: Cardiology | I88: DR-001 | J88: =IF(I88="","",IFERROR(_xlfn.XLOOKUP(I88,DR_Master!A:A,DR_Master!B:B),"Doctor ID not found")) -> Dr. Arjun Bose | K88: BED-020 | L88: =IF(K88="","",IFERROR(_xlfn.XLOOKUP(K88,BED_Master!A:A,BED_Master!B:B),"Bed ID not found")) -> Private | M88: Lumbar Disc Herniation | N88: M51.1 | O88: LAMA | P88: Emergency | Q88: Billing Clerk
A89: =IF(B89="","","ADM-"&TEXT(ROW(A85),"00000")) -> ADM-00085 | B89: PT-00085 | C89: =IF(B89="","",IFERROR(_xlfn.XLOOKUP(B89,PT_Master!A:A,PT_Master!C:C),"Patient ID not found")) -> Parth Patra | D89: OPD | E89: 05/05/2026 | F89: 05/05/2026 | G89: =IF(OR(E89="",F89=""),"",MAX(0,DATEDIF(E89,F89,"D"))) -> 0 | H89: General Medicine | I89: DR-003 | J89: =IF(I89="","",IFERROR(_xlfn.XLOOKUP(I89,DR_Master!A:A,DR_Master!B:B),"Doctor ID not found")) -> Dr. Sanjay Ghosh | L89: =IF(K89="","",IFERROR(_xlfn.XLOOKUP(K89,BED_Master!A:A,BED_Master!B:B),"Bed ID not found")) | M89: Shoulder Dislocation | N89: S43.0 | O89: Discharged | P89: Online Booking | Q89: Ward Nurse
A90: =IF(B90="","","ADM-"&TEXT(ROW(A86),"00000")) -> ADM-00086 | B90: PT-00086 | C90: =IF(B90="","",IFERROR(_xlfn.XLOOKUP(B90,PT_Master!A:A,PT_Master!C:C),"Patient ID not found")) -> Radha Haldar | D90: OPD | E90: 25/01/2026 | F90: 25/01/2026 | G90: =IF(OR(E90="",F90=""),"",MAX(0,DATEDIF(E90,F90,"D"))) -> 0 | H90: Cardiology | I90: DR-009 | J90: =IF(I90="","",IFERROR(_xlfn.XLOOKUP(I90,DR_Master!A:A,DR_Master!B:B),"Doctor ID not found")) -> Dr. Kamala Nair | L90: =IF(K90="","",IFERROR(_xlfn.XLOOKUP(K90,BED_Master!A:A,BED_Master!B:B),"Bed ID not found")) | M90: Community Acquired Pneumonia | N90: J18.9 | O90: Discharged | P90: GP Referral | Q90: Admin Manager
A91: =IF(B91="","","ADM-"&TEXT(ROW(A87),"00000")) -> ADM-00087 | B91: PT-00087 | C91: =IF(B91="","",IFERROR(_xlfn.XLOOKUP(B91,PT_Master!A:A,PT_Master!C:C),"Patient ID not found")) -> Mihir Majumdar | D91: OPD | E91: 16/10/2025 | F91: 16/10/2025 | G91: =IF(OR(E91="",F91=""),"",MAX(0,DATEDIF(E91,F91,"D"))) -> 0 | H91: Gynaecology | I91: DR-002 | J91: =IF(I91="","",IFERROR(_xlfn.XLOOKUP(I91,DR_Master!A:A,DR_Master!B:B),"Doctor ID not found")) -> Dr. Meena Pillai | L91: =IF(K91="","",IFERROR(_xlfn.XLOOKUP(K91,BED_Master!A:A,BED_Master!B:B),"Bed ID not found")) | M91: Iron Deficiency Anaemia | N91: D50.9 | O91: Discharged | P91: Emergency | Q91: Receptionist
A92: =IF(B92="","","ADM-"&TEXT(ROW(A88),"00000")) -> ADM-00088 | B92: PT-00088 | C92: =IF(B92="","",IFERROR(_xlfn.XLOOKUP(B92,PT_Master!A:A,PT_Master!C:C),"Patient ID not found")) -> Sarla Bhattacharya | D92: OPD | E92: 08/11/2025 | F92: 08/11/2025 | G92: =IF(OR(E92="",F92=""),"",MAX(0,DATEDIF(E92,F92,"D"))) -> 0 | H92: Cardiology | I92: DR-001 | J92: =IF(I92="","",IFERROR(_xlfn.XLOOKUP(I92,DR_Master!A:A,DR_Master!B:B),"Doctor ID not found")) -> Dr. Arjun Bose | L92: =IF(K92="","",IFERROR(_xlfn.XLOOKUP(K92,BED_Master!A:A,BED_Master!B:B),"Bed ID not found")) | M92: COPD Exacerbation | N92: J44.1 | O92: Discharged | P92: Corporate Tie-up | Q92: Receptionist
A93: =IF(B93="","","ADM-"&TEXT(ROW(A89),"00000")) -> ADM-00089 | B93: PT-00089 | C93: =IF(B93="","",IFERROR(_xlfn.XLOOKUP(B93,PT_Master!A:A,PT_Master!C:C),"Patient ID not found")) -> Devang Chowdhury | D93: OPD | E93: 11/01/2026 | F93: 11/01/2026 | G93: =IF(OR(E93="",F93=""),"",MAX(0,DATEDIF(E93,F93,"D"))) -> 0 | H93: Gynaecology | I93: DR-002 | J93: =IF(I93="","",IFERROR(_xlfn.XLOOKUP(I93,DR_Master!A:A,DR_Master!B:B),"Doctor ID not found")) -> Dr. Meena Pillai | L93: =IF(K93="","",IFERROR(_xlfn.XLOOKUP(K93,BED_Master!A:A,BED_Master!B:B),"Bed ID not found")) | M93: Neonatal Jaundice | N93: P59.9 | O93: Discharged | P93: Self | Q93: Admin Manager
A94: =IF(B94="","","ADM-"&TEXT(ROW(A90),"00000")) -> ADM-00090 | B94: PT-00090 | C94: =IF(B94="","",IFERROR(_xlfn.XLOOKUP(B94,PT_Master!A:A,PT_Master!C:C),"Patient ID not found")) -> Pushpa Lahiri | D94: OPD | E94: 05/08/2025 | F94: 05/08/2025 | G94: =IF(OR(E94="",F94=""),"",MAX(0,DATEDIF(E94,F94,"D"))) -> 0 | H94: Orthopaedics | I94: DR-010 | J94: =IF(I94="","",IFERROR(_xlfn.XLOOKUP(I94,DR_Master!A:A,DR_Master!B:B),"Doctor ID not found")) -> Dr. Subhash Patra | L94: =IF(K94="","",IFERROR(_xlfn.XLOOKUP(K94,BED_Master!A:A,BED_Master!B:B),"Bed ID not found")) | M94: Asthma | N94: J45.9 | O94: Discharged | P94: Another Hospital | Q94: Billing Clerk
A95: =IF(B95="","","ADM-"&TEXT(ROW(A91),"00000")) -> ADM-00091 | B95: PT-00091 | C95: =IF(B95="","",IFERROR(_xlfn.XLOOKUP(B95,PT_Master!A:A,PT_Master!C:C),"Patient ID not found")) -> Tejas Ganguly | D95: Emergency | E95: 28/03/2026 | F95: 29/03/2026 | G95: =IF(OR(E95="",F95=""),"",MAX(0,DATEDIF(E95,F95,"D"))) -> 1 | H95: Gynaecology | I95: DR-002 | J95: =IF(I95="","",IFERROR(_xlfn.XLOOKUP(I95,DR_Master!A:A,DR_Master!B:B),"Doctor ID not found")) -> Dr. Meena Pillai | L95: =IF(K95="","",IFERROR(_xlfn.XLOOKUP(K95,BED_Master!A:A,BED_Master!B:B),"Bed ID not found")) | M95: Hypothyroidism | N95: E03.9 | O95: Discharged | P95: Corporate Tie-up | Q95: Billing Clerk
A96: =IF(B96="","","ADM-"&TEXT(ROW(A92),"00000")) -> ADM-00092 | B96: PT-00092 | C96: =IF(B96="","",IFERROR(_xlfn.XLOOKUP(B96,PT_Master!A:A,PT_Master!C:C),"Patient ID not found")) -> Sharda Dutta | D96: OPD | E96: 11/10/2025 | F96: 11/10/2025 | G96: =IF(OR(E96="",F96=""),"",MAX(0,DATEDIF(E96,F96,"D"))) -> 0 | H96: Cardiology | I96: DR-009 | J96: =IF(I96="","",IFERROR(_xlfn.XLOOKUP(I96,DR_Master!A:A,DR_Master!B:B),"Doctor ID not found")) -> Dr. Kamala Nair | L96: =IF(K96="","",IFERROR(_xlfn.XLOOKUP(K96,BED_Master!A:A,BED_Master!B:B),"Bed ID not found")) | M96: Cellulitis | N96: L03.9 | O96: Discharged | P96: Another Hospital | Q96: Ward Nurse
A97: =IF(B97="","","ADM-"&TEXT(ROW(A93),"00000")) -> ADM-00093 | B97: PT-00093 | C97: =IF(B97="","",IFERROR(_xlfn.XLOOKUP(B97,PT_Master!A:A,PT_Master!C:C),"Patient ID not found")) -> Jay Sanyal | D97: Emergency | E97: 02/11/2025 | F97: 04/11/2025 | G97: =IF(OR(E97="",F97=""),"",MAX(0,DATEDIF(E97,F97,"D"))) -> 2 | H97: General Medicine | I97: DR-008 | J97: =IF(I97="","",IFERROR(_xlfn.XLOOKUP(I97,DR_Master!A:A,DR_Master!B:B),"Doctor ID not found")) -> Dr. Prabal Roy | L97: =IF(K97="","",IFERROR(_xlfn.XLOOKUP(K97,BED_Master!A:A,BED_Master!B:B),"Bed ID not found")) | M97: Coronary Artery Disease | N97: I25.1 | O97: LAMA | P97: Online Booking | Q97: Receptionist
A98: =IF(B98="","","ADM-"&TEXT(ROW(A94),"00000")) -> ADM-00094 | B98: PT-00094 | C98: =IF(B98="","",IFERROR(_xlfn.XLOOKUP(B98,PT_Master!A:A,PT_Master!C:C),"Patient ID not found")) -> Meera Bhatt | D98: OPD | E98: 16/09/2025 | F98: 16/09/2025 | G98: =IF(OR(E98="",F98=""),"",MAX(0,DATEDIF(E98,F98,"D"))) -> 0 | H98: Orthopaedics | I98: DR-010 | J98: =IF(I98="","",IFERROR(_xlfn.XLOOKUP(I98,DR_Master!A:A,DR_Master!B:B),"Doctor ID not found")) -> Dr. Subhash Patra | L98: =IF(K98="","",IFERROR(_xlfn.XLOOKUP(K98,BED_Master!A:A,BED_Master!B:B),"Bed ID not found")) | M98: Fracture Femur | N98: S72.0 | O98: Discharged | P98: GP Referral | Q98: Admin Manager
A99: =IF(B99="","","ADM-"&TEXT(ROW(A95),"00000")) -> ADM-00095 | B99: PT-00095 | C99: =IF(B99="","",IFERROR(_xlfn.XLOOKUP(B99,PT_Master!A:A,PT_Master!C:C),"Patient ID not found")) -> Bhavesh Joshi | D99: IPD | E99: 30/12/2025 | F99: 11/01/2026 | G99: =IF(OR(E99="",F99=""),"",MAX(0,DATEDIF(E99,F99,"D"))) -> 12 | H99: Diagnostics | I99: DR-007 | J99: =IF(I99="","",IFERROR(_xlfn.XLOOKUP(I99,DR_Master!A:A,DR_Master!B:B),"Doctor ID not found")) -> Dr. Lipika Sen | K99: BED-021 | L99: =IF(K99="","",IFERROR(_xlfn.XLOOKUP(K99,BED_Master!A:A,BED_Master!B:B),"Bed ID not found")) -> Private | M99: Acute Gastroenteritis | N99: A09 | O99: Discharged | P99: Emergency | Q99: Billing Clerk
A100: =IF(B100="","","ADM-"&TEXT(ROW(A96),"00000")) -> ADM-00096 | B100: PT-00096 | C100: =IF(B100="","",IFERROR(_xlfn.XLOOKUP(B100,PT_Master!A:A,PT_Master!C:C),"Patient ID not found")) -> Indira Patel | D100: OPD | E100: 14/09/2025 | F100: 14/09/2025 | G100: =IF(OR(E100="",F100=""),"",MAX(0,DATEDIF(E100,F100,"D"))) -> 0 | H100: Orthopaedics | I100: DR-010 | J100: =IF(I100="","",IFERROR(_xlfn.XLOOKUP(I100,DR_Master!A:A,DR_Master!B:B),"Doctor ID not found")) -> Dr. Subhash Patra | L100: =IF(K100="","",IFERROR(_xlfn.XLOOKUP(K100,BED_Master!A:A,BED_Master!B:B),"Bed ID not found")) | M100: Acute Appendicitis | N100: K37 | O100: Discharged | P100: Online Booking | Q100: Admin Manager
A101: =IF(B101="","","ADM-"&TEXT(ROW(A97),"00000")) -> ADM-00097 | B101: PT-00097 | C101: =IF(B101="","",IFERROR(_xlfn.XLOOKUP(B101,PT_Master!A:A,PT_Master!C:C),"Patient ID not found")) -> Sagar Shah | D101: Emergency | E101: 19/04/2026 | F101: 21/04/2026 | G101: =IF(OR(E101="",F101=""),"",MAX(0,DATEDIF(E101,F101,"D"))) -> 2 | H101: Diagnostics | I101: DR-007 | J101: =IF(I101="","",IFERROR(_xlfn.XLOOKUP(I101,DR_Master!A:A,DR_Master!B:B),"Doctor ID not found")) -> Dr. Lipika Sen | L101: =IF(K101="","",IFERROR(_xlfn.XLOOKUP(K101,BED_Master!A:A,BED_Master!B:B),"Bed ID not found")) | M101: Neonatal Jaundice | N101: P59.9 | O101: Active | P101: Specialist Referral | Q101: Receptionist
A102: =IF(B102="","","ADM-"&TEXT(ROW(A98),"00000")) -> ADM-00098 | B102: PT-00098 | C102: =IF(B102="","",IFERROR(_xlfn.XLOOKUP(B102,PT_Master!A:A,PT_Master!C:C),"Patient ID not found")) -> Leela Desai | D102: OPD | E102: 07/09/2025 | F102: 07/09/2025 | G102: =IF(OR(E102="",F102=""),"",MAX(0,DATEDIF(E102,F102,"D"))) -> 0 | H102: General Medicine | I102: DR-008 | J102: =IF(I102="","",IFERROR(_xlfn.XLOOKUP(I102,DR_Master!A:A,DR_Master!B:B),"Doctor ID not found")) -> Dr. Prabal Roy | L102: =IF(K102="","",IFERROR(_xlfn.XLOOKUP(K102,BED_Master!A:A,BED_Master!B:B),"Bed ID not found")) | M102: Osteoarthritis Knee | N102: M17.1 | O102: Discharged | P102: Specialist Referral | Q102: Admin Manager
...

Sheet SVC_Log
A2: CityMed Multi-Specialty Hospital — Services Consumed Log
A4: SvcLog_ID | B4: Admission_ID | C4: Patient_ID | D4: Patient_Name | E4: Service_Date | F4: Service_Code | G4: Service_Name | H4: Category | I4: Orderd_by | J4: Quantity | K4: Unit_Rate (₹) | L4: Line_Total (₹) | M4: GST_% | N4: GST_Amount (₹) | O4: Gross_Total (₹) | P4: Notes
A5: =IF(B5="","","SL-"&TEXT(ROW(A1),"00000")) -> SL-00001 | B5: ADM-00001 | C5: =IF(B5="","",IFERROR(_xlfn.XLOOKUP(B5,PT_Master!#REF!,PT_Master!B:B),"")) | D5: =IF(C5="","",IFERROR(_xlfn.XLOOKUP(C5,PT_Master!A:A,PT_Master!C:C),"")) | E5: 02/03/2026 | F5: SVC-0001 | G5: =IF(F5="","",IFERROR(_xlfn.XLOOKUP(F5,SVC_RateCard!A:A,SVC_RateCard!B:B),"Service Code not found")) -> General Consultation | H5: =IF(F5="","",IFERROR(_xlfn.XLOOKUP(F5,SVC_RateCard!A:A,SVC_RateCard!C:C),"")) -> Consultation | I5: Dr. Prabal Roy | J5: 1 | K5: =IF(F5="","",IFERROR(_xlfn.XLOOKUP(F5,SVC_RateCard!A:A,SVC_RateCard!I:I),0)) -> 500 | L5: =IF(OR(J5="",K5=""),"",J5*K5) -> 500 | M5: =IF(F5="","",IFERROR(_xlfn.XLOOKUP(F5,SVC_RateCard!A:A,SVC_RateCard!G:G),0)) -> 0 | N5: =IF(L5="","",IFERROR(L5*M5/100,0)) -> 0 | O5: =IF(L5="","",L5) -> 500
A6: =IF(B6="","","SL-"&TEXT(ROW(A2),"00000")) -> SL-00002 | B6: ADM-00001 | C6: =IF(B6="","",IFERROR(_xlfn.XLOOKUP(B6,PT_Master!#REF!,PT_Master!B:B),"")) | D6: =IF(C6="","",IFERROR(_xlfn.XLOOKUP(C6,PT_Master!A:A,PT_Master!C:C),"")) | E6: 02/03/2026 | F6: SVC-0017 | G6: =IF(F6="","",IFERROR(_xlfn.XLOOKUP(F6,SVC_RateCard!A:A,SVC_RateCard!B:B),"Service Code not found")) -> Malaria Antigen Test | H6: =IF(F6="","",IFERROR(_xlfn.XLOOKUP(F6,SVC_RateCard!A:A,SVC_RateCard!C:C),"")) -> Laboratory | I6: Dr. Prabal Roy | J6: 1 | K6: =IF(F6="","",IFERROR(_xlfn.XLOOKUP(F6,SVC_RateCard!A:A,SVC_RateCard!I:I),0)) -> 420 | L6: =IF(OR(J6="",K6=""),"",J6*K6) -> 420 | M6: =IF(F6="","",IFERROR(_xlfn.XLOOKUP(F6,SVC_RateCard!A:A,SVC_RateCard!G:G),0)) -> 5 | N6: =IF(L6="","",IFERROR(L6*M6/100,0)) -> 21 | O6: =IF(L6="","",L6) -> 420
A7: =IF(B7="","","SL-"&TEXT(ROW(A3),"00000")) -> SL-00003 | B7: ADM-00001 | C7: =IF(B7="","",IFERROR(_xlfn.XLOOKUP(B7,PT_Master!#REF!,PT_Master!B:B),"")) | D7: =IF(C7="","",IFERROR(_xlfn.XLOOKUP(C7,PT_Master!A:A,PT_Master!C:C),"")) | E7: 02/03/2026 | F7: SVC-0030 | G7: =IF(F7="","",IFERROR(_xlfn.XLOOKUP(F7,SVC_RateCard!A:A,SVC_RateCard!B:B),"Service Code not found")) -> Ultrasound Obstetric | H7: =IF(F7="","",IFERROR(_xlfn.XLOOKUP(F7,SVC_RateCard!A:A,SVC_RateCard!C:C),"")) -> Radiology | I7: Dr. Prabal Roy | J7: 1 | K7: =IF(F7="","",IFERROR(_xlfn.XLOOKUP(F7,SVC_RateCard!A:A,SVC_RateCard!I:I),0)) -> 1568 | L7: =IF(OR(J7="",K7=""),"",J7*K7) -> 1568 | M7: =IF(F7="","",IFERROR(_xlfn.XLOOKUP(F7,SVC_RateCard!A:A,SVC_RateCard!G:G),0)) -> 12 | N7: =IF(L7="","",IFERROR(L7*M7/100,0)) -> 188.16 | O7: =IF(L7="","",L7) -> 1568
A8: =IF(B8="","","SL-"&TEXT(ROW(A4),"00000")) -> SL-00004 | B8: ADM-00002 | C8: =IF(B8="","",IFERROR(_xlfn.XLOOKUP(B8,PT_Master!#REF!,PT_Master!B:B),"")) | D8: =IF(C8="","",IFERROR(_xlfn.XLOOKUP(C8,PT_Master!A:A,PT_Master!C:C),"")) | E8: 19/08/2025 | F8: SVC-0004 | G8: =IF(F8="","",IFERROR(_xlfn.XLOOKUP(F8,SVC_RateCard!A:A,SVC_RateCard!B:B),"Service Code not found")) -> Orthopaedics Consultation | H8: =IF(F8="","",IFERROR(_xlfn.XLOOKUP(F8,SVC_RateCard!A:A,SVC_RateCard!C:C),"")) -> Consultation | I8: Dr. Tanmoy Das | J8: 1 | K8: =IF(F8="","",IFERROR(_xlfn.XLOOKUP(F8,SVC_RateCard!A:A,SVC_RateCard!I:I),0)) -> 650 | L8: =IF(OR(J8="",K8=""),"",J8*K8) -> 650 | M8: =IF(F8="","",IFERROR(_xlfn.XLOOKUP(F8,SVC_RateCard!A:A,SVC_RateCard!G:G),0)) -> 0 | N8: =IF(L8="","",IFERROR(L8*M8/100,0)) -> 0 | O8: =IF(L8="","",L8) -> 650
A9: =IF(B9="","","SL-"&TEXT(ROW(A5),"00000")) -> SL-00005 | B9: ADM-00002 | C9: =IF(B9="","",IFERROR(_xlfn.XLOOKUP(B9,PT_Master!#REF!,PT_Master!B:B),"")) | D9: =IF(C9="","",IFERROR(_xlfn.XLOOKUP(C9,PT_Master!A:A,PT_Master!C:C),"")) | E9: 19/08/2025 | F9: SVC-0050 | G9: =IF(F9="","",IFERROR(_xlfn.XLOOKUP(F9,SVC_RateCard!A:A,SVC_RateCard!B:B),"Service Code not found")) -> Endoscopy (Upper GI) | H9: =IF(F9="","",IFERROR(_xlfn.XLOOKUP(F9,SVC_RateCard!A:A,SVC_RateCard!C:C),"")) -> Procedure | I9: Dr. Tanmoy Das | J9: 1 | K9: =IF(F9="","",IFERROR(_xlfn.XLOOKUP(F9,SVC_RateCard!A:A,SVC_RateCard!I:I),0)) -> 3675 | L9: =IF(OR(J9="",K9=""),"",J9*K9) -> 3675 | M9: =IF(F9="","",IFERROR(_xlfn.XLOOKUP(F9,SVC_RateCard!A:A,SVC_RateCard!G:G),0)) -> 5 | N9: =IF(L9="","",IFERROR(L9*M9/100,0)) -> 183.75 | O9: =IF(L9="","",L9) -> 3675
A10: =IF(B10="","","SL-"&TEXT(ROW(A6),"00000")) -> SL-00006 | B10: ADM-00002 | C10: =IF(B10="","",IFERROR(_xlfn.XLOOKUP(B10,PT_Master!#REF!,PT_Master!B:B),"")) | D10: =IF(C10="","",IFERROR(_xlfn.XLOOKUP(C10,PT_Master!A:A,PT_Master!C:C),"")) | E10: 19/08/2025 | F10: SVC-0010 | G10: =IF(F10="","",IFERROR(_xlfn.XLOOKUP(F10,SVC_RateCard!A:A,SVC_RateCard!B:B),"Service Code not found")) -> Lipid Profile | H10: =IF(F10="","",IFERROR(_xlfn.XLOOKUP(F10,SVC_RateCard!A:A,SVC_RateCard!C:C),"")) -> Laboratory | I10: Dr. Tanmoy Das | J10: 1 | K10: =IF(F10="","",IFERROR(_xlfn.XLOOKUP(F10,SVC_RateCard!A:A,SVC_RateCard!I:I),0)) -> 472.5 | L10: =IF(OR(J10="",K10=""),"",J10*K10) -> 472.5 | M10: =IF(F10="","",IFERROR(_xlfn.XLOOKUP(F10,SVC_RateCard!A:A,SVC_RateCard!G:G),0)) -> 5 | N10: =IF(L10="","",IFERROR(L10*M10/100,0)) -> 23.625 | O10: =IF(L10="","",L10) -> 472.5
A11: =IF(B11="","","SL-"&TEXT(ROW(A7),"00000")) -> SL-00007 | B11: ADM-00002 | C11: =IF(B11="","",IFERROR(_xlfn.XLOOKUP(B11,PT_Master!#REF!,PT_Master!B:B),"")) | D11: =IF(C11="","",IFERROR(_xlfn.XLOOKUP(C11,PT_Master!A:A,PT_Master!C:C),"")) | E11: 19/08/2025 | F11: SVC-0044 | G11: =IF(F11="","",IFERROR(_xlfn.XLOOKUP(F11,SVC_RateCard!A:A,SVC_RateCard!B:B),"Service Code not found")) -> IV Cannula Insertion | H11: =IF(F11="","",IFERROR(_xlfn.XLOOKUP(F11,SVC_RateCard!A:A,SVC_RateCard!C:C),"")) -> Procedure | I11: Dr. Tanmoy Das | J11: 1 | K11: =IF(F11="","",IFERROR(_xlfn.XLOOKUP(F11,SVC_RateCard!A:A,SVC_RateCard!I:I),0)) -> 210 | L11: =IF(OR(J11="",K11=""),"",J11*K11) -> 210 | M11: =IF(F11="","",IFERROR(_xlfn.XLOOKUP(F11,SVC_RateCard!A:A,SVC_RateCard!G:G),0)) -> 5 | N11: =IF(L11="","",IFERROR(L11*M11/100,0)) -> 10.5 | O11: =IF(L11="","",L11) -> 210
A12: =IF(B12="","","SL-"&TEXT(ROW(A8),"00000")) -> SL-00008 | B12: ADM-00003 | C12: =IF(B12="","",IFERROR(_xlfn.XLOOKUP(B12,PT_Master!#REF!,PT_Master!B:B),"")) | D12: =IF(C12="","",IFERROR(_xlfn.XLOOKUP(C12,PT_Master!A:A,PT_Master!C:C),"")) | E12: 11/03/2026 | F12: SVC-0001 | G12: =IF(F12="","",IFERROR(_xlfn.XLOOKUP(F12,SVC_RateCard!A:A,SVC_RateCard!B:B),"Service Code not found")) -> General Consultation | H12: =IF(F12="","",IFERROR(_xlfn.XLOOKUP(F12,SVC_RateCard!A:A,SVC_RateCard!C:C),"")) -> Consultation | I12: Dr. Sanjay Ghosh | J12: 1 | K12: =IF(F12="","",IFERROR(_xlfn.XLOOKUP(F12,SVC_RateCard!A:A,SVC_RateCard!I:I),0)) -> 500 | L12: =IF(OR(J12="",K12=""),"",J12*K12) -> 500 | M12: =IF(F12="","",IFERROR(_xlfn.XLOOKUP(F12,SVC_RateCard!A:A,SVC_RateCard!G:G),0)) -> 0 | N12: =IF(L12="","",IFERROR(L12*M12/100,0)) -> 0 | O12: =IF(L12="","",L12) -> 500
A13: =IF(B13="","","SL-"&TEXT(ROW(A9),"00000")) -> SL-00009 | B13: ADM-00003 | C13: =IF(B13="","",IFERROR(_xlfn.XLOOKUP(B13,PT_Master!#REF!,PT_Master!B:B),"")) | D13: =IF(C13="","",IFERROR(_xlfn.XLOOKUP(C13,PT_Master!A:A,PT_Master!C:C),"")) | E13: 11/03/2026 | F13: SVC-0031 | G13: =IF(F13="","",IFERROR(_xlfn.XLOOKUP(F13,SVC_RateCard!A:A,SVC_RateCard!B:B),"Service Code not found")) -> General Ward - Daily | H13: =IF(F13="","",IFERROR(_xlfn.XLOOKUP(F13,SVC_RateCard!A:A,SVC_RateCard!C:C),"")) -> Room Charge | I13: Dr. Sanjay Ghosh | J13: 1 | K13: =IF(F13="","",IFERROR(_xlfn.XLOOKUP(F13,SVC_RateCard!A:A,SVC_RateCard!I:I),0)) -> 800 | L13: =IF(OR(J13="",K13=""),"",J13*K13) -> 800 | M13: =IF(F13="","",IFERROR(_xlfn.XLOOKUP(F13,SVC_RateCard!A:A,SVC_RateCard!G:G),0)) -> 0 | N13: =IF(L13="","",IFERROR(L13*M13/100,0)) -> 0 | O13: =IF(L13="","",L13) -> 800
A14: =IF(B14="","","SL-"&TEXT(ROW(A10),"00000")) -> SL-00010 | B14: ADM-00003 | C14: =IF(B14="","",IFERROR(_xlfn.XLOOKUP(B14,PT_Master!#REF!,PT_Master!B:B),"")) | D14: =IF(C14="","",IFERROR(_xlfn.XLOOKUP(C14,PT_Master!A:A,PT_Master!C:C),"")) | E14: 11/03/2026 | F14: SVC-0045 | G14: =IF(F14="","",IFERROR(_xlfn.XLOOKUP(F14,SVC_RateCard!A:A,SVC_RateCard!B:B),"Service Code not found")) -> Nebulisation | H14: =IF(F14="","",IFERROR(_xlfn.XLOOKUP(F14,SVC_RateCard!A:A,SVC_RateCard!C:C),"")) -> Procedure | I14: Dr. Sanjay Ghosh | J14: 1 | K14: =IF(F14="","",IFERROR(_xlfn.XLOOKUP(F14,SVC_RateCard!A:A,SVC_RateCard!I:I),0)) -> 157.5 | L14: =IF(OR(J14="",K14=""),"",J14*K14) -> 157.5 | M14: =IF(F14="","",IFERROR(_xlfn.XLOOKUP(F14,SVC_RateCard!A:A,SVC_RateCard!G:G),0)) -> 5 | N14: =IF(L14="","",IFERROR(L14*M14/100,0)) -> 7.875 | O14: =IF(L14="","",L14) -> 157.5
A15: =IF(B15="","","SL-"&TEXT(ROW(A11),"00000")) -> SL-00011 | B15: ADM-00004 | C15: =IF(B15="","",IFERROR(_xlfn.XLOOKUP(B15,PT_Master!#REF!,PT_Master!B:B),"")) | D15: =IF(C15="","",IFERROR(_xlfn.XLOOKUP(C15,PT_Master!A:A,PT_Master!C:C),"")) | E15: 27/03/2026 | F15: SVC-0004 | G15: =IF(F15="","",IFERROR(_xlfn.XLOOKUP(F15,SVC_RateCard!A:A,SVC_RateCard!B:B),"Service Code not found")) -> Orthopaedics Consultation | H15: =IF(F15="","",IFERROR(_xlfn.XLOOKUP(F15,SVC_RateCard!A:A,SVC_RateCard!C:C),"")) -> Consultation | I15: Dr. Subhash Patra | J15: 1 | K15: =IF(F15="","",IFERROR(_xlfn.XLOOKUP(F15,SVC_RateCard!A:A,SVC_RateCard!I:I),0)) -> 650 | L15: =IF(OR(J15="",K15=""),"",J15*K15) -> 650 | M15: =IF(F15="","",IFERROR(_xlfn.XLOOKUP(F15,SVC_RateCard!A:A,SVC_RateCard!G:G),0)) -> 0 | N15: =IF(L15="","",IFERROR(L15*M15/100,0)) -> 0 | O15: =IF(L15="","",L15) -> 650
A16: =IF(B16="","","SL-"&TEXT(ROW(A12),"00000")) -> SL-00012 | B16: ADM-00004 | C16: =IF(B16="","",IFERROR(_xlfn.XLOOKUP(B16,PT_Master!#REF!,PT_Master!B:B),"")) | D16: =IF(C16="","",IFERROR(_xlfn.XLOOKUP(C16,PT_Master!A:A,PT_Master!C:C),"")) | E16: 27/03/2026 | F16: SVC-0028 | G16: =IF(F16="","",IFERROR(_xlfn.XLOOKUP(F16,SVC_RateCard!A:A,SVC_RateCard!B:B),"Service Code not found")) -> CT Scan Brain | H16: =IF(F16="","",IFERROR(_xlfn.XLOOKUP(F16,SVC_RateCard!A:A,SVC_RateCard!C:C),"")) -> Radiology | I16: Dr. Subhash Patra | J16: 1 | K16: =IF(F16="","",IFERROR(_xlfn.XLOOKUP(F16,SVC_RateCard!A:A,SVC_RateCard!I:I),0)) -> 5040 | L16: =IF(OR(J16="",K16=""),"",J16*K16) -> 5040 | M16: =IF(F16="","",IFERROR(_xlfn.XLOOKUP(F16,SVC_RateCard!A:A,SVC_RateCard!G:G),0)) -> 12 | N16: =IF(L16="","",IFERROR(L16*M16/100,0)) -> 604.8 | O16: =IF(L16="","",L16) -> 5040
... A926: =IF(B926="","","SL-"&TEXT(ROW(A922),"00000")) -> SL-00922 | B926: ADM-00150 | C926: =IF(B926="","",IFERROR(_xlfn.XLOOKUP(B926,PT_Master!#REF!,PT_Master!B:B),"")) | D926: =IF(C926="","",IFERROR(_xlfn.XLOOKUP(C926,PT_Master!A:A,PT_Master!C:C),"")) | E926: 25/09/2025 | F926: SVC-0013 | G926: =IF(F926="","",IFERROR(_xlfn.XLOOKUP(F926,SVC_RateCard!A:A,SVC_RateCard!B:B),"Service Code not found")) -> Urine Routine | H926: =IF(F926="","",IFERROR(_xlfn.XLOOKUP(F926,SVC_RateCard!A:A,SVC_RateCard!C:C),"")) -> Laboratory | I926: Dr. Prabal Roy | J926: 1 | K926: =IF(F926="","",IFERROR(_xlfn.XLOOKUP(F926,SVC_RateCard!A:A,SVC_RateCard!I:I),0)) -> 157.5 | L926: =IF(OR(J926="",K926=""),"",J926*K926) -> 157.5 | M926: =IF(F926="","",IFERROR(_xlfn.XLOOKUP(F926,SVC_RateCard!A:A,SVC_RateCard!G:G),0)) -> 5 | N926: =IF(L926="","",IFERROR(L926*M926/100,0)) -> 7.875 | O926: =IF(L926="","",L926) -> 157.5
A927: =IF(B927="","","SL-"&TEXT(ROW(A923),"00000")) | C927: =IF(B927="","",IFERROR(_xlfn.XLOOKUP(B927,PT_Master!#REF!,PT_Master!B:B),"")) | D927: =IF(C927="","",IFERROR(_xlfn.XLOOKUP(C927,PT_Master!A:A,PT_Master!C:C),"")) | G927: =IF(F927="","",IFERROR(_xlfn.XLOOKUP(F927,SVC_RateCard!A:A,SVC_RateCard!B:B),"Service Code not found")) | H927: =IF(F927="","",IFERROR(_xlfn.XLOOKUP(F927,SVC_RateCard!A:A,SVC_RateCard!C:C),"")) | K927: =IF(F927="","",IFERROR(_xlfn.XLOOKUP(F927,SVC_RateCard!A:A,SVC_RateCard!I:I),0)) | L927: =IF(OR(J927="",K927=""),"",J927*K927) | M927: =IF(F927="","",IFERROR(_xlfn.XLOOKUP(F927,SVC_RateCard!A:A,SVC_RateCard!G:G),0)) | N927: =IF(L927="","",IFERROR(L927*M927/100,0)) | O927: =IF(L927="","",L927)
A928: =IF(B928="","","SL-"&TEXT(ROW(A924),"00000")) | C928: =IF(B928="","",IFERROR(_xlfn.XLOOKUP(B928,PT_Master!#REF!,PT_Master!B:B),"")) | D928: =IF(C928="","",IFERROR(_xlfn.XLOOKUP(C928,PT_Master!A:A,PT_Master!C:C),"")) | G928: =IF(F928="","",IFERROR(_xlfn.XLOOKUP(F928,SVC_RateCard!A:A,SVC_RateCard!B:B),"Service Code not found")) | H928: =IF(F928="","",IFERROR(_xlfn.XLOOKUP(F928,SVC_RateCard!A:A,SVC_RateCard!C:C),"")) | K928: =IF(F928="","",IFERROR(_xlfn.XLOOKUP(F928,SVC_RateCard!A:A,SVC_RateCard!I:I),0)) | L928: =IF(OR(J928="",K928=""),"",J928*K928) | M928: =IF(F928="","",IFERROR(_xlfn.XLOOKUP(F928,SVC_RateCard!A:A,SVC_RateCard!G:G),0)) | N928: =IF(L928="","",IFERROR(L928*M928/100,0)) | O928: =IF(L928="","",L928)
A929: =IF(B929="","","SL-"&TEXT(ROW(A925),"00000")) | C929: =IF(B929="","",IFERROR(_xlfn.XLOOKUP(B929,PT_Master!#REF!,PT_Master!B:B),"")) | D929: =IF(C929="","",IFERROR(_xlfn.XLOOKUP(C929,PT_Master!A:A,PT_Master!C:C),"")) | G929: =IF(F929="","",IFERROR(_xlfn.XLOOKUP(F929,SVC_RateCard!A:A,SVC_RateCard!B:B),"Service Code not found")) | H929: =IF(F929="","",IFERROR(_xlfn.XLOOKUP(F929,SVC_RateCard!A:A,SVC_RateCard!C:C),"")) | K929: =IF(F929="","",IFERROR(_xlfn.XLOOKUP(F929,SVC_RateCard!A:A,SVC_RateCard!I:I),0)) | L929: =IF(OR(J929="",K929=""),"",J929*K929) | M929: =IF(F929="","",IFERROR(_xlfn.XLOOKUP(F929,SVC_RateCard!A:A,SVC_RateCard!G:G),0)) | N929: =IF(L929="","",IFERROR(L929*M929/100,0)) | O929: =IF(L929="","",L929)
A930: =IF(B930="","","SL-"&TEXT(ROW(A926),"00000")) | C930: =IF(B930="","",IFERROR(_xlfn.XLOOKUP(B930,PT_Master!#REF!,PT_Master!B:B),"")) | D930: =IF(C930="","",IFERROR(_xlfn.XLOOKUP(C930,PT_Master!A:A,PT_Master!C:C),"")) | G930: =IF(F930="","",IFERROR(_xlfn.XLOOKUP(F930,SVC_RateCard!A:A,SVC_RateCard!B:B),"Service Code not found")) | H930: =IF(F930="","",IFERROR(_xlfn.XLOOKUP(F930,SVC_RateCard!A:A,SVC_RateCard!C:C),"")) | K930: =IF(F930="","",IFERROR(_xlfn.XLOOKUP(F930,SVC_RateCard!A:A,SVC_RateCard!I:I),0)) | L930: =IF(OR(J930="",K930=""),"",J930*K930) | M930: =IF(F930="","",IFERROR(_xlfn.XLOOKUP(F930,SVC_RateCard!A:A,SVC_RateCard!G:G),0)) | N930: =IF(L930="","",IFERROR(L930*M930/100,0)) | O930: =IF(L930="","",L930)
A931: =IF(B931="","","SL-"&TEXT(ROW(A927),"00000")) | C931: =IF(B931="","",IFERROR(_xlfn.XLOOKUP(B931,PT_Master!#REF!,PT_Master!B:B),"")) | D931: =IF(C931="","",IFERROR(_xlfn.XLOOKUP(C931,PT_Master!A:A,PT_Master!C:C),"")) | G931: =IF(F931="","",IFERROR(_xlfn.XLOOKUP(F931,SVC_RateCard!A:A,SVC_RateCard!B:B),"Service Code not found")) | H931: =IF(F931="","",IFERROR(_xlfn.XLOOKUP(F931,SVC_RateCard!A:A,SVC_RateCard!C:C),"")) | K931: =IF(F931="","",IFERROR(_xlfn.XLOOKUP(F931,SVC_RateCard!A:A,SVC_RateCard!I:I),0)) | L931: =IF(OR(J931="",K931=""),"",J931*K931) | M931: =IF(F931="","",IFERROR(_xlfn.XLOOKUP(F931,SVC_RateCard!A:A,SVC_RateCard!G:G),0)) | N931: =IF(L931="","",IFERROR(L931*M931/100,0)) | O931: =IF(L931="","",L931)
A932: =IF(B932="","","SL-"&TEXT(ROW(A928),"00000")) | C932: =IF(B932="","",IFERROR(_xlfn.XLOOKUP(B932,PT_Master!#REF!,PT_Master!B:B),"")) | D932: =IF(C932="","",IFERROR(_xlfn.XLOOKUP(C932,PT_Master!A:A,PT_Master!C:C),"")) | G932: =IF(F932="","",IFERROR(_xlfn.XLOOKUP(F932,SVC_RateCard!A:A,SVC_RateCard!B:B),"Service Code not found")) | H932: =IF(F932="","",IFERROR(_xlfn.XLOOKUP(F932,SVC_RateCard!A:A,SVC_RateCard!C:C),"")) | K932: =IF(F932="","",IFERROR(_xlfn.XLOOKUP(F932,SVC_RateCard!A:A,SVC_RateCard!I:I),0)) | L932: =IF(OR(J932="",K932=""),"",J932*K932) | M932: =IF(F932="","",IFERROR(_xlfn.XLOOKUP(F932,SVC_RateCard!A:A,SVC_RateCard!G:G),0)) | N932: =IF(L932="","",IFERROR(L932*M932/100,0)) | O932: =IF(L932="","",L932)
A933: =IF(B933="","","SL-"&TEXT(ROW(A929),"00000")) | C933: =IF(B933="","",IFERROR(_xlfn.XLOOKUP(B933,PT_Master!#REF!,PT_Master!B:B),"")) | D933: =IF(C933="","",IFERROR(_xlfn.XLOOKUP(C933,PT_Master!A:A,PT_Master!C:C),"")) | G933: =IF(F933="","",IFERROR(_xlfn.XLOOKUP(F933,SVC_RateCard!A:A,SVC_RateCard!B:B),"Service Code not found")) | H933: =IF(F933="","",IFERROR(_xlfn.XLOOKUP(F933,SVC_RateCard!A:A,SVC_RateCard!C:C),"")) | K933: =IF(F933="","",IFERROR(_xlfn.XLOOKUP(F933,SVC_RateCard!A:A,SVC_RateCard!I:I),0)) | L933: =IF(OR(J933="",K933=""),"",J933*K933) | M933: =IF(F933="","",IFERROR(_xlfn.XLOOKUP(F933,SVC_RateCard!A:A,SVC_RateCard!G:G),0)) | N933: =IF(L933="","",IFERROR(L933*M933/100,0)) | O933: =IF(L933="","",L933)
A934: =IF(B934="","","SL-"&TEXT(ROW(A930),"00000")) | C934: =IF(B934="","",IFERROR(_xlfn.XLOOKUP(B934,PT_Master!#REF!,PT_Master!B:B),"")) | D934: =IF(C934="","",IFERROR(_xlfn.XLOOKUP(C934,PT_Master!A:A,PT_Master!C:C),"")) | G934: =IF(F934="","",IFERROR(_xlfn.XLOOKUP(F934,SVC_RateCard!A:A,SVC_RateCard!B:B),"Service Code not found")) | H934: =IF(F934="","",IFERROR(_xlfn.XLOOKUP(F934,SVC_RateCard!A:A,SVC_RateCard!C:C),"")) | K934: =IF(F934="","",IFERROR(_xlfn.XLOOKUP(F934,SVC_RateCard!A:A,SVC_RateCard!I:I),0)) | L934: =IF(OR(J934="",K934=""),"",J934*K934) | M934: =IF(F934="","",IFERROR(_xlfn.XLOOKUP(F934,SVC_RateCard!A:A,SVC_RateCard!G:G),0)) | N934: =IF(L934="","",IFERROR(L934*M934/100,0)) | O934: =IF(L934="","",L934)
A935: =IF(B935="","","SL-"&TEXT(ROW(A931),"00000")) | C935: =IF(B935="","",IFERROR(_xlfn.XLOOKUP(B935,PT_Master!#REF!,PT_Master!B:B),"")) | D935: =IF(C935="","",IFERROR(_xlfn.XLOOKUP(C935,PT_Master!A:A,PT_Master!C:C),"")) | G935: =IF(F935="","",IFERROR(_xlfn.XLOOKUP(F935,SVC_RateCard!A:A,SVC_RateCard!B:B),"Service Code not found")) | H935: =IF(F935="","",IFERROR(_xlfn.XLOOKUP(F935,SVC_RateCard!A:A,SVC_RateCard!C:C),"")) | K935: =IF(F935="","",IFERROR(_xlfn.XLOOKUP(F935,SVC_RateCard!A:A,SVC_RateCard!I:I),0)) | L935: =IF(OR(J935="",K935=""),"",J935*K935) | M935: =IF(F935="","",IFERROR(_xlfn.XLOOKUP(F935,SVC_RateCard!A:A,SVC_RateCard!G:G),0)) | N935: =IF(L935="","",IFERROR(L935*M935/100,0)) | O935: =IF(L935="","",L935)
A936: =IF(B936="","","SL-"&TEXT(ROW(A932),"00000")) | C936: =IF(B936="","",IFERROR(_xlfn.XLOOKUP(B936,PT_Master!#REF!,PT_Master!B:B),"")) | D936: =IF(C936="","",IFERROR(_xlfn.XLOOKUP(C936,PT_Master!A:A,PT_Master!C:C),"")) | G936: =IF(F936="","",IFERROR(_xlfn.XLOOKUP(F936,SVC_RateCard!A:A,SVC_RateCard!B:B),"Service Code not found")) | H936: =IF(F936="","",IFERROR(_xlfn.XLOOKUP(F936,SVC_RateCard!A:A,SVC_RateCard!C:C),"")) | K936: =IF(F936="","",IFERROR(_xlfn.XLOOKUP(F936,SVC_RateCard!A:A,SVC_RateCard!I:I),0)) | L936: =IF(OR(J936="",K936=""),"",J936*K936) | M936: =IF(F936="","",IFERROR(_xlfn.XLOOKUP(F936,SVC_RateCard!A:A,SVC_RateCard!G:G),0)) | N936: =IF(L936="","",IFERROR(L936*M936/100,0)) | O936: =IF(L936="","",L936)
A937: =IF(B937="","","SL-"&TEXT(ROW(A933),"00000")) | C937: =IF(B937="","",IFERROR(_xlfn.XLOOKUP(B937,PT_Master!#REF!,PT_Master!B:B),"")) | D937: =IF(C937="","",IFERROR(_xlfn.XLOOKUP(C937,PT_Master!A:A,PT_Master!C:C),"")) | G937: =IF(F937="","",IFERROR(_xlfn.XLOOKUP(F937,SVC_RateCard!A:A,SVC_RateCard!B:B),"Service Code not found")) | H937: =IF(F937="","",IFERROR(_xlfn.XLOOKUP(F937,SVC_RateCard!A:A,SVC_RateCard!C:C),"")) | K937: =IF(F937="","",IFERROR(_xlfn.XLOOKUP(F937,SVC_RateCard!A:A,SVC_RateCard!I:I),0)) | L937: =IF(OR(J937="",K937=""),"",J937*K937) | M937: =IF(F937="","",IFERROR(_xlfn.XLOOKUP(F937,SVC_RateCard!A:A,SVC_RateCard!G:G),0)) | N937: =IF(L937="","",IFERROR(L937*M937/100,0)) | O937: =IF(L937="","",L937)
A938: =IF(B938="","","SL-"&TEXT(ROW(A934),"00000")) | C938: =IF(B938="","",IFERROR(_xlfn.XLOOKUP(B938,PT_Master!#REF!,PT_Master!B:B),"")) | D938: =IF(C938="","",IFERROR(_xlfn.XLOOKUP(C938,PT_Master!A:A,PT_Master!C:C),"")) | G938: =IF(F938="","",IFERROR(_xlfn.XLOOKUP(F938,SVC_RateCard!A:A,SVC_RateCard!B:B),"Service Code not found")) | H938: =IF(F938="","",IFERROR(_xlfn.XLOOKUP(F938,SVC_RateCard!A:A,SVC_RateCard!C:C),"")) | K938: =IF(F938="","",IFERROR(_xlfn.XLOOKUP(F938,SVC_RateCard!A:A,SVC_RateCard!I:I),0)) | L938: =IF(OR(J938="",K938=""),"",J938*K938) | M938: =IF(F938="","",IFERROR(_xlfn.XLOOKUP(F938,SVC_RateCard!A:A,SVC_RateCard!G:G),0)) | N938: =IF(L938="","",IFERROR(L938*M938/100,0)) | O938: =IF(L938="","",L938)
... A1004: =IF(B1004="","","SL-"&TEXT(ROW(A1000),"00000")) | C1004: =IF(B1004="","",IFERROR(_xlfn.XLOOKUP(B1004,PT_Master!#REF!,PT_Master!B:B),"")) | D1004: =IF(C1004="","",IFERROR(_xlfn.XLOOKUP(C1004,PT_Master!A:A,PT_Master!C:C),"")) | G1004: =IF(F1004="","",IFERROR(_xlfn.XLOOKUP(F1004,SVC_RateCard!A:A,SVC_RateCard!B:B),"Service Code not found")) | H1004: =IF(F1004="","",IFERROR(_xlfn.XLOOKUP(F1004,SVC_RateCard!A:A,SVC_RateCard!C:C),"")) | K1004: =IF(F1004="","",IFERROR(_xlfn.XLOOKUP(F1004,SVC_RateCard!A:A,SVC_RateCard!I:I),0)) | L1004: =IF(OR(J1004="",K1004=""),"",J1004*K1004) | M1004: =IF(F1004="","",IFERROR(_xlfn.XLOOKUP(F1004,SVC_RateCard!A:A,SVC_RateCard!G:G),0)) | N1004: =IF(L1004="","",IFERROR(L1004*M1004/100,0)) | O1004: =IF(L1004="","",L1004)

Sheet BILLING
A2: CityMed Multi-Specialty Hospital — Billing & Invoice
A4: Bill_ID | B4: Admission_ID | C4: Patient_ID | D4: Patient_Name | E4: Bill_Date | F4: Insurance_Provider | G4: Services_Total (₹) | H4: Room_Charges (₹) | I4: Doctor_Charges (₹) | J4: Gross_Ammount (₹) | K4: Discount_Type | L4: Discount_Ammount (₹) | M4: Net_Payable (₹) | N4: Insurance_Claim (₹) | O4: Paitent_Payble (₹) | P4: Payment_Status | Q4: Generated_By | R4: Bill_Month
A5: =IF(B5="","","BILL-"&TEXT(ROW(A1),"00000")) -> BILL-00001 | B5: ADM-00001 | C5: =IF(B5="","",IFERROR(_xlfn.XLOOKUP(B5,ADM_Log!A:A,ADM_Log!B:B),"ADM not found")) -> PT-00001 | D5: =IF(C5="","",IFERROR(_xlfn.XLOOKUP(C5,PT_Master!A:A,PT_Master!C:C),"")) -> Ananya Roy | E5: 19/08/2024 | F5: =IF(C5="","",IFERROR(_xlfn.XLOOKUP(C5,PT_Master!A:A,PT_Master!P:P),"Self-Pay")) -> Care Health Insurance | G5: =IF(B5="","",IFERROR(SUMIF(SVC_Log!B:B,B5,SVC_Log!O:O),0)) -> 2488 | H5: =IF(B5="","",IFERROR( _xlfn.XLOOKUP(B5,ADM_Log!A:A,ADM_Log!G:G)* _xlfn.XLOOKUP(_xlfn.XLOOKUP(B5,ADM_Log!A:A,ADM_Log!K:K),BED_Master!A:A,BED_Master!F:F),0)) -> 0 | I5: =IF(B5="","",IFERROR( IF(_xlfn.XLOOKUP(B5,ADM_Log!A:A,ADM_Log!D:D)="OPD", _xlfn.XLOOKUP(_xlfn.XLOOKUP(B5,ADM_Log!A:A,ADM_Log!I:I),DR_Master!A:A,DR_Master!G:G), _xlfn.XLOOKUP(_xlfn.XLOOKUP(B5,ADM_Log!A:A,ADM_Log!I:I),DR_Master!A:A,DR_Master!H:H)* _xlfn.XLOOKUP(B5,ADM_Log!A:A,ADM_Log!G:G) ),0)) -> 550 | J5: =IF(B5="","",G5+H5+I5) -> 3038 | K5: None | L5: 0 | M5: =IF(J5="","",J5-IF(L5="",0,L5)) -> 3038 | N5: 1282.57 | O5: =IF(M5="","",IFERROR(M5-IF(N5="",0,N5),M5)) -> 1755.43 | P5: Paid | Q5: Billing Clerk | R5: =TEXT(E4,"MMM YYYY") -> Bill_Date
A6: =IF(B6="","","BILL-"&TEXT(ROW(A2),"00000")) -> BILL-00002 | B6: ADM-00002 | C6: =IF(B6="","",IFERROR(_xlfn.XLOOKUP(B6,ADM_Log!A:A,ADM_Log!B:B),"ADM not found")) -> PT-00002 | D6: =IF(C6="","",IFERROR(_xlfn.XLOOKUP(C6,PT_Master!A:A,PT_Master!C:C),"")) -> Rahul Sharma | E6: 19/08/2025 | F6: =IF(C6="","",IFERROR(_xlfn.XLOOKUP(C6,PT_Master!A:A,PT_Master!P:P),"Self-Pay")) -> 0 | G6: =IF(B6="","",IFERROR(SUMIF(SVC_Log!B:B,B6,SVC_Log!O:O),0)) -> 5007.5 | H6: =IF(B6="","",IFERROR( _xlfn.XLOOKUP(B6,ADM_Log!A:A,ADM_Log!G:G)* _xlfn.XLOOKUP(_xlfn.XLOOKUP(B6,ADM_Log!A:A,ADM_Log!K:K),BED_Master!A:A,BED_Master!F:F),0)) -> 0 | I6: =IF(B6="","",IFERROR( IF(_xlfn.XLOOKUP(B6,ADM_Log!A:A,ADM_Log!D:D)="OPD", _xlfn.XLOOKUP(_xlfn.XLOOKUP(B6,ADM_Log!A:A,ADM_Log!I:I),DR_Master!A:A,DR_Master!G:G), _xlfn.XLOOKUP(_xlfn.XLOOKUP(B6,ADM_Log!A:A,ADM_Log!I:I),DR_Master!A:A,DR_Master!H:H)* _xlfn.XLOOKUP(B6,ADM_Log!A:A,ADM_Log!G:G) ),0)) -> 650 | J6: =IF(B6="","",G6+H6+I6) -> 5657.5 | K6: None | L6: 0 | M6: =IF(J6="","",J6-IF(L6="",0,L6)) -> 5657.5 | N6: 0 | O6: =IF(M6="","",IFERROR(M6-IF(N6="",0,N6),M6)) -> 5657.5 | P6: Paid | Q6: Billing Clerk | R6: =TEXT(E5,"MMM YYYY") -> Aug 2024 | U6: =MONTH(BILLING!E5) -> 8
A7: =IF(B7="","","BILL-"&TEXT(ROW(A3),"00000")) -> BILL-00003 | B7: ADM-00003 | C7: =IF(B7="","",IFERROR(_xlfn.XLOOKUP(B7,ADM_Log!A:A,ADM_Log!B:B),"ADM not found")) -> PT-00003 | D7: =IF(C7="","",IFERROR(_xlfn.XLOOKUP(C7,PT_Master!A:A,PT_Master!C:C),"")) -> Priya Mehta | E7: 11/03/2026 | F7: =IF(C7="","",IFERROR(_xlfn.XLOOKUP(C7,PT_Master!A:A,PT_Master!P:P),"Self-Pay")) -> 0 | G7: =IF(B7="","",IFERROR(SUMIF(SVC_Log!B:B,B7,SVC_Log!O:O),0)) -> 1457.5 | H7: =IF(B7="","",IFERROR( _xlfn.XLOOKUP(B7,ADM_Log!A:A,ADM_Log!G:G)* _xlfn.XLOOKUP(_xlfn.XLOOKUP(B7,ADM_Log!A:A,ADM_Log!K:K),BED_Master!A:A,BED_Master!F:F),0)) -> 0 | I7: =IF(B7="","",IFERROR( IF(_xlfn.XLOOKUP(B7,ADM_Log!A:A,ADM_Log!D:D)="OPD", _xlfn.XLOOKUP(_xlfn.XLOOKUP(B7,ADM_Log!A:A,ADM_Log!I:I),DR_Master!A:A,DR_Master!G:G), _xlfn.XLOOKUP(_xlfn.XLOOKUP(B7,ADM_Log!A:A,ADM_Log!I:I),DR_Master!A:A,DR_Master!H:H)* _xlfn.XLOOKUP(B7,ADM_Log!A:A,ADM_Log!G:G) ),0)) -> 500 | J7: =IF(B7="","",G7+H7+I7) -> 1957.5 | K7: None | L7: 0 | M7: =IF(J7="","",J7-IF(L7="",0,L7)) -> 1957.5 | N7: 439.83 | O7: =IF(M7="","",IFERROR(M7-IF(N7="",0,N7),M7)) -> 1517.67 | P7: Insurance Pending | Q7: Billing Clerk | R7: =TEXT(E6,"MMM YYYY") -> Aug 2025
A8: =IF(B8="","","BILL-"&TEXT(ROW(A4),"00000")) -> BILL-00004 | B8: ADM-00004 | C8: =IF(B8="","",IFERROR(_xlfn.XLOOKUP(B8,ADM_Log!A:A,ADM_Log!B:B),"ADM not found")) -> PT-00004 | D8: =IF(C8="","",IFERROR(_xlfn.XLOOKUP(C8,PT_Master!A:A,PT_Master!C:C),"")) -> Debasis Mondal | E8: 29/03/2026 | F8: =IF(C8="","",IFERROR(_xlfn.XLOOKUP(C8,PT_Master!A:A,PT_Master!P:P),"Self-Pay")) -> 0 | G8: =IF(B8="","",IFERROR(SUMIF(SVC_Log!B:B,B8,SVC_Log!O:O),0)) -> 54891.5 | H8: =IF(B8="","",IFERROR( _xlfn.XLOOKUP(B8,ADM_Log!A:A,ADM_Log!G:G)* _xlfn.XLOOKUP(_xlfn.XLOOKUP(B8,ADM_Log!A:A,ADM_Log!K:K),BED_Master!A:A,BED_Master!F:F),0)) -> 0 | I8: =IF(B8="","",IFERROR( IF(_xlfn.XLOOKUP(B8,ADM_Log!A:A,ADM_Log!D:D)="OPD", _xlfn.XLOOKUP(_xlfn.XLOOKUP(B8,ADM_Log!A:A,ADM_Log!I:I),DR_Master!A:A,DR_Master!G:G), _xlfn.XLOOKUP(_xlfn.XLOOKUP(B8,ADM_Log!A:A,ADM_Log!I:I),DR_Master!A:A,DR_Master!H:H)* _xlfn.XLOOKUP(B8,ADM_Log!A:A,ADM_Log!G:G) ),0)) -> 1000 | J8: =IF(B8="","",G8+H8+I8) -> 55891.5 | K8: None | L8: 0 | M8: =IF(J8="","",J8-IF(L8="",0,L8)) -> 55891.5 | N8: 0 | O8: =IF(M8="","",IFERROR(M8-IF(N8="",0,N8),M8)) -> 55891.5 | P8: Partial | Q8: Billing Clerk | R8: =TEXT(E7,"MMM YYYY") -> Mar 2026
A9: =IF(B9="","","BILL-"&TEXT(ROW(A5),"00000")) -> BILL-00005 | B9: ADM-00005 | C9: =IF(B9="","",IFERROR(_xlfn.XLOOKUP(B9,ADM_Log!A:A,ADM_Log!B:B),"ADM not found")) -> PT-00005 | D9: =IF(C9="","",IFERROR(_xlfn.XLOOKUP(C9,PT_Master!A:A,PT_Master!C:C),"")) -> Sneha Das | E9: 15/10/2025 | F9: =IF(C9="","",IFERROR(_xlfn.XLOOKUP(C9,PT_Master!A:A,PT_Master!P:P),"Self-Pay")) -> Bajaj Allianz Health | G9: =IF(B9="","",IFERROR(SUMIF(SVC_Log!B:B,B9,SVC_Log!O:O),0)) -> 6691.5 | H9: =IF(B9="","",IFERROR( _xlfn.XLOOKUP(B9,ADM_Log!A:A,ADM_Log!G:G)* _xlfn.XLOOKUP(_xlfn.XLOOKUP(B9,ADM_Log!A:A,ADM_Log!K:K),BED_Master!A:A,BED_Master!F:F),0)) -> 8800 | I9: =IF(B9="","",IFERROR( IF(_xlfn.XLOOKUP(B9,ADM_Log!A:A,ADM_Log!D:D)="OPD", _xlfn.XLOOKUP(_xlfn.XLOOKUP(B9,ADM_Log!A:A,ADM_Log!I:I),DR_Master!A:A,DR_Master!G:G), _xlfn.XLOOKUP(_xlfn.XLOOKUP(B9,ADM_Log!A:A,ADM_Log!I:I),DR_Master!A:A,DR_Master!H:H)* _xlfn.XLOOKUP(B9,ADM_Log!A:A,ADM_Log!G:G) ),0)) -> 4180 | J9: =IF(B9="","",G9+H9+I9) -> 19671.5 | K9: None | L9: 0 | M9: =IF(J9="","",J9-IF(L9="",0,L9)) -> 19671.5 | N9: 9023.1 | O9: =IF(M9="","",IFERROR(M9-IF(N9="",0,N9),M9)) -> 10648.4 | P9: Partial | Q9: Billing Clerk | R9: =TEXT(E8,"MMM YYYY") -> Mar 2026
A10: =IF(B10="","","BILL-"&TEXT(ROW(A6),"00000")) -> BILL-00006 | B10: ADM-00006 | C10: =IF(B10="","",IFERROR(_xlfn.XLOOKUP(B10,ADM_Log!A:A,ADM_Log!B:B),"ADM not found")) -> PT-00006 | D10: =IF(C10="","",IFERROR(_xlfn.XLOOKUP(C10,PT_Master!A:A,PT_Master!C:C),"")) -> Amit Gupta | E10: 22/01/2026 | F10: =IF(C10="","",IFERROR(_xlfn.XLOOKUP(C10,PT_Master!A:A,PT_Master!P:P),"Self-Pay")) -> 0 | G10: =IF(B10="","",IFERROR(SUMIF(SVC_Log!B:B,B10,SVC_Log!O:O),0)) -> 2809 | H10: =IF(B10="","",IFERROR( _xlfn.XLOOKUP(B10,ADM_Log!A:A,ADM_Log!G:G)* _xlfn.XLOOKUP(_xlfn.XLOOKUP(B10,ADM_Log!A:A,ADM_Log!K:K),BED_Master!A:A,BED_Master!F:F),0)) -> 0 | I10: =IF(B10="","",IFERROR( IF(_xlfn.XLOOKUP(B10,ADM_Log!A:A,ADM_Log!D:D)="OPD", _xlfn.XLOOKUP(_xlfn.XLOOKUP(B10,ADM_Log!A:A,ADM_Log!I:I),DR_Master!A:A,DR_Master!G:G), _xlfn.XLOOKUP(_xlfn.XLOOKUP(B10,ADM_Log!A:A,ADM_Log!I:I),DR_Master!A:A,DR_Master!H:H)* _xlfn.XLOOKUP(B10,ADM_Log!A:A,ADM_Log!G:G) ),0)) -> 1200 | J10: =IF(B10="","",G10+H10+I10) -> 4009 | K10: Insurance Negotiated | L10: 345.04 | M10: =IF(J10="","",J10-IF(L10="",0,L10)) -> 3663.96 | N10: 0 | O10: =IF(M10="","",IFERROR(M10-IF(N10="",0,N10),M10)) -> 3663.96 | P10: Paid | Q10: Billing Clerk | R10: =TEXT(E9,"MMM YYYY") -> Oct 2025
A11: =IF(B11="","","BILL-"&TEXT(ROW(A7),"00000")) -> BILL-00007 | B11: ADM-00007 | C11: =IF(B11="","",IFERROR(_xlfn.XLOOKUP(B11,ADM_Log!A:A,ADM_Log!B:B),"ADM not found")) -> PT-00007 | D11: =IF(C11="","",IFERROR(_xlfn.XLOOKUP(C11,PT_Master!A:A,PT_Master!C:C),"")) -> Kavita Singh | E11: 25/01/2026 | F11: =IF(C11="","",IFERROR(_xlfn.XLOOKUP(C11,PT_Master!A:A,PT_Master!P:P),"Self-Pay")) -> MediAssist TPA | G11: =IF(B11="","",IFERROR(SUMIF(SVC_Log!B:B,B11,SVC_Log!O:O),0)) -> 371255 | H11: =IF(B11="","",IFERROR( _xlfn.XLOOKUP(B11,ADM_Log!A:A,ADM_Log!G:G)* _xlfn.XLOOKUP(_xlfn.XLOOKUP(B11,ADM_Log!A:A,ADM_Log!K:K),BED_Master!A:A,BED_Master!F:F),0)) -> 6400 | I11: =IF(B11="","",IFERROR( IF(_xlfn.XLOOKUP(B11,ADM_Log!A:A,ADM_Log!D:D)="OPD", _xlfn.XLOOKUP(_xlfn.XLOOKUP(B11,ADM_Log!A:A,ADM_Log!I:I),DR_Master!A:A,DR_Master!G:G), _xlfn.XLOOKUP(_xlfn.XLOOKUP(B11,ADM_Log!A:A,ADM_Log!I:I),DR_Master!A:A,DR_Master!H:H)* _xlfn.XLOOKUP(B11,ADM_Log!A:A,ADM_Log!G:G) ),0)) -> 4000 | J11: =IF(B11="","",G11+H11+I11) -> 381655 | K11: None | L11: 0 | M11: =IF(J11="","",J11-IF(L11="",0,L11)) -> 381655 | N11: 234810.94 | O11: =IF(M11="","",IFERROR(M11-IF(N11="",0,N11),M11)) -> 146844.06 | P11: Insurance Pending | Q11: Billing Clerk | R11: =TEXT(E10,"MMM YYYY") -> Jan 2026
A12: =IF(B12="","","BILL-"&TEXT(ROW(A8),"00000")) -> BILL-00008 | B12: ADM-00008 | C12: =IF(B12="","",IFERROR(_xlfn.XLOOKUP(B12,ADM_Log!A:A,ADM_Log!B:B),"ADM not found")) -> PT-00008 | D12: =IF(C12="","",IFERROR(_xlfn.XLOOKUP(C12,PT_Master!A:A,PT_Master!C:C),"")) -> Suresh Chatterjee | E12: 10/09/2025 | F12: =IF(C12="","",IFERROR(_xlfn.XLOOKUP(C12,PT_Master!A:A,PT_Master!P:P),"Self-Pay")) -> 0 | G12: =IF(B12="","",IFERROR(SUMIF(SVC_Log!B:B,B12,SVC_Log!O:O),0)) -> 152592.5 | H12: =IF(B12="","",IFERROR( _xlfn.XLOOKUP(B12,ADM_Log!A:A,ADM_Log!G:G)* _xlfn.XLOOKUP(_xlfn.XLOOKUP(B12,ADM_Log!A:A,ADM_Log!K:K),BED_Master!A:A,BED_Master!F:F),0)) -> 0 | I12: =IF(B12="","",IFERROR( IF(_xlfn.XLOOKUP(B12,ADM_Log!A:A,ADM_Log!D:D)="OPD", _xlfn.XLOOKUP(_xlfn.XLOOKUP(B12,ADM_Log!A:A,ADM_Log!I:I),DR_Master!A:A,DR_Master!G:G), _xlfn.XLOOKUP(_xlfn.XLOOKUP(B12,ADM_Log!A:A,ADM_Log!I:I),DR_Master!A:A,DR_Master!H:H)* _xlfn.XLOOKUP(B12,ADM_Log!A:A,ADM_Log!G:G) ),0)) -> 300 | J12: =IF(B12="","",G12+H12+I12) -> 152892.5 | K12: None | L12: 0 | M12: =IF(J12="","",J12-IF(L12="",0,L12)) -> 152892.5 | N12: 0 | O12: =IF(M12="","",IFERROR(M12-IF(N12="",0,N12),M12)) -> 152892.5 | P12: Unpaid | Q12: Billing Clerk | R12: =TEXT(E11,"MMM YYYY") -> Jan 2026
A13: =IF(B13="","","BILL-"&TEXT(ROW(A9),"00000")) -> BILL-00009 | B13: ADM-00009 | C13: =IF(B13="","",IFERROR(_xlfn.XLOOKUP(B13,ADM_Log!A:A,ADM_Log!B:B),"ADM not found")) -> PT-00009 | D13: =IF(C13="","",IFERROR(_xlfn.XLOOKUP(C13,PT_Master!A:A,PT_Master!C:C),"")) -> Pooja Mukherjee | E13: 25/11/2025 | F13: =IF(C13="","",IFERROR(_xlfn.XLOOKUP(C13,PT_Master!A:A,PT_Master!P:P),"Self-Pay")) -> 0 | G13: =IF(B13="","",IFERROR(SUMIF(SVC_Log!B:B,B13,SVC_Log!O:O),0)) -> 8410 | H13: =IF(B13="","",IFERROR( _xlfn.XLOOKUP(B13,ADM_Log!A:A,ADM_Log!G:G)* _xlfn.XLOOKUP(_xlfn.XLOOKUP(B13,ADM_Log!A:A,ADM_Log!K:K),BED_Master!A:A,BED_Master!F:F),0)) -> 0 | I13: =IF(B13="","",IFERROR( IF(_xlfn.XLOOKUP(B13,ADM_Log!A:A,ADM_Log!D:D)="OPD", _xlfn.XLOOKUP(_xlfn.XLOOKUP(B13,ADM_Log!A:A,ADM_Log!I:I),DR_Master!A:A,DR_Master!G:G), _xlfn.XLOOKUP(_xlfn.XLOOKUP(B13,ADM_Log!A:A,ADM_Log!I:I),DR_Master!A:A,DR_Master!H:H)* _xlfn.XLOOKUP(B13,ADM_Log!A:A,ADM_Log!G:G) ),0)) -> 1200 | J13: =IF(B13="","",G13+H13+I13) -> 9610 | K13: None | L13: 0 | M13: =IF(J13="","",J13-IF(L13="",0,L13)) -> 9610 | N13: 3674.64 | O13: =IF(M13="","",IFERROR(M13-IF(N13="",0,N13),M13)) -> 5935.36 | P13: Partial | Q13: Billing Clerk | R13: =TEXT(E12,"MMM YYYY") -> Sep 2025
A14: =IF(B14="","","BILL-"&TEXT(ROW(A10),"00000")) -> BILL-00010 | B14: ADM-00010 | C14: =IF(B14="","",IFERROR(_xlfn.XLOOKUP(B14,ADM_Log!A:A,ADM_Log!B:B),"ADM not found")) -> PT-00010 | D14: =IF(C14="","",IFERROR(_xlfn.XLOOKUP(C14,PT_Master!A:A,PT_Master!C:C),"")) -> Arjun Bose | E14: 14/02/2026 | F14: =IF(C14="","",IFERROR(_xlfn.XLOOKUP(C14,PT_Master!A:A,PT_Master!P:P),"Self-Pay")) -> 0 | G14: =IF(B14="","",IFERROR(SUMIF(SVC_Log!B:B,B14,SVC_Log!O:O),0)) -> 10355 | H14: =IF(B14="","",IFERROR( _xlfn.XLOOKUP(B14,ADM_Log!A:A,ADM_Log!G:G)* _xlfn.XLOOKUP(_xlfn.XLOOKUP(B14,ADM_Log!A:A,ADM_Log!K:K),BED_Master!A:A,BED_Master!F:F),0)) -> 0 | I14: =IF(B14="","",IFERROR( IF(_xlfn.XLOOKUP(B14,ADM_Log!A:A,ADM_Log!D:D)="OPD", _xlfn.XLOOKUP(_xlfn.XLOOKUP(B14,ADM_Log!A:A,ADM_Log!I:I),DR_Master!A:A,DR_Master!G:G), _xlfn.XLOOKUP(_xlfn.XLOOKUP(B14,ADM_Log!A:A,ADM_Log!I:I),DR_Master!A:A,DR_Master!H:H)* _xlfn.XLOOKUP(B14,ADM_Log!A:A,ADM_Log!G:G) ),0)) -> 800 | J14: =IF(B14="","",G14+H14+I14) -> 11155 | K14: Insurance Negotiated | L14: 784.41 | M14: =IF(J14="","",J14-IF(L14="",0,L14)) -> 10370.59 | N14: 0 | O14: =IF(M14="","",IFERROR(M14-IF(N14="",0,N14),M14)) -> 10370.59 | P14: Partial | Q14: Billing Clerk | R14: =TEXT(E13,"MMM YYYY") -> Nov 2025
A15: =IF(B15="","","BILL-"&TEXT(ROW(A11),"00000")) -> BILL-00011 | B15: ADM-00011 | C15: =IF(B15="","",IFERROR(_xlfn.XLOOKUP(B15,ADM_Log!A:A,ADM_Log!B:B),"ADM not found")) -> PT-00011 | D15: =IF(C15="","",IFERROR(_xlfn.XLOOKUP(C15,PT_Master!A:A,PT_Master!C:C),"")) -> Meena Sen | E15: 12/10/2025 | F15: =IF(C15="","",IFERROR(_xlfn.XLOOKUP(C15,PT_Master!A:A,PT_Master!P:P),"Self-Pay")) -> New India Assurance | G15: =IF(B15="","",IFERROR(SUMIF(SVC_Log!B:B,B15,SVC_Log!O:O),0)) -> 128514.5 | H15: =IF(B15="","",IFERROR( _xlfn.XLOOKUP(B15,ADM_Log!A:A,ADM_Log!G:G)* _xlfn.XLOOKUP(_xlfn.XLOOKUP(B15,ADM_Log!A:A,ADM_Log!K:K),BED_Master!A:A,BED_Master!F:F),0)) -> 0 | I15: =IF(B15="","",IFERROR( IF(_xlfn.XLOOKUP(B15,ADM_Log!A:A,ADM_Log!D:D)="OPD", _xlfn.XLOOKUP(_xlfn.XLOOKUP(B15,ADM_Log!A:A,ADM_Log!I:I),DR_Master!A:A,DR_Master!G:G), _xlfn.XLOOKUP(_xlfn.XLOOKUP(B15,ADM_Log!A:A,ADM_Log!I:I),DR_Master!A:A,DR_Master!H:H)* _xlfn.XLOOKUP(B15,ADM_Log!A:A,ADM_Log!G:G) ),0)) -> 500 | J15: =IF(B15="","",G15+H15+I15) -> 129014.5 | K15: None | L15: 0 | M15: =IF(J15="","",J15-IF(L15="",0,L15)) -> 129014.5 | N15: 71556.44 | O15: =IF(M15="","",IFERROR(M15-IF(N15="",0,N15),M15)) -> 57458.06 | P15: Unpaid | Q15: Billing Clerk | R15: =TEXT(E14,"MMM YYYY") -> Feb 2026
A16: =IF(B16="","","BILL-"&TEXT(ROW(A12),"00000")) -> BILL-00012 | B16: ADM-00012 | C16: =IF(B16="","",IFERROR(_xlfn.XLOOKUP(B16,ADM_Log!A:A,ADM_Log!B:B),"ADM not found")) -> PT-00012 | D16: =IF(C16="","",IFERROR(_xlfn.XLOOKUP(C16,PT_Master!A:A,PT_Master!C:C),"")) -> Vikram Ghosh | E16: 17/08/2025 | F16: =IF(C16="","",IFERROR(_xlfn.XLOOKUP(C16,PT_Master!A:A,PT_Master!P:P),"Self-Pay")) -> 0 | G16: =IF(B16="","",IFERROR(SUMIF(SVC_Log!B:B,B16,SVC_Log!O:O),0)) -> 169927.5 | H16: =IF(B16="","",IFERROR( _xlfn.XLOOKUP(B16,ADM_Log!A:A,ADM_Log!G:G)* _xlfn.XLOOKUP(_xlfn.XLOOKUP(B16,ADM_Log!A:A,ADM_Log!K:K),BED_Master!A:A,BED_Master!F:F),0)) -> 5400 | I16: =IF(B16="","",IFERROR( IF(_xlfn.XLOOKUP(B16,ADM_Log!A:A,ADM_Log!D:D)="OPD", _xlfn.XLOOKUP(_xlfn.XLOOKUP(B16,ADM_Log!A:A,ADM_Log!I:I),DR_Master!A:A,DR_Master!G:G), _xlfn.XLOOKUP(_xlfn.XLOOKUP(B16,ADM_Log!A:A,ADM_Log!I:I),DR_Master!A:A,DR_Master!H:H)* _xlfn.XLOOKUP(B16,ADM_Log!A:A,ADM_Log!G:G) ),0)) -> 1500 | J16: =IF(B16="","",G16+H16+I16) -> 176827.5 | K16: Insurance Negotiated | L16: 8282.76 | M16: =IF(J16="","",J16-IF(L16="",0,L16)) -> 168544.74 | N16: 0 | O16: =IF(M16="","",IFERROR(M16-IF(N16="",0,N16),M16)) -> 168544.74 | P16: Insurance Pending | Q16: Billing Clerk | R16: =TEXT(E15,"MMM YYYY") -> Oct 2025
A17: =IF(B17="","","BILL-"&TEXT(ROW(A13),"00000")) -> BILL-00013 | B17: ADM-00013 | C17: =IF(B17="","",IFERROR(_xlfn.XLOOKUP(B17,ADM_Log!A:A,ADM_Log!B:B),"ADM not found")) -> PT-00013 | D17: =IF(C17="","",IFERROR(_xlfn.XLOOKUP(C17,PT_Master!A:A,PT_Master!C:C),"")) -> Divya Banerjee | E17: 16/02/2026 | F17: =IF(C17="","",IFERROR(_xlfn.XLOOKUP(C17,PT_Master!A:A,PT_Master!P:P),"Self-Pay")) -> Aditya Birla Health | G17: =IF(B17="","",IFERROR(SUMIF(SVC_Log!B:B,B17,SVC_Log!O:O),0)) -> 172930.5 | H17: =IF(B17="","",IFERROR( _xlfn.XLOOKUP(B17,ADM_Log!A:A,ADM_Log!G:G)* _xlfn.XLOOKUP(_xlfn.XLOOKUP(B17,ADM_Log!A:A,ADM_Log!K:K),BED_Master!A:A,BED_Master!F:F),0)) -> 24000 | I17: =IF(B17="","",IFERROR( IF(_xlfn.XLOOKUP(B17,ADM_Log!A:A,ADM_Log!D:D)="OPD", _xlfn.XLOOKUP(_xlfn.XLOOKUP(B17,ADM_Log!A:A,ADM_Log!I:I),DR_Master!A:A,DR_Master!G:G), _xlfn.XLOOKUP(_xlfn.XLOOKUP(B17,ADM_Log!A:A,ADM_Log!I:I),DR_Master!A:A,DR_Master!H:H)* _xlfn.XLOOKUP(B17,ADM_Log!A:A,ADM_Log!G:G) ),0)) -> 1140 | J17: =IF(B17="","",G17+H17+I17) -> 198070.5 | K17: None | L17: 0 | M17: =IF(J17="","",J17-IF(L17="",0,L17)) -> 198070.5 | N17: 127806.95 | O17: =IF(M17="","",IFERROR(M17-IF(N17="",0,N17),M17)) -> 70263.55 | P17: Paid | Q17: Billing Clerk | R17: =TEXT(E16,"MMM YYYY") -> Aug 2025
A18: =IF(B18="","","BILL-"&TEXT(ROW(A14),"00000")) -> BILL-00014 | B18: ADM-00014 | C18: =IF(B18="","",IFERROR(_xlfn.XLOOKUP(B18,ADM_Log!A:A,ADM_Log!B:B),"ADM not found")) -> PT-00014 | D18: =IF(C18="","",IFERROR(_xlfn.XLOOKUP(C18,PT_Master!A:A,PT_Master!C:C),"")) -> Rajan Dey | E18: 01/11/2025 | F18: =IF(C18="","",IFERROR(_xlfn.XLOOKUP(C18,PT_Master!A:A,PT_Master!P:P),"Self-Pay")) -> ICICI Lombard Health | G18: =IF(B18="","",IFERROR(SUMIF(SVC_Log!B:B,B18,SVC_Log!O:O),0)) -> 1587.5 | H18: =IF(B18="","",IFERROR( _xlfn.XLOOKUP(B18,ADM_Log!A:A,ADM_Log!G:G)* _xlfn.XLOOKUP(_xlfn.XLOOKUP(B18,ADM_Log!A:A,ADM_Log!K:K),BED_Master!A:A,BED_Master!F:F),0)) -> 0 | I18: =IF(B18="","",IFERROR( IF(_xlfn.XLOOKUP(B18,ADM_Log!A:A,ADM_Log!D:D)="OPD", _xlfn.XLOOKUP(_xlfn.XLOOKUP(B18,ADM_Log!A:A,ADM_Log!I:I),DR_Master!A:A,DR_Master!G:G), _xlfn.XLOOKUP(_xlfn.XLOOKUP(B18,ADM_Log!A:A,ADM_Log!I:I),DR_Master!A:A,DR_Master!H:H)* _xlfn.XLOOKUP(B18,ADM_Log!A:A,ADM_Log!G:G) ),0)) -> 1200 | J18: =IF(B18="","",G18+H18+I18) -> 2787.5 | K18: Compassionate | L18: 137.09 | M18: =IF(J18="","",J18-IF(L18="",0,L18)) -> 2650.41 | N18: 1507.56 | O18: =IF(M18="","",IFERROR(M18-IF(N18="",0,N18),M18)) -> 1142.85 | P18: Insurance Pending | Q18: Billing Clerk | R18: =TEXT(E17,"MMM YYYY") -> Feb 2026
... A154: =IF(B154="","","BILL-"&TEXT(ROW(A150),"00000")) -> BILL-00150 | B154: ADM-00150 | C154: =IF(B154="","",IFERROR(_xlfn.XLOOKUP(B154,ADM_Log!A:A,ADM_Log!B:B),"ADM not found")) -> PT-00150 | D154: =IF(C154="","",IFERROR(_xlfn.XLOOKUP(C154,PT_Master!A:A,PT_Master!C:C),"")) -> Varun Lahiri | E154: 25/09/2025 | F154: =IF(C154="","",IFERROR(_xlfn.XLOOKUP(C154,PT_Master!A:A,PT_Master!P:P),"Self-Pay")) -> 0 | G154: =IF(B154="","",IFERROR(SUMIF(SVC_Log!B:B,B154,SVC_Log!O:O),0)) -> 1105.5 | H154: =IF(B154="","",IFERROR( _xlfn.XLOOKUP(B154,ADM_Log!A:A,ADM_Log!G:G)* _xlfn.XLOOKUP(_xlfn.XLOOKUP(B154,ADM_Log!A:A,ADM_Log!K:K),BED_Master!A:A,BED_Master!F:F),0)) -> 0 | I154: =IF(B154="","",IFERROR( IF(_xlfn.XLOOKUP(B154,ADM_Log!A:A,ADM_Log!D:D)="OPD", _xlfn.XLOOKUP(_xlfn.XLOOKUP(B154,ADM_Log!A:A,ADM_Log!I:I),DR_Master!A:A,DR_Master!G:G), _xlfn.XLOOKUP(_xlfn.XLOOKUP(B154,ADM_Log!A:A,ADM_Log!I:I),DR_Master!A:A,DR_Master!H:H)* _xlfn.XLOOKUP(B154,ADM_Log!A:A,ADM_Log!G:G) ),0)) -> 550 | J154: =IF(B154="","",G154+H154+I154) -> 1655.5 | K154: None | L154: 0 | M154: =IF(J154="","",J154-IF(L154="",0,L154)) -> 1655.5 | N154: 0 | O154: =IF(M154="","",IFERROR(M154-IF(N154="",0,N154),M154)) -> 1655.5 | P154: Unpaid | Q154: Billing Clerk | R154: =TEXT(E153,"MMM YYYY") -> Mar 2026
A155: =IF(B155="","","BILL-"&TEXT(ROW(A151),"00000")) | C155: =IF(B155="","",IFERROR(_xlfn.XLOOKUP(B155,ADM_Log!A:A,ADM_Log!B:B),"ADM not found")) | D155: =IF(C155="","",IFERROR(_xlfn.XLOOKUP(C155,PT_Master!A:A,PT_Master!C:C),"")) | F155: =IF(C155="","",IFERROR(_xlfn.XLOOKUP(C155,PT_Master!A:A,PT_Master!P:P),"Self-Pay")) | G155: =IF(B155="","",IFERROR(SUMIF(SVC_Log!B:B,B155,SVC_Log!O:O),0)) | H155: =IF(B155="","",IFERROR( _xlfn.XLOOKUP(B155,ADM_Log!A:A,ADM_Log!G:G)* _xlfn.XLOOKUP(_xlfn.XLOOKUP(B155,ADM_Log!A:A,ADM_Log!K:K),BED_Master!A:A,BED_Master!F:F),0)) | I155: =IF(B155="","",IFERROR( IF(_xlfn.XLOOKUP(B155,ADM_Log!A:A,ADM_Log!D:D)="OPD", _xlfn.XLOOKUP(_xlfn.XLOOKUP(B155,ADM_Log!A:A,ADM_Log!I:I),DR_Master!A:A,DR_Master!G:G), _xlfn.XLOOKUP(_xlfn.XLOOKUP(B155,ADM_Log!A:A,ADM_Log!I:I),DR_Master!A:A,DR_Master!H:H)* _xlfn.XLOOKUP(B155,ADM_Log!A:A,ADM_Log!G:G) ),0)) | J155: =IF(B155="","",G155+H155+I155) | M155: =IF(J155="","",J155-IF(L155="",0,L155)) | O155: =IF(M155="","",IFERROR(M155-IF(N155="",0,N155),M155)) | R155: =TEXT(E154,"MMM YYYY") -> Sep 2025
A156: =IF(B156="","","BILL-"&TEXT(ROW(A152),"00000")) | C156: =IF(B156="","",IFERROR(_xlfn.XLOOKUP(B156,ADM_Log!A:A,ADM_Log!B:B),"ADM not found")) | D156: =IF(C156="","",IFERROR(_xlfn.XLOOKUP(C156,PT_Master!A:A,PT_Master!C:C),"")) | F156: =IF(C156="","",IFERROR(_xlfn.XLOOKUP(C156,PT_Master!A:A,PT_Master!P:P),"Self-Pay")) | G156: =IF(B156="","",IFERROR(SUMIF(SVC_Log!B:B,B156,SVC_Log!O:O),0)) | H156: =IF(B156="","",IFERROR( _xlfn.XLOOKUP(B156,ADM_Log!A:A,ADM_Log!G:G)* _xlfn.XLOOKUP(_xlfn.XLOOKUP(B156,ADM_Log!A:A,ADM_Log!K:K),BED_Master!A:A,BED_Master!F:F),0)) | I156: =IF(B156="","",IFERROR( IF(_xlfn.XLOOKUP(B156,ADM_Log!A:A,ADM_Log!D:D)="OPD", _xlfn.XLOOKUP(_xlfn.XLOOKUP(B156,ADM_Log!A:A,ADM_Log!I:I),DR_Master!A:A,DR_Master!G:G), _xlfn.XLOOKUP(_xlfn.XLOOKUP(B156,ADM_Log!A:A,ADM_Log!I:I),DR_Master!A:A,DR_Master!H:H)* _xlfn.XLOOKUP(B156,ADM_Log!A:A,ADM_Log!G:G) ),0)) | J156: =IF(B156="","",G156+H156+I156) | M156: =IF(J156="","",J156-IF(L156="",0,L156)) | O156: =IF(M156="","",IFERROR(M156-IF(N156="",0,N156),M156)) | R156: =TEXT(E155,"MMM YYYY") -> Jan 1900
A157: =IF(B157="","","BILL-"&TEXT(ROW(A153),"00000")) | C157: =IF(B157="","",IFERROR(_xlfn.XLOOKUP(B157,ADM_Log!A:A,ADM_Log!B:B),"ADM not found")) | D157: =IF(C157="","",IFERROR(_xlfn.XLOOKUP(C157,PT_Master!A:A,PT_Master!C:C),"")) | F157: =IF(C157="","",IFERROR(_xlfn.XLOOKUP(C157,PT_Master!A:A,PT_Master!P:P),"Self-Pay")) | G157: =IF(B157="","",IFERROR(SUMIF(SVC_Log!B:B,B157,SVC_Log!O:O),0)) | H157: =IF(B157="","",IFERROR( _xlfn.XLOOKUP(B157,ADM_Log!A:A,ADM_Log!G:G)* _xlfn.XLOOKUP(_xlfn.XLOOKUP(B157,ADM_Log!A:A,ADM_Log!K:K),BED_Master!A:A,BED_Master!F:F),0)) | I157: =IF(B157="","",IFERROR( IF(_xlfn.XLOOKUP(B157,ADM_Log!A:A,ADM_Log!D:D)="OPD", _xlfn.XLOOKUP(_xlfn.XLOOKUP(B157,ADM_Log!A:A,ADM_Log!I:I),DR_Master!A:A,DR_Master!G:G), _xlfn.XLOOKUP(_xlfn.XLOOKUP(B157,ADM_Log!A:A,ADM_Log!I:I),DR_Master!A:A,DR_Master!H:H)* _xlfn.XLOOKUP(B157,ADM_Log!A:A,ADM_Log!G:G) ),0)) | J157: =IF(B157="","",G157+H157+I157) | M157: =IF(J157="","",J157-IF(L157="",0,L157)) | O157: =IF(M157="","",IFERROR(M157-IF(N157="",0,N157),M157)) | R157: =TEXT(E156,"MMM YYYY") -> Jan 1900
A158: =IF(B158="","","BILL-"&TEXT(ROW(A154),"00000")) | C158: =IF(B158="","",IFERROR(_xlfn.XLOOKUP(B158,ADM_Log!A:A,ADM_Log!B:B),"ADM not found")) | D158: =IF(C158="","",IFERROR(_xlfn.XLOOKUP(C158,PT_Master!A:A,PT_Master!C:C),"")) | F158: =IF(C158="","",IFERROR(_xlfn.XLOOKUP(C158,PT_Master!A:A,PT_Master!P:P),"Self-Pay")) | G158: =IF(B158="","",IFERROR(SUMIF(SVC_Log!B:B,B158,SVC_Log!O:O),0)) | H158: =IF(B158="","",IFERROR( _xlfn.XLOOKUP(B158,ADM_Log!A:A,ADM_Log!G:G)* _xlfn.XLOOKUP(_xlfn.XLOOKUP(B158,ADM_Log!A:A,ADM_Log!K:K),BED_Master!A:A,BED_Master!F:F),0)) | I158: =IF(B158="","",IFERROR( IF(_xlfn.XLOOKUP(B158,ADM_Log!A:A,ADM_Log!D:D)="OPD", _xlfn.XLOOKUP(_xlfn.XLOOKUP(B158,ADM_Log!A:A,ADM_Log!I:I),DR_Master!A:A,DR_Master!G:G), _xlfn.XLOOKUP(_xlfn.XLOOKUP(B158,ADM_Log!A:A,ADM_Log!I:I),DR_Master!A:A,DR_Master!H:H)* _xlfn.XLOOKUP(B158,ADM_Log!A:A,ADM_Log!G:G) ),0)) | J158: =IF(B158="","",G158+H158+I158) | M158: =IF(J158="","",J158-IF(L158="",0,L158)) | O158: =IF(M158="","",IFERROR(M158-IF(N158="",0,N158),M158)) | R158: =TEXT(E157,"MMM YYYY") -> Jan 1900
A159: =IF(B159="","","BILL-"&TEXT(ROW(A155),"00000")) | C159: =IF(B159="","",IFERROR(_xlfn.XLOOKUP(B159,ADM_Log!A:A,ADM_Log!B:B),"ADM not found")) | D159: =IF(C159="","",IFERROR(_xlfn.XLOOKUP(C159,PT_Master!A:A,PT_Master!C:C),"")) | F159: =IF(C159="","",IFERROR(_xlfn.XLOOKUP(C159,PT_Master!A:A,PT_Master!P:P),"Self-Pay")) | G159: =IF(B159="","",IFERROR(SUMIF(SVC_Log!B:B,B159,SVC_Log!O:O),0)) | H159: =IF(B159="","",IFERROR( _xlfn.XLOOKUP(B159,ADM_Log!A:A,ADM_Log!G:G)* _xlfn.XLOOKUP(_xlfn.XLOOKUP(B159,ADM_Log!A:A,ADM_Log!K:K),BED_Master!A:A,BED_Master!F:F),0)) | I159: =IF(B159="","",IFERROR( IF(_xlfn.XLOOKUP(B159,ADM_Log!A:A,ADM_Log!D:D)="OPD", _xlfn.XLOOKUP(_xlfn.XLOOKUP(B159,ADM_Log!A:A,ADM_Log!I:I),DR_Master!A:A,DR_Master!G:G), _xlfn.XLOOKUP(_xlfn.XLOOKUP(B159,ADM_Log!A:A,ADM_Log!I:I),DR_Master!A:A,DR_Master!H:H)* _xlfn.XLOOKUP(B159,ADM_Log!A:A,ADM_Log!G:G) ),0)) | J159: =IF(B159="","",G159+H159+I159) | M159: =IF(J159="","",J159-IF(L159="",0,L159)) | O159: =IF(M159="","",IFERROR(M159-IF(N159="",0,N159),M159)) | R159: =TEXT(E158,"MMM YYYY") -> Jan 1900
A160: =IF(B160="","","BILL-"&TEXT(ROW(A156),"00000")) | C160: =IF(B160="","",IFERROR(_xlfn.XLOOKUP(B160,ADM_Log!A:A,ADM_Log!B:B),"ADM not found")) | D160: =IF(C160="","",IFERROR(_xlfn.XLOOKUP(C160,PT_Master!A:A,PT_Master!C:C),"")) | F160: =IF(C160="","",IFERROR(_xlfn.XLOOKUP(C160,PT_Master!A:A,PT_Master!P:P),"Self-Pay")) | G160: =IF(B160="","",IFERROR(SUMIF(SVC_Log!B:B,B160,SVC_Log!O:O),0)) | H160: =IF(B160="","",IFERROR( _xlfn.XLOOKUP(B160,ADM_Log!A:A,ADM_Log!G:G)* _xlfn.XLOOKUP(_xlfn.XLOOKUP(B160,ADM_Log!A:A,ADM_Log!K:K),BED_Master!A:A,BED_Master!F:F),0)) | I160: =IF(B160="","",IFERROR( IF(_xlfn.XLOOKUP(B160,ADM_Log!A:A,ADM_Log!D:D)="OPD", _xlfn.XLOOKUP(_xlfn.XLOOKUP(B160,ADM_Log!A:A,ADM_Log!I:I),DR_Master!A:A,DR_Master!G:G), _xlfn.XLOOKUP(_xlfn.XLOOKUP(B160,ADM_Log!A:A,ADM_Log!I:I),DR_Master!A:A,DR_Master!H:H)* _xlfn.XLOOKUP(B160,ADM_Log!A:A,ADM_Log!G:G) ),0)) | J160: =IF(B160="","",G160+H160+I160) | M160: =IF(J160="","",J160-IF(L160="",0,L160)) | O160: =IF(M160="","",IFERROR(M160-IF(N160="",0,N160),M160)) | R160: =TEXT(E159,"MMM YYYY") -> Jan 1900
A161: =IF(B161="","","BILL-"&TEXT(ROW(A157),"00000")) | C161: =IF(B161="","",IFERROR(_xlfn.XLOOKUP(B161,ADM_Log!A:A,ADM_Log!B:B),"ADM not found")) | D161: =IF(C161="","",IFERROR(_xlfn.XLOOKUP(C161,PT_Master!A:A,PT_Master!C:C),"")) | F161: =IF(C161="","",IFERROR(_xlfn.XLOOKUP(C161,PT_Master!A:A,PT_Master!P:P),"Self-Pay")) | G161: =IF(B161="","",IFERROR(SUMIF(SVC_Log!B:B,B161,SVC_Log!O:O),0)) | H161: =IF(B161="","",IFERROR( _xlfn.XLOOKUP(B161,ADM_Log!A:A,ADM_Log!G:G)* _xlfn.XLOOKUP(_xlfn.XLOOKUP(B161,ADM_Log!A:A,ADM_Log!K:K),BED_Master!A:A,BED_Master!F:F),0)) | I161: =IF(B161="","",IFERROR( IF(_xlfn.XLOOKUP(B161,ADM_Log!A:A,ADM_Log!D:D)="OPD", _xlfn.XLOOKUP(_xlfn.XLOOKUP(B161,ADM_Log!A:A,ADM_Log!I:I),DR_Master!A:A,DR_Master!G:G), _xlfn.XLOOKUP(_xlfn.XLOOKUP(B161,ADM_Log!A:A,ADM_Log!I:I),DR_Master!A:A,DR_Master!H:H)* _xlfn.XLOOKUP(B161,ADM_Log!A:A,ADM_Log!G:G) ),0)) | J161: =IF(B161="","",G161+H161+I161) | M161: =IF(J161="","",J161-IF(L161="",0,L161)) | O161: =IF(M161="","",IFERROR(M161-IF(N161="",0,N161),M161)) | R161: =TEXT(E160,"MMM YYYY") -> Jan 1900
A162: =IF(B162="","","BILL-"&TEXT(ROW(A158),"00000")) | C162: =IF(B162="","",IFERROR(_xlfn.XLOOKUP(B162,ADM_Log!A:A,ADM_Log!B:B),"ADM not found")) | D162: =IF(C162="","",IFERROR(_xlfn.XLOOKUP(C162,PT_Master!A:A,PT_Master!C:C),"")) | F162: =IF(C162="","",IFERROR(_xlfn.XLOOKUP(C162,PT_Master!A:A,PT_Master!P:P),"Self-Pay")) | G162: =IF(B162="","",IFERROR(SUMIF(SVC_Log!B:B,B162,SVC_Log!O:O),0)) | H162: =IF(B162="","",IFERROR( _xlfn.XLOOKUP(B162,ADM_Log!A:A,ADM_Log!G:G)* _xlfn.XLOOKUP(_xlfn.XLOOKUP(B162,ADM_Log!A:A,ADM_Log!K:K),BED_Master!A:A,BED_Master!F:F),0)) | I162: =IF(B162="","",IFERROR( IF(_xlfn.XLOOKUP(B162,ADM_Log!A:A,ADM_Log!D:D)="OPD", _xlfn.XLOOKUP(_xlfn.XLOOKUP(B162,ADM_Log!A:A,ADM_Log!I:I),DR_Master!A:A,DR_Master!G:G), _xlfn.XLOOKUP(_xlfn.XLOOKUP(B162,ADM_Log!A:A,ADM_Log!I:I),DR_Master!A:A,DR_Master!H:H)* _xlfn.XLOOKUP(B162,ADM_Log!A:A,ADM_Log!G:G) ),0)) | J162: =IF(B162="","",G162+H162+I162) | M162: =IF(J162="","",J162-IF(L162="",0,L162)) | O162: =IF(M162="","",IFERROR(M162-IF(N162="",0,N162),M162)) | R162: =TEXT(E161,"MMM YYYY") -> Jan 1900
A163: =IF(B163="","","BILL-"&TEXT(ROW(A159),"00000")) | C163: =IF(B163="","",IFERROR(_xlfn.XLOOKUP(B163,ADM_Log!A:A,ADM_Log!B:B),"ADM not found")) | D163: =IF(C163="","",IFERROR(_xlfn.XLOOKUP(C163,PT_Master!A:A,PT_Master!C:C),"")) | F163: =IF(C163="","",IFERROR(_xlfn.XLOOKUP(C163,PT_Master!A:A,PT_Master!P:P),"Self-Pay")) | G163: =IF(B163="","",IFERROR(SUMIF(SVC_Log!B:B,B163,SVC_Log!O:O),0)) | H163: =IF(B163="","",IFERROR( _xlfn.XLOOKUP(B163,ADM_Log!A:A,ADM_Log!G:G)* _xlfn.XLOOKUP(_xlfn.XLOOKUP(B163,ADM_Log!A:A,ADM_Log!K:K),BED_Master!A:A,BED_Master!F:F),0)) | I163: =IF(B163="","",IFERROR( IF(_xlfn.XLOOKUP(B163,ADM_Log!A:A,ADM_Log!D:D)="OPD", _xlfn.XLOOKUP(_xlfn.XLOOKUP(B163,ADM_Log!A:A,ADM_Log!I:I),DR_Master!A:A,DR_Master!G:G), _xlfn.XLOOKUP(_xlfn.XLOOKUP(B163,ADM_Log!A:A,ADM_Log!I:I),DR_Master!A:A,DR_Master!H:H)* _xlfn.XLOOKUP(B163,ADM_Log!A:A,ADM_Log!G:G) ),0)) | J163: =IF(B163="","",G163+H163+I163) | M163: =IF(J163="","",J163-IF(L163="",0,L163)) | O163: =IF(M163="","",IFERROR(M163-IF(N163="",0,N163),M163)) | R163: =TEXT(E162,"MMM YYYY") -> Jan 1900
A164: =IF(B164="","","BILL-"&TEXT(ROW(A160),"00000")) | C164: =IF(B164="","",IFERROR(_xlfn.XLOOKUP(B164,ADM_Log!A:A,ADM_Log!B:B),"ADM not found")) | D164: =IF(C164="","",IFERROR(_xlfn.XLOOKUP(C164,PT_Master!A:A,PT_Master!C:C),"")) | F164: =IF(C164="","",IFERROR(_xlfn.XLOOKUP(C164,PT_Master!A:A,PT_Master!P:P),"Self-Pay")) | G164: =IF(B164="","",IFERROR(SUMIF(SVC_Log!B:B,B164,SVC_Log!O:O),0)) | H164: =IF(B164="","",IFERROR( _xlfn.XLOOKUP(B164,ADM_Log!A:A,ADM_Log!G:G)* _xlfn.XLOOKUP(_xlfn.XLOOKUP(B164,ADM_Log!A:A,ADM_Log!K:K),BED_Master!A:A,BED_Master!F:F),0)) | I164: =IF(B164="","",IFERROR( IF(_xlfn.XLOOKUP(B164,ADM_Log!A:A,ADM_Log!D:D)="OPD", _xlfn.XLOOKUP(_xlfn.XLOOKUP(B164,ADM_Log!A:A,ADM_Log!I:I),DR_Master!A:A,DR_Master!G:G), _xlfn.XLOOKUP(_xlfn.XLOOKUP(B164,ADM_Log!A:A,ADM_Log!I:I),DR_Master!A:A,DR_Master!H:H)* _xlfn.XLOOKUP(B164,ADM_Log!A:A,ADM_Log!G:G) ),0)) | J164: =IF(B164="","",G164+H164+I164) | M164: =IF(J164="","",J164-IF(L164="",0,L164)) | O164: =IF(M164="","",IFERROR(M164-IF(N164="",0,N164),M164)) | R164: =TEXT(E163,"MMM YYYY") -> Jan 1900
A165: =IF(B165="","","BILL-"&TEXT(ROW(A161),"00000")) | C165: =IF(B165="","",IFERROR(_xlfn.XLOOKUP(B165,ADM_Log!A:A,ADM_Log!B:B),"ADM not found")) | D165: =IF(C165="","",IFERROR(_xlfn.XLOOKUP(C165,PT_Master!A:A,PT_Master!C:C),"")) | F165: =IF(C165="","",IFERROR(_xlfn.XLOOKUP(C165,PT_Master!A:A,PT_Master!P:P),"Self-Pay")) | G165: =IF(B165="","",IFERROR(SUMIF(SVC_Log!B:B,B165,SVC_Log!O:O),0)) | H165: =IF(B165="","",IFERROR( _xlfn.XLOOKUP(B165,ADM_Log!A:A,ADM_Log!G:G)* _xlfn.XLOOKUP(_xlfn.XLOOKUP(B165,ADM_Log!A:A,ADM_Log!K:K),BED_Master!A:A,BED_Master!F:F),0)) | I165: =IF(B165="","",IFERROR( IF(_xlfn.XLOOKUP(B165,ADM_Log!A:A,ADM_Log!D:D)="OPD", _xlfn.XLOOKUP(_xlfn.XLOOKUP(B165,ADM_Log!A:A,ADM_Log!I:I),DR_Master!A:A,DR_Master!G:G), _xlfn.XLOOKUP(_xlfn.XLOOKUP(B165,ADM_Log!A:A,ADM_Log!I:I),DR_Master!A:A,DR_Master!H:H)* _xlfn.XLOOKUP(B165,ADM_Log!A:A,ADM_Log!G:G) ),0)) | J165: =IF(B165="","",G165+H165+I165) | M165: =IF(J165="","",J165-IF(L165="",0,L165)) | O165: =IF(M165="","",IFERROR(M165-IF(N165="",0,N165),M165)) | R165: =TEXT(E164,"MMM YYYY") -> Jan 1900
A166: =IF(B166="","","BILL-"&TEXT(ROW(A162),"00000")) | C166: =IF(B166="","",IFERROR(_xlfn.XLOOKUP(B166,ADM_Log!A:A,ADM_Log!B:B),"ADM not found")) | D166: =IF(C166="","",IFERROR(_xlfn.XLOOKUP(C166,PT_Master!A:A,PT_Master!C:C),"")) | F166: =IF(C166="","",IFERROR(_xlfn.XLOOKUP(C166,PT_Master!A:A,PT_Master!P:P),"Self-Pay")) | G166: =IF(B166="","",IFERROR(SUMIF(SVC_Log!B:B,B166,SVC_Log!O:O),0)) | H166: =IF(B166="","",IFERROR( _xlfn.XLOOKUP(B166,ADM_Log!A:A,ADM_Log!G:G)* _xlfn.XLOOKUP(_xlfn.XLOOKUP(B166,ADM_Log!A:A,ADM_Log!K:K),BED_Master!A:A,BED_Master!F:F),0)) | I166: =IF(B166="","",IFERROR( IF(_xlfn.XLOOKUP(B166,ADM_Log!A:A,ADM_Log!D:D)="OPD", _xlfn.XLOOKUP(_xlfn.XLOOKUP(B166,ADM_Log!A:A,ADM_Log!I:I),DR_Master!A:A,DR_Master!G:G), _xlfn.XLOOKUP(_xlfn.XLOOKUP(B166,ADM_Log!A:A,ADM_Log!I:I),DR_Master!A:A,DR_Master!H:H)* _xlfn.XLOOKUP(B166,ADM_Log!A:A,ADM_Log!G:G) ),0)) | J166: =IF(B166="","",G166+H166+I166) | M166: =IF(J166="","",J166-IF(L166="",0,L166)) | O166: =IF(M166="","",IFERROR(M166-IF(N166="",0,N166),M166)) | R166: =TEXT(E165,"MMM YYYY") -> Jan 1900
... A1004: =IF(B1004="","","BILL-"&TEXT(ROW(A1000),"00000")) | C1004: =IF(B1004="","",IFERROR(_xlfn.XLOOKUP(B1004,ADM_Log!A:A,ADM_Log!B:B),"ADM not found")) | D1004: =IF(C1004="","",IFERROR(_xlfn.XLOOKUP(C1004,PT_Master!A:A,PT_Master!C:C),"")) | F1004: =IF(C1004="","",IFERROR(_xlfn.XLOOKUP(C1004,PT_Master!A:A,PT_Master!P:P),"Self-Pay")) | G1004: =IF(B1004="","",IFERROR(SUMIF(SVC_Log!B:B,B1004,SVC_Log!O:O),0)) | H1004: =IF(B1004="","",IFERROR( _xlfn.XLOOKUP(B1004,ADM_Log!A:A,ADM_Log!G:G)* _xlfn.XLOOKUP(_xlfn.XLOOKUP(B1004,ADM_Log!A:A,ADM_Log!K:K),BED_Master!A:A,BED_Master!F:F),0)) | I1004: =IF(B1004="","",IFERROR( IF(_xlfn.XLOOKUP(B1004,ADM_Log!A:A,ADM_Log!D:D)="OPD", _xlfn.XLOOKUP(_xlfn.XLOOKUP(B1004,ADM_Log!A:A,ADM_Log!I:I),DR_Master!A:A,DR_Master!G:G), _xlfn.XLOOKUP(_xlfn.XLOOKUP(B1004,ADM_Log!A:A,ADM_Log!I:I),DR_Master!A:A,DR_Master!H:H)* _xlfn.XLOOKUP(B1004,ADM_Log!A:A,ADM_Log!G:G) ),0)) | J1004: =IF(B1004="","",G1004+H1004+I1004) | M1004: =IF(J1004="","",J1004-IF(L1004="",0,L1004)) | O1004: =IF(M1004="","",IFERROR(M1004-IF(N1004="",0,N1004),M1004)) | R1004: =TEXT(E1003,"MMM YYYY") -> Jan 1900

Sheet PAYMENTS
A2: Column1 | B2: Column2 | C2: Column3 | D2: Column4 | E2: Column5 | F2: Column6 | G2: Column7 | H2: Column8 | I2: Column9 | J2: Column10 | K2: Column11 | L2: Column12 | M2: Column13
A3: CityMed Multi-Specialty Hospital — Payments & Collections
B4: Total Billed (₹): | C4: =IFERROR(SUM(E6:E2005),0) -> 7790801 | D4: Total Collected (₹): | E4: =IFERROR(SUM(G6:G2005),0) -> 5434705.8 | F4: Total Outstanding (₹): | G4: =IFERROR(SUMIF(J6:J2005,">"&0,J6:J2005),0) -> 2356305.2 | H4: Collection Rate: | I4: =IF(C4=0,"",TEXT(E4/C4,"0.0%")) -> 69.8% | J4: Critical AR (90+ days): | K4: =IFERROR(SUMIF(L6:L2005,"90+ Days",J6:J2005),0) -> 1749114.5
A5: Payment_ID | B5: Bill_ID | C5: Patient_ID | D5: Paitent_Name | E5: Bill_Amount (₹) | F5: Pyment_Date | G5: Amount_Paid (₹) | H5: Payment_Mode | I5: Reference_No | J5: Balance_Due (₹) | K5: AR_Age (Days) | L5: AR_Bucket | M5: Received_By
A6: =IF(B6="","","PAY-"&TEXT(ROW(A1),"00000")) -> PAY-00001 | B6: BILL-00001 | C6: =IF(B6="","",IFERROR(_xlfn.XLOOKUP(B6,BILLING!A:A,BILLING!C:C),"Bill not found")) -> PT-00001 | D6: =IF(C6="","",IFERROR(_xlfn.XLOOKUP(C6,PT_Master!A:A,PT_Master!C:C),"")) -> Ananya Roy | E6: =IF(B6="","",IFERROR(_xlfn.XLOOKUP(B6,BILLING!A:A,BILLING!O:O),0)) -> 1755.43 | F6: 24/03/2026 | G6: 1755.43 | H6: Debit Card | I6: REF26663165 | J6: =IF(B6="","",IFERROR(E6-SUMIF(B$6:B6,B6,G$6:G6),E6)) -> 0 | K6: =IF(B6="","",IFERROR(TODAY()-_xlfn.XLOOKUP(B6,BILLING!A:A,BILLING!E:E),0)) -> 646 | L6: =IF(K6="","",IF(K6<=30,"0-30 Days",IF(K6<=60,"31-60 Days",IF(K6<=90,"61-90 Days","90+ Days")))) -> 90+ Days | M6: Billing Clerk
A7: =IF(B7="","","PAY-"&TEXT(ROW(A3),"00000")) -> PAY-00003 | B7: BILL-00002 | C7: =IF(B7="","",IFERROR(_xlfn.XLOOKUP(B7,BILLING!A:A,BILLING!C:C),"Bill not found")) -> PT-00002 | D7: =IF(C7="","",IFERROR(_xlfn.XLOOKUP(C7,PT_Master!A:A,PT_Master!C:C),"")) -> Rahul Sharma | E7: =IF(B7="","",IFERROR(_xlfn.XLOOKUP(B7,BILLING!A:A,BILLING!O:O),0)) -> 5657.5 | F7: 04/09/2025 | G7: 5657.5 | H7: UPI | I7: REF98476031 | J7: =IF(B7="","",IFERROR(E7-SUMIF(B$6:B7,B7,G$6:G7),E7)) -> 0 | K7: =IF(B7="","",IFERROR(TODAY()-_xlfn.XLOOKUP(B7,BILLING!A:A,BILLING!E:E),0)) -> 281 | L7: =IF(K7="","",IF(K7<=30,"0-30 Days",IF(K7<=60,"31-60 Days",IF(K7<=90,"61-90 Days","90+ Days")))) -> 90+ Days | M7: Billing Clerk
A8: =IF(B8="","","PAY-"&TEXT(ROW(A4),"00000")) -> PAY-00004 | B8: BILL-00003 | C8: =IF(B8="","",IFERROR(_xlfn.XLOOKUP(B8,BILLING!A:A,BILLING!C:C),"Bill not found")) -> PT-00003 | D8: =IF(C8="","",IFERROR(_xlfn.XLOOKUP(C8,PT_Master!A:A,PT_Master!C:C),"")) -> Priya Mehta | E8: =IF(B8="","",IFERROR(_xlfn.XLOOKUP(B8,BILLING!A:A,BILLING!O:O),0)) -> 1517.67 | F8: 28/03/2026 | G8: 332.91 | H8: NEFT/RTGS | I8: REF91917817 | J8: =IF(B8="","",IFERROR(E8-SUMIF(B$6:B8,B8,G$6:G8),E8)) -> 1184.76 | K8: =IF(B8="","",IFERROR(TODAY()-_xlfn.XLOOKUP(B8,BILLING!A:A,BILLING!E:E),0)) -> 77 | L8: =IF(K8="","",IF(K8<=30,"0-30 Days",IF(K8<=60,"31-60 Days",IF(K8<=90,"61-90 Days","90+ Days")))) -> 61-90 Days | M8: Billing Clerk
A9: =IF(B9="","","PAY-"&TEXT(ROW(A5),"00000")) -> PAY-00005 | B9: BILL-00004 | C9: =IF(B9="","",IFERROR(_xlfn.XLOOKUP(B9,BILLING!A:A,BILLING!C:C),"Bill not found")) -> PT-00004 | D9: =IF(C9="","",IFERROR(_xlfn.XLOOKUP(C9,PT_Master!A:A,PT_Master!C:C),"")) -> Debasis Mondal | E9: =IF(B9="","",IFERROR(_xlfn.XLOOKUP(B9,BILLING!A:A,BILLING!O:O),0)) -> 55891.5 | F9: 15/04/2026 | G9: 17008.88 | H9: NEFT/RTGS | I9: REF25974367 | J9: =IF(B9="","",IFERROR(E9-SUMIF(B$6:B9,B9,G$6:G9),E9)) -> 38882.62 | K9: =IF(B9="","",IFERROR(TODAY()-_xlfn.XLOOKUP(B9,BILLING!A:A,BILLING!E:E),0)) -> 59 | L9: =IF(K9="","",IF(K9<=30,"0-30 Days",IF(K9<=60,"31-60 Days",IF(K9<=90,"61-90 Days","90+ Days")))) -> 31-60 Days | M9: Billing Clerk
A10: =IF(B10="","","PAY-"&TEXT(ROW(A6),"00000")) -> PAY-00006 | B10: BILL-00005 | C10: =IF(B10="","",IFERROR(_xlfn.XLOOKUP(B10,BILLING!A:A,BILLING!C:C),"Bill not found")) -> PT-00005 | D10: =IF(C10="","",IFERROR(_xlfn.XLOOKUP(C10,PT_Master!A:A,PT_Master!C:C),"")) -> Sneha Das | E10: =IF(B10="","",IFERROR(_xlfn.XLOOKUP(B10,BILLING!A:A,BILLING!O:O),0)) -> 10648.4 | F10: 05/11/2025 | G10: 3303.93 | H10: Debit Card | I10: REF66174590 | J10: =IF(B10="","",IFERROR(E10-SUMIF(B$6:B10,B10,G$6:G10),E10)) -> 7344.47 | K10: =IF(B10="","",IFERROR(TODAY()-_xlfn.XLOOKUP(B10,BILLING!A:A,BILLING!E:E),0)) -> 224 | L10: =IF(K10="","",IF(K10<=30,"0-30 Days",IF(K10<=60,"31-60 Days",IF(K10<=90,"61-90 Days","90+ Days")))) -> 90+ Days | M10: Billing Clerk
A11: =IF(B11="","","PAY-"&TEXT(ROW(A7),"00000")) -> PAY-00007 | B11: BILL-00006 | C11: =IF(B11="","",IFERROR(_xlfn.XLOOKUP(B11,BILLING!A:A,BILLING!C:C),"Bill not found")) -> PT-00006 | D11: =IF(C11="","",IFERROR(_xlfn.XLOOKUP(C11,PT_Master!A:A,PT_Master!C:C),"")) -> Amit Gupta | E11: =IF(B11="","",IFERROR(_xlfn.XLOOKUP(B11,BILLING!A:A,BILLING!O:O),0)) -> 3663.96 | F11: 11/02/2026 | G11: 3663.96 | H11: NEFT/RTGS | I11: REF75846020 | J11: =IF(B11="","",IFERROR(E11-SUMIF(B$6:B11,B11,G$6:G11),E11)) -> 0 | K11: =IF(B11="","",IFERROR(TODAY()-_xlfn.XLOOKUP(B11,BILLING!A:A,BILLING!E:E),0)) -> 125 | L11: =IF(K11="","",IF(K11<=30,"0-30 Days",IF(K11<=60,"31-60 Days",IF(K11<=90,"61-90 Days","90+ Days")))) -> 90+ Days | M11: Billing Clerk
A12: =IF(B12="","","PAY-"&TEXT(ROW(A8),"00000")) -> PAY-00008 | B12: BILL-00007 | C12: =IF(B12="","",IFERROR(_xlfn.XLOOKUP(B12,BILLING!A:A,BILLING!C:C),"Bill not found")) -> PT-00007 | D12: =IF(C12="","",IFERROR(_xlfn.XLOOKUP(C12,PT_Master!A:A,PT_Master!C:C),"")) -> Kavita Singh | E12: =IF(B12="","",IFERROR(_xlfn.XLOOKUP(B12,BILLING!A:A,BILLING!O:O),0)) -> 146844.06 | F12: 28/01/2026 | G12: 30845.96 | H12: Credit Card | I12: REF72104813 | J12: =IF(B12="","",IFERROR(E12-SUMIF(B$6:B12,B12,G$6:G12),E12)) -> 115998.1 | K12: =IF(B12="","",IFERROR(TODAY()-_xlfn.XLOOKUP(B12,BILLING!A:A,BILLING!E:E),0)) -> 122 | L12: =IF(K12="","",IF(K12<=30,"0-30 Days",IF(K12<=60,"31-60 Days",IF(K12<=90,"61-90 Days","90+ Days")))) -> 90+ Days | M12: Billing Clerk
A13: =IF(B13="","","PAY-"&TEXT(ROW(A9),"00000")) -> PAY-00009 | B13: BILL-00009 | C13: =IF(B13="","",IFERROR(_xlfn.XLOOKUP(B13,BILLING!A:A,BILLING!C:C),"Bill not found")) -> PT-00009 | D13: =IF(C13="","",IFERROR(_xlfn.XLOOKUP(C13,PT_Master!A:A,PT_Master!C:C),"")) -> Pooja Mukherjee | E13: =IF(B13="","",IFERROR(_xlfn.XLOOKUP(B13,BILLING!A:A,BILLING!O:O),0)) -> 5935.36 | F13: 30/11/2025 | G13: 2723.36 | H13: Cash | I13: REF11003060 | J13: =IF(B13="","",IFERROR(E13-SUMIF(B$6:B13,B13,G$6:G13),E13)) -> 3212 | K13: =IF(B13="","",IFERROR(TODAY()-_xlfn.XLOOKUP(B13,BILLING!A:A,BILLING!E:E),0)) -> 183 | L13: =IF(K13="","",IF(K13<=30,"0-30 Days",IF(K13<=60,"31-60 Days",IF(K13<=90,"61-90 Days","90+ Days")))) -> 90+ Days | M13: Billing Clerk
A14: =IF(B14="","","PAY-"&TEXT(ROW(A10),"00000")) -> PAY-00010 | B14: BILL-00010 | C14: =IF(B14="","",IFERROR(_xlfn.XLOOKUP(B14,BILLING!A:A,BILLING!C:C),"Bill not found")) -> PT-00010 | D14: =IF(C14="","",IFERROR(_xlfn.XLOOKUP(C14,PT_Master!A:A,PT_Master!C:C),"")) -> Arjun Bose | E14: =IF(B14="","",IFERROR(_xlfn.XLOOKUP(B14,BILLING!A:A,BILLING!O:O),0)) -> 10370.59 | F14: 21/02/2026 | G14: 4092.82 | H14: NEFT/RTGS | I14: REF85528685 | J14: =IF(B14="","",IFERROR(E14-SUMIF(B$6:B14,B14,G$6:G14),E14)) -> 6277.77 | K14: =IF(B14="","",IFERROR(TODAY()-_xlfn.XLOOKUP(B14,BILLING!A:A,BILLING!E:E),0)) -> 102 | L14: =IF(K14="","",IF(K14<=30,"0-30 Days",IF(K14<=60,"31-60 Days",IF(K14<=90,"61-90 Days","90+ Days")))) -> 90+ Days | M14: Billing Clerk
A15: =IF(B15="","","PAY-"&TEXT(ROW(A11),"00000")) -> PAY-00011 | B15: BILL-00012 | C15: =IF(B15="","",IFERROR(_xlfn.XLOOKUP(B15,BILLING!A:A,BILLING!C:C),"Bill not found")) -> PT-00012 | D15: =IF(C15="","",IFERROR(_xlfn.XLOOKUP(C15,PT_Master!A:A,PT_Master!C:C),"")) -> Vikram Ghosh | E15: =IF(B15="","",IFERROR(_xlfn.XLOOKUP(B15,BILLING!A:A,BILLING!O:O),0)) -> 168544.74 | F15: 08/09/2025 | G15: 44384 | H15: UPI | I15: REF14354152 | J15: =IF(B15="","",IFERROR(E15-SUMIF(B$6:B15,B15,G$6:G15),E15)) -> 124160.74 | K15: =IF(B15="","",IFERROR(TODAY()-_xlfn.XLOOKUP(B15,BILLING!A:A,BILLING!E:E),0)) -> 283 | L15: =IF(K15="","",IF(K15<=30,"0-30 Days",IF(K15<=60,"31-60 Days",IF(K15<=90,"61-90 Days","90+ Days")))) -> 90+ Days | M15: Billing Clerk
A16: =IF(B16="","","PAY-"&TEXT(ROW(A12),"00000")) -> PAY-00012 | B16: BILL-00013 | C16: =IF(B16="","",IFERROR(_xlfn.XLOOKUP(B16,BILLING!A:A,BILLING!C:C),"Bill not found")) -> PT-00013 | D16: =IF(C16="","",IFERROR(_xlfn.XLOOKUP(C16,PT_Master!A:A,PT_Master!C:C),"")) -> Divya Banerjee | E16: =IF(B16="","",IFERROR(_xlfn.XLOOKUP(B16,BILLING!A:A,BILLING!O:O),0)) -> 70263.55 | F16: 05/03/2026 | G16: 70263.55 | H16: Debit Card | I16: REF78054326 | J16: =IF(B16="","",IFERROR(E16-SUMIF(B$6:B16,B16,G$6:G16),E16)) -> 0 | K16: =IF(B16="","",IFERROR(TODAY()-_xlfn.XLOOKUP(B16,BILLING!A:A,BILLING!E:E),0)) -> 100 | L16: =IF(K16="","",IF(K16<=30,"0-30 Days",IF(K16<=60,"31-60 Days",IF(K16<=90,"61-90 Days","90+ Days")))) -> 90+ Days | M16: Billing Clerk
A17: =IF(B17="","","PAY-"&TEXT(ROW(A13),"00000")) -> PAY-00013 | B17: BILL-00014 | C17: =IF(B17="","",IFERROR(_xlfn.XLOOKUP(B17,BILLING!A:A,BILLING!C:C),"Bill not found")) -> PT-00014 | D17: =IF(C17="","",IFERROR(_xlfn.XLOOKUP(C17,PT_Master!A:A,PT_Master!C:C),"")) -> Rajan Dey | E17: =IF(B17="","",IFERROR(_xlfn.XLOOKUP(B17,BILLING!A:A,BILLING!O:O),0)) -> 1142.85 | F17: 22/11/2025 | G17: 156.32 | H17: NEFT/RTGS | I17: REF31954961 | J17: =IF(B17="","",IFERROR(E17-SUMIF(B$6:B17,B17,G$6:G17),E17)) -> 986.53 | K17: =IF(B17="","",IFERROR(TODAY()-_xlfn.XLOOKUP(B17,BILLING!A:A,BILLING!E:E),0)) -> 207 | L17: =IF(K17="","",IF(K17<=30,"0-30 Days",IF(K17<=60,"31-60 Days",IF(K17<=90,"61-90 Days","90+ Days")))) -> 90+ Days | M17: Billing Clerk
A18: =IF(B18="","","PAY-"&TEXT(ROW(A14),"00000")) -> PAY-00014 | B18: BILL-00015 | C18: =IF(B18="","",IFERROR(_xlfn.XLOOKUP(B18,BILLING!A:A,BILLING!C:C),"Bill not found")) -> PT-00015 | D18: =IF(C18="","",IFERROR(_xlfn.XLOOKUP(C18,PT_Master!A:A,PT_Master!C:C),"")) -> Sunita Pal | E18: =IF(B18="","",IFERROR(_xlfn.XLOOKUP(B18,BILLING!A:A,BILLING!O:O),0)) -> 4420.46 | F18: 20/04/2026 | G18: 4420.46 | H18: Debit Card | I18: REF62005457 | J18: =IF(B18="","",IFERROR(E18-SUMIF(B$6:B18,B18,G$6:G18),E18)) -> 0 | K18: =IF(B18="","",IFERROR(TODAY()-_xlfn.XLOOKUP(B18,BILLING!A:A,BILLING!E:E),0)) -> 50 | L18: =IF(K18="","",IF(K18<=30,"0-30 Days",IF(K18<=60,"31-60 Days",IF(K18<=90,"61-90 Days","90+ Days")))) -> 31-60 Days | M18: Billing Clerk
... A137: =IF(B137="","","PAY-"&TEXT(ROW(A133),"00000")) -> PAY-00133 | B137: BILL-00149 | C137: =IF(B137="","",IFERROR(_xlfn.XLOOKUP(B137,BILLING!A:A,BILLING!C:C),"Bill not found")) -> PT-00149 | D137: =IF(C137="","",IFERROR(_xlfn.XLOOKUP(C137,PT_Master!A:A,PT_Master!C:C),"")) -> Seema Chowdhury | E137: =IF(B137="","",IFERROR(_xlfn.XLOOKUP(B137,BILLING!A:A,BILLING!O:O),0)) -> 1984.35 | F137: 02/04/2026 | G137: 1984.35 | H137: Debit Card | I137: REF28413105 | J137: =IF(B137="","",IFERROR(E137-SUMIF(B$6:B137,B137,G$6:G137),E137)) -> 2.2737368e-13 | K137: =IF(B137="","",IFERROR(TODAY()-_xlfn.XLOOKUP(B137,BILLING!A:A,BILLING!E:E),0)) -> 69 | L137: =IF(K137="","",IF(K137<=30,"0-30 Days",IF(K137<=60,"31-60 Days",IF(K137<=90,"61-90 Days","90+ Days")))) -> 61-90 Days | M137: Billing Clerk
A138: =IF(B138="","","PAY-"&TEXT(ROW(A134),"00000")) | C138: =IF(B138="","",IFERROR(_xlfn.XLOOKUP(B138,BILLING!A:A,BILLING!C:C),"Bill not found")) | D138: =IF(C138="","",IFERROR(_xlfn.XLOOKUP(C138,PT_Master!A:A,PT_Master!C:C),"")) | E138: =IF(B138="","",IFERROR(_xlfn.XLOOKUP(B138,BILLING!A:A,BILLING!O:O),0)) | J138: =IF(B138="","",IFERROR(E138-SUMIF(B$6:B138,B138,G$6:G138),E138)) | K138: =IF(B138="","",IFERROR(TODAY()-_xlfn.XLOOKUP(B138,BILLING!A:A,BILLING!E:E),0)) | L138: =IF(K138="","",IF(K138<=30,"0-30 Days",IF(K138<=60,"31-60 Days",IF(K138<=90,"61-90 Days","90+ Days"))))
A139: =IF(B139="","","PAY-"&TEXT(ROW(A135),"00000")) | C139: =IF(B139="","",IFERROR(_xlfn.XLOOKUP(B139,BILLING!A:A,BILLING!C:C),"Bill not found")) | D139: =IF(C139="","",IFERROR(_xlfn.XLOOKUP(C139,PT_Master!A:A,PT_Master!C:C),"")) | E139: =IF(B139="","",IFERROR(_xlfn.XLOOKUP(B139,BILLING!A:A,BILLING!O:O),0)) | J139: =IF(B139="","",IFERROR(E139-SUMIF(B$6:B139,B139,G$6:G139),E139)) | K139: =IF(B139="","",IFERROR(TODAY()-_xlfn.XLOOKUP(B139,BILLING!A:A,BILLING!E:E),0)) | L139: =IF(K139="","",IF(K139<=30,"0-30 Days",IF(K139<=60,"31-60 Days",IF(K139<=90,"61-90 Days","90+ Days"))))
A140: =IF(B140="","","PAY-"&TEXT(ROW(A136),"00000")) | C140: =IF(B140="","",IFERROR(_xlfn.XLOOKUP(B140,BILLING!A:A,BILLING!C:C),"Bill not found")) | D140: =IF(C140="","",IFERROR(_xlfn.XLOOKUP(C140,PT_Master!A:A,PT_Master!C:C),"")) | E140: =IF(B140="","",IFERROR(_xlfn.XLOOKUP(B140,BILLING!A:A,BILLING!O:O),0)) | J140: =IF(B140="","",IFERROR(E140-SUMIF(B$6:B140,B140,G$6:G140),E140)) | K140: =IF(B140="","",IFERROR(TODAY()-_xlfn.XLOOKUP(B140,BILLING!A:A,BILLING!E:E),0)) | L140: =IF(K140="","",IF(K140<=30,"0-30 Days",IF(K140<=60,"31-60 Days",IF(K140<=90,"61-90 Days","90+ Days"))))
A141: =IF(B141="","","PAY-"&TEXT(ROW(A137),"00000")) | C141: =IF(B141="","",IFERROR(_xlfn.XLOOKUP(B141,BILLING!A:A,BILLING!C:C),"Bill not found")) | D141: =IF(C141="","",IFERROR(_xlfn.XLOOKUP(C141,PT_Master!A:A,PT_Master!C:C),"")) | E141: =IF(B141="","",IFERROR(_xlfn.XLOOKUP(B141,BILLING!A:A,BILLING!O:O),0)) | J141: =IF(B141="","",IFERROR(E141-SUMIF(B$6:B141,B141,G$6:G141),E141)) | K141: =IF(B141="","",IFERROR(TODAY()-_xlfn.XLOOKUP(B141,BILLING!A:A,BILLING!E:E),0)) | L141: =IF(K141="","",IF(K141<=30,"0-30 Days",IF(K141<=60,"31-60 Days",IF(K141<=90,"61-90 Days","90+ Days"))))
A142: =IF(B142="","","PAY-"&TEXT(ROW(A138),"00000")) | C142: =IF(B142="","",IFERROR(_xlfn.XLOOKUP(B142,BILLING!A:A,BILLING!C:C),"Bill not found")) | D142: =IF(C142="","",IFERROR(_xlfn.XLOOKUP(C142,PT_Master!A:A,PT_Master!C:C),"")) | E142: =IF(B142="","",IFERROR(_xlfn.XLOOKUP(B142,BILLING!A:A,BILLING!O:O),0)) | J142: =IF(B142="","",IFERROR(E142-SUMIF(B$6:B142,B142,G$6:G142),E142)) | K142: =IF(B142="","",IFERROR(TODAY()-_xlfn.XLOOKUP(B142,BILLING!A:A,BILLING!E:E),0)) | L142: =IF(K142="","",IF(K142<=30,"0-30 Days",IF(K142<=60,"31-60 Days",IF(K142<=90,"61-90 Days","90+ Days"))))
A143: =IF(B143="","","PAY-"&TEXT(ROW(A139),"00000")) | C143: =IF(B143="","",IFERROR(_xlfn.XLOOKUP(B143,BILLING!A:A,BILLING!C:C),"Bill not found")) | D143: =IF(C143="","",IFERROR(_xlfn.XLOOKUP(C143,PT_Master!A:A,PT_Master!C:C),"")) | E143: =IF(B143="","",IFERROR(_xlfn.XLOOKUP(B143,BILLING!A:A,BILLING!O:O),0)) | J143: =IF(B143="","",IFERROR(E143-SUMIF(B$6:B143,B143,G$6:G143),E143)) | K143: =IF(B143="","",IFERROR(TODAY()-_xlfn.XLOOKUP(B143,BILLING!A:A,BILLING!E:E),0)) | L143: =IF(K143="","",IF(K143<=30,"0-30 Days",IF(K143<=60,"31-60 Days",IF(K143<=90,"61-90 Days","90+ Days"))))
A144: =IF(B144="","","PAY-"&TEXT(ROW(A140),"00000")) | C144: =IF(B144="","",IFERROR(_xlfn.XLOOKUP(B144,BILLING!A:A,BILLING!C:C),"Bill not found")) | D144: =IF(C144="","",IFERROR(_xlfn.XLOOKUP(C144,PT_Master!A:A,PT_Master!C:C),"")) | E144: =IF(B144="","",IFERROR(_xlfn.XLOOKUP(B144,BILLING!A:A,BILLING!O:O),0)) | J144: =IF(B144="","",IFERROR(E144-SUMIF(B$6:B144,B144,G$6:G144),E144)) | K144: =IF(B144="","",IFERROR(TODAY()-_xlfn.XLOOKUP(B144,BILLING!A:A,BILLING!E:E),0)) | L144: =IF(K144="","",IF(K144<=30,"0-30 Days",IF(K144<=60,"31-60 Days",IF(K144<=90,"61-90 Days","90+ Days"))))
A145: =IF(B145="","","PAY-"&TEXT(ROW(A141),"00000")) | C145: =IF(B145="","",IFERROR(_xlfn.XLOOKUP(B145,BILLING!A:A,BILLING!C:C),"Bill not found")) | D145: =IF(C145="","",IFERROR(_xlfn.XLOOKUP(C145,PT_Master!A:A,PT_Master!C:C),"")) | E145: =IF(B145="","",IFERROR(_xlfn.XLOOKUP(B145,BILLING!A:A,BILLING!O:O),0)) | J145: =IF(B145="","",IFERROR(E145-SUMIF(B$6:B145,B145,G$6:G145),E145)) | K145: =IF(B145="","",IFERROR(TODAY()-_xlfn.XLOOKUP(B145,BILLING!A:A,BILLING!E:E),0)) | L145: =IF(K145="","",IF(K145<=30,"0-30 Days",IF(K145<=60,"31-60 Days",IF(K145<=90,"61-90 Days","90+ Days"))))
A146: =IF(B146="","","PAY-"&TEXT(ROW(A142),"00000")) | C146: =IF(B146="","",IFERROR(_xlfn.XLOOKUP(B146,BILLING!A:A,BILLING!C:C),"Bill not found")) | D146: =IF(C146="","",IFERROR(_xlfn.XLOOKUP(C146,PT_Master!A:A,PT_Master!C:C),"")) | E146: =IF(B146="","",IFERROR(_xlfn.XLOOKUP(B146,BILLING!A:A,BILLING!O:O),0)) | J146: =IF(B146="","",IFERROR(E146-SUMIF(B$6:B146,B146,G$6:G146),E146)) | K146: =IF(B146="","",IFERROR(TODAY()-_xlfn.XLOOKUP(B146,BILLING!A:A,BILLING!E:E),0)) | L146: =IF(K146="","",IF(K146<=30,"0-30 Days",IF(K146<=60,"31-60 Days",IF(K146<=90,"61-90 Days","90+ Days"))))
A147: =IF(B147="","","PAY-"&TEXT(ROW(A143),"00000")) | C147: =IF(B147="","",IFERROR(_xlfn.XLOOKUP(B147,BILLING!A:A,BILLING!C:C),"Bill not found")) | D147: =IF(C147="","",IFERROR(_xlfn.XLOOKUP(C147,PT_Master!A:A,PT_Master!C:C),"")) | E147: =IF(B147="","",IFERROR(_xlfn.XLOOKUP(B147,BILLING!A:A,BILLING!O:O),0)) | J147: =IF(B147="","",IFERROR(E147-SUMIF(B$6:B147,B147,G$6:G147),E147)) | K147: =IF(B147="","",IFERROR(TODAY()-_xlfn.XLOOKUP(B147,BILLING!A:A,BILLING!E:E),0)) | L147: =IF(K147="","",IF(K147<=30,"0-30 Days",IF(K147<=60,"31-60 Days",IF(K147<=90,"61-90 Days","90+ Days"))))
A148: =IF(B148="","","PAY-"&TEXT(ROW(A144),"00000")) | C148: =IF(B148="","",IFERROR(_xlfn.XLOOKUP(B148,BILLING!A:A,BILLING!C:C),"Bill not found")) | D148: =IF(C148="","",IFERROR(_xlfn.XLOOKUP(C148,PT_Master!A:A,PT_Master!C:C),"")) | E148: =IF(B148="","",IFERROR(_xlfn.XLOOKUP(B148,BILLING!A:A,BILLING!O:O),0)) | J148: =IF(B148="","",IFERROR(E148-SUMIF(B$6:B148,B148,G$6:G148),E148)) | K148: =IF(B148="","",IFERROR(TODAY()-_xlfn.XLOOKUP(B148,BILLING!A:A,BILLING!E:E),0)) | L148: =IF(K148="","",IF(K148<=30,"0-30 Days",IF(K148<=60,"31-60 Days",IF(K148<=90,"61-90 Days","90+ Days"))))
A149: =IF(B149="","","PAY-"&TEXT(ROW(A145),"00000")) | C149: =IF(B149="","",IFERROR(_xlfn.XLOOKUP(B149,BILLING!A:A,BILLING!C:C),"Bill not found")) | D149: =IF(C149="","",IFERROR(_xlfn.XLOOKUP(C149,PT_Master!A:A,PT_Master!C:C),"")) | E149: =IF(B149="","",IFERROR(_xlfn.XLOOKUP(B149,BILLING!A:A,BILLING!O:O),0)) | J149: =IF(B149="","",IFERROR(E149-SUMIF(B$6:B149,B149,G$6:G149),E149)) | K149: =IF(B149="","",IFERROR(TODAY()-_xlfn.XLOOKUP(B149,BILLING!A:A,BILLING!E:E),0)) | L149: =IF(K149="","",IF(K149<=30,"0-30 Days",IF(K149<=60,"31-60 Days",IF(K149<=90,"61-90 Days","90+ Days"))))
... A995: =IF(B995="","","PAY-"&TEXT(ROW(A991),"00000")) | C995: =IF(B995="","",IFERROR(_xlfn.XLOOKUP(B995,BILLING!A:A,BILLING!C:C),"Bill not found")) | D995: =IF(C995="","",IFERROR(_xlfn.XLOOKUP(C995,PT_Master!A:A,PT_Master!C:C),"")) | E995: =IF(B995="","",IFERROR(_xlfn.XLOOKUP(B995,BILLING!A:A,BILLING!O:O),0)) | J995: =IF(B995="","",IFERROR(E995-SUMIF(B$6:B995,B995,G$6:G995),E995)) | K995: =IF(B995="","",IFERROR(TODAY()-_xlfn.XLOOKUP(B995,BILLING!A:A,BILLING!E:E),0)) | L995: =IF(K995="","",IF(K995<=30,"0-30 Days",IF(K995<=60,"31-60 Days",IF(K995<=90,"61-90 Days","90+ Days"))))
A996: =IF(B996="","","PAY-"&TEXT(ROW(A992),"00000")) | C996: =IF(B996="","",IFERROR(_xlfn.XLOOKUP(B996,BILLING!A:A,BILLING!C:C),"Bill not found")) | D996: =IF(C996="","",IFERROR(_xlfn.XLOOKUP(C996,PT_Master!A:A,PT_Master!C:C),"")) | E996: =IF(B996="","",IFERROR(_xlfn.XLOOKUP(B996,BILLING!A:A,BILLING!O:O),0)) | J996: =IF(B996="","",IFERROR(E996-SUMIF(B$6:B996,B996,G$6:G996),E996))
A997: =IF(B997="","","PAY-"&TEXT(ROW(A993),"00000")) | C997: =IF(B997="","",IFERROR(_xlfn.XLOOKUP(B997,BILLING!A:A,BILLING!C:C),"Bill not found")) | D997: =IF(C997="","",IFERROR(_xlfn.XLOOKUP(C997,PT_Master!A:A,PT_Master!C:C),"")) | E997: =IF(B997="","",IFERROR(_xlfn.XLOOKUP(B997,BILLING!A:A,BILLING!O:O),0)) | J997: =IF(B997="","",IFERROR(E997-SUMIF(B$6:B997,B997,G$6:G997),E997)) | L997: =IF(K997="","",IF(K997<=30,"0-30 Days",IF(K997<=60,"31-60 Days",IF(K997<=90,"61-90 Days","90+ Days"))))
A998: =IF(B998="","","PAY-"&TEXT(ROW(A994),"00000")) | C998: =IF(B998="","",IFERROR(_xlfn.XLOOKUP(B998,BILLING!A:A,BILLING!C:C),"Bill not found")) | D998: =IF(C998="","",IFERROR(_xlfn.XLOOKUP(C998,PT_Master!A:A,PT_Master!C:C),"")) | E998: =IF(B998="","",IFERROR(_xlfn.XLOOKUP(B998,BILLING!A:A,BILLING!O:O),0)) | J998: =IF(B998="","",IFERROR(E998-SUMIF(B$6:B998,B998,G$6:G998),E998)) | K998: =IF(B998="","",IFERROR(TODAY()-_xlfn.XLOOKUP(B998,BILLING!A:A,BILLING!E:E),0)) | L998: =IF(K998="","",IF(K998<=30,"0-30 Days",IF(K998<=60,"31-60 Days",IF(K998<=90,"61-90 Days","90+ Days"))))
A999: =IF(B999="","","PAY-"&TEXT(ROW(A995),"00000")) | C999: =IF(B999="","",IFERROR(_xlfn.XLOOKUP(B999,BILLING!A:A,BILLING!C:C),"Bill not found")) | D999: =IF(C999="","",IFERROR(_xlfn.XLOOKUP(C999,PT_Master!A:A,PT_Master!C:C),"")) | E999: =IF(B999="","",IFERROR(_xlfn.XLOOKUP(B999,BILLING!A:A,BILLING!O:O),0)) | J999: =IF(B999="","",IFERROR(E999-SUMIF(B$6:B999,B999,G$6:G999),E999)) | K999: =IF(B999="","",IFERROR(TODAY()-_xlfn.XLOOKUP(B999,BILLING!A:A,BILLING!E:E),0)) | L999: =IF(K999="","",IF(K999<=30,"0-30 Days",IF(K999<=60,"31-60 Days",IF(K999<=90,"61-90 Days","90+ Days"))))
